Workbook

Sheet Navigation Key
A1: Page Navigation Key
A2: Page Type | B2: Page Color
A3: Information
A4: Parameters and Results
A5: Configuration - Traditional Onsite
A6: Configuration - Local Modular
A7: Configuration - Multi-Market Modular
A8: Sources and Calculations
A10: Cell Highlight Color
A11: Highlight Meaning | B11: Cell Color
A12: Modifiable Parameters

Sheet Model Information
A1: Supply Chain Configurations
A26: Summary of Model Calculations
A27: National Average (Traditional vs Local): 1. Itemized home construction to assembly process level 2. Used national average housing cost per square feet (source: NAHB) and average time (source: approximation from 2025 Capstone) for site built construction as benchmark 3. Estimated % of total cost for material vs labor (source: approximation) 4. Estimated % of total time per assembly process (source: 2025 Capstone and approximation) 5. Based on traditional, site-built as a benchmark, calculated cost and time % savings from local offsite construction (source: estimated % savings from public reports and approximation) 6. Compared cost results between traditional, site built and local, offsite housing based on national average Regional (Traditional vs Local): 7. Followed steps 2-5 at the regional level (Salt Lake City, UT and Los Angeles, CA) 8. Compare cost results between traditional, site built and local, off site housing for both markets separately Multi-Market : 9. Modular: multi-market factory in SLC shipping modules locally to SLC and distant to LA -- Use SLC material and labor costs with % savings from economies of scale (also account for larger facility = higher fixed costs). Production sq ft cost same for every module out of SLC facility, transportation cost per sq ft differs to each market --- SLC customers: Calculate transportation costs of modules to SLC local customers --- LA customers: Calculate transportation costs of modules to LA distant customers 10. Hybrid Scenario 1: multi-market hybrid factory in SLC shipping modules locally to SLC and shipping panels to local modular factory near LA which ships modules locally to LA customers -- Determine assembly processes to be done in hybrid SLC factory. Use SLC material and labor costs with % savings from economies of scale of shared processes (also account for larger facility = higher fixed costs). Production sq ft cost differ for modules, transportation cost per sq ft differs for each market --- SLC customers: Calculate transportation costs of modules to SLC local customers --- LA customers: Calculate transportation cost of panels from SLC hybrid facility to LA local modular facility. Use LA material and labor costs for localized processes. Calculate transportation cost of shipping modules from LA local modular facility to local LA customers 11. Hybrid Scenario 2: multi-market hybrid factory in SLC shipping panels to local modular factory in SLC which ships modules locally to SLC customers and shipping panels to local modular factory near LA which ships modules locally to LA customers -- Determine assembly processes to be done in hybrid SLC factory. Use SLC material and labor costs with % savings from economies of scale of shared processes (also account for larger facility = higher fixed costs). Production sq ft cost different for modules, transportation cost per sq ft differs to each market --- SLC customers: Calculate transportation cost of panels from SLC hybrid facility to SLC local modular facility. Use SLC material and labor costs for localized processes. Calculate transportation cost of shipping modules from SLC local modular facility to local customers --- LA customers: Calculate transportation cost of panels from SLC hybrid facility to LA local modular facility. Use LA material and labor costs for localized processes. Calculate transportation cost of shipping modules from LA local modular facility to local customers 12. Compare cost results between the three different multi-market scenarios

Sheet Overall Results
A1: Modular
A2: Manufacturing Strategy | B2: Market Location | C2: Construction Cost | D2: Other Costs | E2: Fixed Costs | F2: Profit | G2: Total Selling Price | H2: Profit % | I2: Construction Cost Savings % | K2: Check | M2: Unit of measure* | N2: Notes
A3: Site Built | B3: Salt Lake City | C3: ='SLC - Site Built'!B34 -> 150 | D3: ='SLC - Site Built'!B35 -> 57.763623 | E3: 0 | F3: ='SLC - Site Built'!B36 -> 25.683945 | G3: ='SLC - Site Built'!B37 -> 233.44757 | H3: =F3/G3 -> 0.11002019 | I3: 0 | K3: =F3-(G3-SUM(C3:E3)) -> 0 | M3: ='Parameter Adjustment'!Z2 -> Square foot | N3: *Go to parameter adjustment page to move
A4: Local | B4: Salt Lake City | C4: ='SLC - Local'!B32 -> 139.595 | D4: ='SLC - Local'!B33 -> 57.763623 | E4: ='SLC - Local'!B34 -> 19.152 | F4: ='SLC - Local'!B35 -> 16.936945 | G4: ='SLC - Local'!B36 -> 233.44757 | H4: =F4/G4 -> 0.07255139 | I4: =(C4-$C$3)/$C$3 -> -0.069366667 | K4: =F4-(G4-SUM(C4:E4)) -> -2.8421709e-14
A5: Multi-Market Modular | B5: Salt Lake City | C5: ='Multi-Market Modular'!B34 -> 128.57 | D5: ='Multi-Market Modular'!B35 -> 57.763623 | E5: ='Multi-Market Modular'!B36 -> 19.152 | F5: ='Multi-Market Modular'!B37 -> 27.961945 | G5: ='Multi-Market Modular'!B38 -> 233.44757 | H5: =F5/G5 -> 0.11977827 | I5: =(C5-$C$3)/$C$3 -> -0.14286667 | K5: =F5-(G5-SUM(C5:E5)) -> -2.8421709e-14
A6: Site Built | B6: Los Angeles | C6: ='LA - Site Built'!B34 -> 320 | D6: ='LA - Site Built'!B35 -> 123.22906 | E6: 0 | F6: ='LA - Site Built'!B36 -> 54.792417 | G6: ='LA - Site Built'!B37 -> 498.02148 | H6: =F6/G6 -> 0.11002019 | K6: =F6-(G6-SUM(C6:E6)) -> 0
A7: Local | B7: Los Angeles | C7: ='LA - Local'!B34 -> 285.676 | D7: ='LA - Local'!B35 -> 123.22906 | E7: ='LA - Local'!B36 -> 32.048 | F7: ='LA - Local'!B37 -> 57.068417 | G7: ='LA - Local'!B38 -> 498.02148 | H7: =F7/G7 -> 0.11459027 | I7: =(C7-$C$6)/$C$6 -> -0.1072625 | K7: =F7-(G7-SUM(C7:E7)) -> 0
A8: Multi-Market Modular | B8: Los Angeles | C8: ='Multi-Market Modular'!C34 -> 168.9525 | D8: ='Multi-Market Modular'!C35 -> 123.22906 | E8: ='Multi-Market Modular'!C36 -> 19.152 | F8: ='Multi-Market Modular'!C37 -> 186.68792 | G8: ='Multi-Market Modular'!C38 -> 498.02148 | H8: =F8/G8 -> 0.37485917 | I8: =(C8-$C$6)/$C$6 -> -0.47202344 | K8: =F8-(G8-SUM(C8:E8)) -> 0
A10: Hybrid
A11: Manufacturing Strategy | B11: Market Location | C11: Construction Cost | D11: Other Costs | E11: Fixed Costs | F11: Profit | G11: Total Selling Price | H11: Profit % | I11: Construction Cost Savings %
A12: Site Built | B12: Salt Lake City | C12: ='SLC - Site Built'!B34 -> 150 | D12: ='SLC - Site Built'!B35 -> 57.763623 | E12: 0 | F12: ='SLC - Site Built'!B36 -> 25.683945 | G12: ='SLC - Site Built'!B37 -> 233.44757 | H12: =F12/G12 -> 0.11002019 | I12: 0 | K12: =F12-(G12-SUM(C12:E12)) -> 0
A13: Multi-Market Hybrid 1 | B13: Salt Lake City | C13: ='Multi-Market Hybrid 1'!B34 -> 131.045 | D13: ='Multi-Market Hybrid 1'!B35 -> 57.763623 | E13: ='Multi-Market Hybrid 1'!B36 -> 38.304 | F13: ='Multi-Market Hybrid 1'!B37 -> 6.3349455 | G13: ='Multi-Market Hybrid 1'!B38 -> 233.44757 | H13: =F13/G13 -> 0.027136481 | I13: =(C13-$C$12)/$C$12 -> -0.12636667 | K13: =F13-(G13-SUM(C13:E13)) -> -1.4210855e-14
A14: Multi-Market Hybrid 2 | B14: Salt Lake City | C14: ='Multi-Market Hybrid 2'!B34 -> 133.67 | D14: ='Multi-Market Hybrid 2'!B35 -> 57.763623 | E14: ='Multi-Market Hybrid 2'!B36 -> 28.728 | F14: ='Multi-Market Hybrid 2'!B37 -> 13.285945 | G14: ='Multi-Market Hybrid 2'!B38 -> 233.44757 | H14: =F14/G14 -> 0.056911903 | I14: =(C14-$C$12)/$C$12 -> -0.10886667 | K14: =F14-(G14-SUM(C14:E14)) -> 2.1316282e-14
A15: Site Built | B15: Los Angeles | C15: ='LA - Site Built'!B34 -> 320 | D15: ='LA - Site Built'!B35 -> 123.22906 | E15: 0 | F15: ='LA - Site Built'!B36 -> 54.792417 | G15: ='LA - Site Built'!B37 -> 498.02148 | H15: =F15/G15 -> 0.11002019 | I15: 0 | K15: =F15-(G15-SUM(C15:E15)) -> 0
A16: Multi-Market Hybrid 1 | B16: Los Angeles | C16: ='Multi-Market Hybrid 1'!C34 -> 219.308 | D16: ='Multi-Market Hybrid 1'!C35 -> 123.22906 | E16: ='Multi-Market Hybrid 1'!C36 -> 51.2 | F16: ='Multi-Market Hybrid 1'!C37 -> 104.28442 | G16: ='Multi-Market Hybrid 1'!C38 -> 498.02148 | H16: =F16/G16 -> 0.20939743 | I16: =(C16-$C$15)/$C$15 -> -0.3146625 | K16: =F16-(G16-SUM(C16:E16)) -> 0
A17: Multi-Market Hybrid 2 | B17: Los Angeles | C17: ='Multi-Market Hybrid 2'!C34 -> 219.308 | D17: ='Multi-Market Hybrid 2'!C35 -> 123.22906 | E17: ='Multi-Market Hybrid 2'!C36 -> 41.624 | F17: ='Multi-Market Hybrid 2'!C37 -> 113.86042 | G17: ='Multi-Market Hybrid 2'!C38 -> 498.02148 | H17: =F17/G17 -> 0.22862551 | I17: =(C17-$C$15)/$C$15 -> -0.3146625 | K17: =F17-(G17-SUM(C17:E17)) -> 0

Sheet Parameter Adjustment
A1: Site Built - Process Percentage Allocation | F1: Economies of Scale (Eos) Savings | L1: Notes | N1: =Z2 -> Square foot | P1: Site Built Time (days) | R1: Modular Transportation Costs | W1: On-site Installation Cost | Z1: Select Unit Of Measure | AB1: Cost per Sqft | AE1: Facility Fixed Costs
A2: Construction Process | B2: % Material Cost | C2: % Labor Cost | D2: % of Total Cost | E2: % of Total Time | F2: LOCAL % Cost Savings (Modular) | G2: LOCAL % Time Savings (Modular) | H2: MULTI-MARKET LOCAL % Cost Savings (Modular) | I2: MULTI-MARKET LOCAL % Time Savings (Modular) | J2: MULTI-MARKET CENTRAL % Cost Savings (Hybrid) | K2: MULTI-MARKET HYBRID % Time Savings (Hybrid) | L2: NAHB Category Reference (% of Total Cost) | P2: 210 | R2: Type | S2: Cost Per Mile | T2: Distance (miles) | U2: Inter-state Permit ($100/state) | W2: Sqft | X2: 1000 | Z2: Square foot | AB2: Market | AC2: Value | AE2: Facility Location | AF2: Configuration | AG2: 1-Yr Lease | AH2: Equipment | AI2: Total Fixed Costs per Year | AJ2: Modular Fixed Costs/Sqft | AK2: Panel Fixed Costs/Sqft
A3: Site Work | B3: 0.6 | C3: 0.4 | D3: 0.076 | E3: 0.10810811 | F3: 0 | G3: 1 | H3: 0 | I3: 1 | J3: 0 | K3: 1 | L3: NAHB (Site Work) | N3: NA Site Built Cost | R3: Local (SLC) | S3: 14 | T3: 50 | W3: $/Sqft | X3: 10 | AB3: Los Angeles | AC3: 320 | AE3: Los Angeles | AF3: Local | AG3: {=_xlfn.IFS(AND(AE3="Los Angeles",AF3="Local"),$AF$11*$AF$16,AND(AE3="Salt Lake City",AF3="Local"),$AF$11*$AF$17,AND(AE3="Salt Lake City",AF3=OR("Multi-Market Modular","Multi-Market Hybrid")),$AF$12*$AF$17)} -> 951500 | AH3: =IF(AF3="Local",$AF$29, $AF$30) -> 50000 | AI3: =AG3+AH3 -> 1001500 | AJ3: =$AI3/AG21 -> 32.048 | AK3: =$AI3/AH21 -> #DIV/0!
A4: Foundations | B4: 0.7 | C4: 0.3 | D4: 0.105 | E4: 0.10810811 | F4: 0 | G4: 1 | H4: 0 | I4: 1 | J4: 0 | K4: 1 | L4: NAHB (Foundations) | N4: =IF(Z2="1,000 square-foot home", AC5*1000, AC5) -> 161 | R4: Local (LA) | S4: 16 | T4: 50 | AB4: Salt Lake City | AC4: 150 | AE4: Salt Lake City | AF4: Local | AG4: {=_xlfn.IFS(AND(AE4="Los Angeles",AF4="Local"),$AF$11*$AF$16,AND(AE4="Salt Lake City",AF4="Local"),$AF$11*$AF$17,AND(AE4="Salt Lake City",AF4=OR("Multi-Market Modular","Multi-Market Hybrid")),$AF$12*$AF$17)} -> 548500 | AH4: =IF(AF4="Local",$AF$29, $AF$30) -> 50000 | AI4: =AG4+AH4 -> 598500 | AJ4: =$AI4/AG22 -> 19.152 | AK4: =$AI4/AH22 -> #DIV/0!
A5: Floor framing | B5: 0.6 | C5: 0.4 | D5: =16.6%/COUNTA($A$6:$A$13) -> 0.02075 | E5: 0.032432432 | F5: 0.1 | G5: 0.2 | H5: 0.15 | I5: 0.2 | J5: 0.2 | K5: 0.2 | L5: NAHB (Average 16.6%/7 all Framing, Trusses, Sheathing, Other) | R5: Distant (SLC-LA) | S5: =10+(T5/U5) -> 13.75 | T5: 750 | U5: =2*100 -> 200 | AB5: National Average | AC5: 161 | AE5: Salt Lake City | AF5: Multi-Market Modular | AG5: {=_xlfn.IFS(AND(AE5="Los Angeles",AF5="Local"),$AF$11*$AF$16,AND(AE5="Salt Lake City",AF5="Local"),$AF$11*$AF$17,AND(AE5="Salt Lake City",AF5="Multi-Market Modular"),$AF$12*$AF$17,AND(AE5="Salt Lake City",AF5="Multi-Market Hybrid"),$AF$12*$AF$17)} -> 1097000 | AH5: =IF(AF5="Local",$AF$29, $AF$30) -> 100000 | AI5: =AG5+AH5 -> 1197000 | AJ5: =$AI5/AG23 -> 19.152 | AK5: =$AI5/AH23 -> #DIV/0!
A6: Floor sheathing | B6: 0.6 | C6: 0.4 | D6: =16.6%/COUNTA($A$6:$A$13) -> 0.02075 | E6: 0.016216216 | F6: 0.1 | G6: 0.2 | H6: 0.15 | I6: 0.2 | J6: 0.2 | K6: 0.2 | AE6: Salt Lake City | AF6: Multi-Market Hybrid 1 | AG6: {=_xlfn.IFS(AND(AE6="Los Angeles",AF6="Local"),$AF$11*$AF$16,AND(AE6="Salt Lake City",AF6="Local"),$AF$11*$AF$17,AND(AE6="Salt Lake City",AF6="Multi-Market Modular"),$AF$12*$AF$17,AND(AE6="Salt Lake City",AF6="Multi-Market Hybrid 1"),$AF$12*$AF$17)} -> 1097000 | AH6: =IF(AF6="Local",$AF$29, $AF$30) -> 100000 | AI6: =AG6+AH6 -> 1197000 | AJ6: =$AI6/AG24 -> 38.304 | AK6: =$AI6/AH24 -> 19.152
A7: Interior Wall framing | B7: 0.6 | C7: 0.4 | D7: =16.6%/COUNTA($A$6:$A$13) -> 0.02075 | E7: 0.040540541 | F7: 0.1 | G7: 0.2 | H7: 0.15 | I7: 0.2 | J7: 0.2 | K7: 0.2 | N7: LA Site Built Cost | AE7: Salt Lake City | AF7: Multi-Market Hybrid 2 | AG7: {=_xlfn.IFS(AND(AE7="Los Angeles",AF7="Local"),$AF$11*$AF$16,AND(AE7="Salt Lake City",AF7="Local"),$AF$11*$AF$17,AND(AE7="Salt Lake City",AF7="Multi-Market Modular"),$AF$12*$AF$17,AND(AE7="Salt Lake City",AF7="Multi-Market Hybrid 1"),$AF$12*$AF$17,AND(AE7="Salt Lake City",AF7="Multi-Market Hybrid 2"),$AF$12*$AF$17)} -> 1097000 | AH7: =IF(AF7="Local",$AF$29, $AF$30) -> 100000 | AI7: =AG7+AH7 -> 1197000 | AJ7: =$AI7/AG25 -> #DIV/0! | AK7: =$AI7/AH25 -> 9.576
A8: Interior Wall sheathing | B8: 0.6 | C8: 0.4 | D8: =16.6%/COUNTA($A$6:$A$13) -> 0.02075 | E8: 0.016216216 | F8: 0.1 | G8: 0.2 | H8: 0.15 | I8: 0.2 | J8: 0.2 | K8: 0.2 | N8: =IF(Z2="1,000 square-foot home", AC3*1000, AC3) -> 320 | R8: Components + 2D Panels Transportation Costs
A9: Exterior Walls framing | B9: 0.6 | C9: 0.4 | D9: =16.6%/COUNTA($A$6:$A$13) -> 0.02075 | E9: 0.091891892 | F9: 0.1 | G9: 0.2 | H9: 0.15 | I9: 0.2 | J9: 0.2 | K9: 0.2 | R9: Type | S9: Cost Per Mile | T9: Distance (miles) | AE9: Configuration Sizes
A10: Exterior Wall sheathing | B10: 0.6 | C10: 0.4 | D10: =16.6%/COUNTA($A$6:$A$13) -> 0.02075 | E10: 0.027027027 | F10: 0.1 | G10: 0.2 | H10: 0.15 | I10: 0.2 | J10: 0.2 | K10: 0.2 | R10: Local (SLC) | S10: 3 | T10: 50 | AE10: Configuration | AF10: Size (sqft) | AG10: Note
A11: Roof framing | B11: 0.6 | C11: 0.4 | D11: =16.6%/COUNTA($A$6:$A$13) -> 0.02075 | E11: 0.032432432 | F11: 0.1 | G11: 0.2 | H11: 0.15 | I11: 0.2 | J11: 0.2 | K11: 0.2 | N11: SLC Site Built Cost | R11: Local (LA) | S11: 4 | T11: 50 | AE11: Local | AF11: 50000 | AG11: Industry Company Reports 18-50k sqft
A12: Roof sheathing and waterproofing | B12: 0.6 | C12: 0.4 | D12: =16.6%/COUNTA($A$6:$A$13) -> 0.02075 | E12: 0.027027027 | F12: 0.1 | G12: 0.2 | H12: 0.15 | I12: 0.2 | J12: 0.2 | K12: 0.2 | N12: =IF(Z2="1,000 square-foot home", AC4*1000, AC4) -> 150 | R12: Distant (SLC-LA) | S12: 4 | T12: 750 | AE12: Multi-Market | AF12: 100000 | AG12: Industry Company Reports 110k sqft
A13: Mechanical Rough In | B13: 0.3 | C13: 0.7 | D13: 0.063 | E13: 0.045945946 | F13: 0.1 | G13: 0.2 | H13: 0.15 | I13: 0.2 | J13: 0.2 | K13: 0.2 | L13: NAHB (Major Systems Rough-ins Plumbing)
A14: Electrical Rough In | B14: 0.3 | C14: 0.7 | D14: 0.064 | E14: 0.02972973 | F14: 0.1 | G14: 0.2 | H14: 0.15 | I14: 0.2 | J14: 0.2 | K14: 0.2 | L14: NAHB (Major Systems Rough-ins Electrical) | AE14: Lease Costs
A15: Plumbing Rough In | B15: 0.3 | C15: 0.7 | D15: 0.063 | E15: 0.043243243 | F15: 0.1 | G15: 0.2 | H15: 0.15 | I15: 0.2 | J15: 0.2 | K15: 0.2 | L15: NAHB (Major Systems Rough-ins HVAC) | AE15: Facility Location | AF15: $/Sqft/Yr | AG15: Source
A16: Insulation | B16: 0.6 | C16: 0.4 | D16: 0.016 | E16: 0.032432432 | F16: 0.1 | G16: 0.2 | H16: 0.15 | I16: 0.2 | J16: 0.2 | K16: 0.2 | L16: NAHB (Interior Finishes Insulation) | AE16: Los Angeles | AF16: 19.03 | AG16: Property Shark
A17: Drywall | B17: 0.6 | C17: 0.4 | D17: 0.033 | E17: 0.021621622 | F17: 0.1 | G17: 0.2 | H17: 0.15 | I17: 0.2 | J17: 0.2 | K17: 0.2 | L17: NAHB (Interior Finishes Drywall) | AE17: Salt Lake City | AF17: 10.97 | AG17: Property Shark
A18: Mechanical Finishing | B18: 0.6 | C18: 0.4 | D18: 0.01 | E18: 0.045945946 | F18: 0.1 | G18: 0.2 | H18: 0.15 | I18: 0.2 | J18: 0.2 | K18: 0.2 | L18: NAHB (Interior Finishes Fireplace, Other)
A19: Electrical Finishing | B19: 0.6 | C19: 0.4 | D19: 0.031 | E19: 0.045945946 | F19: 0.1 | G19: 0.2 | H19: 0.15 | I19: 0.2 | J19: 0.2 | K19: 0.2 | L19: NAHB (Interior Finishes Appliances, Lighting) | AE19: Throughput
A20: Plumbing Finishing | B20: 0.6 | C20: 0.4 | D20: 0.019 | E20: 0.045945946 | F20: 0.1 | G20: 0.2 | H20: 0.15 | I20: 0.2 | J20: 0.2 | K20: 0.2 | L20: NAHB (Interior Finishes Plumbing Fixtures) | AE20: Facility Location | AF20: Configuration | AG20: Modular Throughput (Sqft) | AH20: Panel Throughput (Sqft) | AI20: Note
A21: Carpentry | B21: 0.3 | C21: 0.7 | D21: =(3+4.5)/100 -> 0.075 | E21: 0.043243243 | F21: 0.1 | G21: 0.2 | H21: 0.15 | I21: 0.2 | J21: 0.2 | K21: 0.2 | L21: NAHB (Interior Finishes Trims, Doors, and Mirrors, Cabinets, Countertops) | AE21: Los Angeles | AF21: Local | AG21: =AVERAGE(500,750)*50 -> 31250 | AI21: Industry Company Reports 500-750 sqft per week. Assume 50 working weeks
A22: Floor Finishing | B22: 0.6 | C22: 0.4 | D22: 0.036 | E22: 0.016216216 | F22: 0.1 | G22: 0.2 | H22: 0.15 | I22: 0.2 | J22: 0.2 | K22: 0.2 | L22: NAHB (Interior Finishes Flooring) | AE22: Salt Lake City | AF22: Local | AG22: =AVERAGE(500,750)*50 -> 31250
A23: Painting | B23: 0.3 | C23: 0.7 | D23: 0.026 | E23: 0.016216216 | F23: 0.1 | G23: 0.2 | H23: 0.15 | I23: 0.2 | J23: 0.2 | K23: 0.2 | L23: NAHB (Interior Finishes Painting) | AE23: Salt Lake City | AF23: Multi-Market Modular | AG23: =AG22*(AF12/AF11) -> 62500 | AI23: Assume double Local config. 50% SLC and 50% LA
A24: Exterior Wall Finishing | B24: 0.6 | C24: 0.4 | D24: =(5.7+3.7)/100 -> 0.094 | E24: 0.027027027 | F24: 0.1 | G24: 0.2 | H24: 0.15 | I24: 0.2 | J24: 0.2 | K24: 0.2 | L24: NAHB (Exterior Finsihes Wall, Windows and Doors) | AE24: Salt Lake City | AF24: Multi-Market Hybrid 1 | AG24: =(AG23/2) -> 31250 | AH24: =(AG23/2*2) -> 62500 | AI24: Assume 50% modular, 50% panel with panels being 2x faster
A25: Exterior Roof Finishing | B25: 0.6 | C25: 0.4 | D25: 0.039 | E25: 0.027027027 | F25: 0.1 | G25: 0.2 | H25: 0.15 | I25: 0.2 | J25: 0.2 | K25: 0.2 | L25: NAHB (Exterior Finsihes Roofing) | AE25: Salt Lake City | AF25: Multi-Market Hybrid 2 | AH25: =(AG23/2*2)+(AG23/2*2) -> 125000 | AI25: Assume 100% panel, 2x faster than modular
A26: Transportation
A27: Assembly | AE27: Equipment Fixed Costs (Assume Same Regardless of Location)
A28: All Inspections | C28: 1 | D28: 0.084 | E28: 0.059459459 | F28: 0.8 | G28: 0.8 | H28: 0.8 | I28: 0.8 | J28: 0.8 | K28: 0.8 | L28: NAHB (Final Steps and Other) | AE28: Configuration | AF28: Total Equip Costs | AG28: Source
A29: Total | D29: =SUM(D3:D28) -> 1 | E29: =SUM(E3:E28) -> 1 | AE29: Local | AF29: 50000 | AG29: Estimate
AE30: Multi-Market | AF30: 100000 | AG30: Estimate
B33: Modifiable Parameters
A36: Hourly Labor Cost (facility location model)
A37: Construction Process | B37: CA - Los Angeles | C37: UT - Salt Lake City | D37: National Average | E37: BLS - OEWS Category Reference
A38: Site Work | B38: =_xlfn.XLOOKUP("*" & $A38 & "*",'OEWS - California May 2024'!$A:$A,'OEWS - California May 2024'!$E:$E, "Not Found", 2) -> 31.8 | C38: =_xlfn.XLOOKUP("*" & $A38 & "*",'OEWS - Utah May 2024'!$A:$A,'OEWS - Utah May 2024'!$E:$E, "Not Found", 2) -> 22.96 | D38: =_xlfn.XLOOKUP("*" & $A38 & "*",'OEWS - National May 2024'!$A:$A,'OEWS - National May 2024'!$E:$E, "Not Found", 2) -> 24.64 | E38: =_xlfn.XLOOKUP("*" & $A38 & "*",'OEWS - National May 2024'!$A:$A,'OEWS - National May 2024'!$B:$B, "Not Found", 2) -> Construction Laborers (47-2061)
A39: Foundations | B39: =_xlfn.XLOOKUP("*" & $A39 & "*",'OEWS - California May 2024'!$A:$A,'OEWS - California May 2024'!$E:$E, "Not Found", 2) -> 31.8 | C39: =_xlfn.XLOOKUP("*" & $A39 & "*",'OEWS - Utah May 2024'!$A:$A,'OEWS - Utah May 2024'!$E:$E, "Not Found", 2) -> 22.96 | D39: =_xlfn.XLOOKUP("*" & $A39 & "*",'OEWS - National May 2024'!$A:$A,'OEWS - National May 2024'!$E:$E, "Not Found", 2) -> 24.64 | E39: =_xlfn.XLOOKUP("*" & $A39 & "*",'OEWS - National May 2024'!$A:$A,'OEWS - National May 2024'!$B:$B, "Not Found", 2) -> Construction Laborers (47-2061)
A40: Floor framing | B40: =_xlfn.XLOOKUP("*" & $A40 & "*",'OEWS - California May 2024'!$A:$A,'OEWS - California May 2024'!$E:$E, "Not Found", 2) -> 34.68 | C40: =_xlfn.XLOOKUP("*" & $A40 & "*",'OEWS - Utah May 2024'!$A:$A,'OEWS - Utah May 2024'!$E:$E, "Not Found", 2) -> 22.81 | D40: =_xlfn.XLOOKUP("*" & $A40 & "*",'OEWS - National May 2024'!$A:$A,'OEWS - National May 2024'!$E:$E, "Not Found", 2) -> 29.11 | E40: =_xlfn.XLOOKUP("*" & $A40 & "*",'OEWS - National May 2024'!$A:$A,'OEWS - National May 2024'!$B:$B, "Not Found", 2) -> Floor Layers, Except Carpet, Wood, and Hard Tiles (47-2042)
A41: Floor sheathing | B41: =_xlfn.XLOOKUP("*" & $A41 & "*",'OEWS - California May 2024'!$A:$A,'OEWS - California May 2024'!$E:$E, "Not Found", 2) -> 34.68 | C41: =_xlfn.XLOOKUP("*" & $A41 & "*",'OEWS - Utah May 2024'!$A:$A,'OEWS - Utah May 2024'!$E:$E, "Not Found", 2) -> 22.81 | D41: =_xlfn.XLOOKUP("*" & $A41 & "*",'OEWS - National May 2024'!$A:$A,'OEWS - National May 2024'!$E:$E, "Not Found", 2) -> 29.11 | E41: =_xlfn.XLOOKUP("*" & $A41 & "*",'OEWS - National May 2024'!$A:$A,'OEWS - National May 2024'!$B:$B, "Not Found", 2) -> Floor Layers, Except Carpet, Wood, and Hard Tiles (47-2042)
A42: Interior Wall framing | B42: =_xlfn.XLOOKUP("*" & $A42 & "*",'OEWS - California May 2024'!$A:$A,'OEWS - California May 2024'!$E:$E, "Not Found", 2) -> 37.35 | C42: =_xlfn.XLOOKUP("*" & $A42 & "*",'OEWS - Utah May 2024'!$A:$A,'OEWS - Utah May 2024'!$E:$E, "Not Found", 2) -> 26.26 | D42: =_xlfn.XLOOKUP("*" & $A42 & "*",'OEWS - National May 2024'!$A:$A,'OEWS - National May 2024'!$E:$E, "Not Found", 2) -> 30.79 | E42: =_xlfn.XLOOKUP("*" & $A42 & "*",'OEWS - National May 2024'!$A:$A,'OEWS - National May 2024'!$B:$B, "Not Found", 2) -> Carpenters (47-2031)
A43: Interior Wall sheathing | B43: =_xlfn.XLOOKUP("*" & $A43 & "*",'OEWS - California May 2024'!$A:$A,'OEWS - California May 2024'!$E:$E, "Not Found", 2) -> 37.35 | C43: =_xlfn.XLOOKUP("*" & $A43 & "*",'OEWS - Utah May 2024'!$A:$A,'OEWS - Utah May 2024'!$E:$E, "Not Found", 2) -> 26.26 | D43: =_xlfn.XLOOKUP("*" & $A43 & "*",'OEWS - National May 2024'!$A:$A,'OEWS - National May 2024'!$E:$E, "Not Found", 2) -> 30.79 | E43: =_xlfn.XLOOKUP("*" & $A43 & "*",'OEWS - National May 2024'!$A:$A,'OEWS - National May 2024'!$B:$B, "Not Found", 2) -> Carpenters (47-2031)
A44: Exterior Walls framing | B44: =_xlfn.XLOOKUP("*" & $A44 & "*",'OEWS - California May 2024'!$A:$A,'OEWS - California May 2024'!$E:$E, "Not Found", 2) -> 37.35 | C44: =_xlfn.XLOOKUP("*" & $A44 & "*",'OEWS - Utah May 2024'!$A:$A,'OEWS - Utah May 2024'!$E:$E, "Not Found", 2) -> 26.26 | D44: =_xlfn.XLOOKUP("*" & $A44 & "*",'OEWS - National May 2024'!$A:$A,'OEWS - National May 2024'!$E:$E, "Not Found", 2) -> 30.79 | E44: =_xlfn.XLOOKUP("*" & $A44 & "*",'OEWS - National May 2024'!$A:$A,'OEWS - National May 2024'!$B:$B, "Not Found", 2) -> Carpenters (47-2031)
A45: Exterior Wall sheathing | B45: =_xlfn.XLOOKUP("*" & $A45 & "*",'OEWS - California May 2024'!$A:$A,'OEWS - California May 2024'!$E:$E, "Not Found", 2) -> 37.35 | C45: =_xlfn.XLOOKUP("*" & $A45 & "*",'OEWS - Utah May 2024'!$A:$A,'OEWS - Utah May 2024'!$E:$E, "Not Found", 2) -> 26.26 | D45: =_xlfn.XLOOKUP("*" & $A45 & "*",'OEWS - National May 2024'!$A:$A,'OEWS - National May 2024'!$E:$E, "Not Found", 2) -> 30.79 | E45: =_xlfn.XLOOKUP("*" & $A45 & "*",'OEWS - National May 2024'!$A:$A,'OEWS - National May 2024'!$B:$B, "Not Found", 2) -> Carpenters (47-2031)
A46: Roof framing | B46: =_xlfn.XLOOKUP("*" & $A46 & "*",'OEWS - California May 2024'!$A:$A,'OEWS - California May 2024'!$E:$E, "Not Found", 2) -> 32.73 | C46: =_xlfn.XLOOKUP("*" & $A46 & "*",'OEWS - Utah May 2024'!$A:$A,'OEWS - Utah May 2024'!$E:$E, "Not Found", 2) -> 25.36 | D46: =_xlfn.XLOOKUP("*" & $A46 & "*",'OEWS - National May 2024'!$A:$A,'OEWS - National May 2024'!$E:$E, "Not Found", 2) -> 27.45 | E46: =_xlfn.XLOOKUP("*" & $A46 & "*",'OEWS - National May 2024'!$A:$A,'OEWS - National May 2024'!$B:$B, "Not Found", 2) -> Roofers (47-2181)
A47: Roof sheathing and waterproofing | B47: =_xlfn.XLOOKUP("*" & $A47 & "*",'OEWS - California May 2024'!$A:$A,'OEWS - California May 2024'!$E:$E, "Not Found", 2) -> 32.73 | C47: =_xlfn.XLOOKUP("*" & $A47 & "*",'OEWS - Utah May 2024'!$A:$A,'OEWS - Utah May 2024'!$E:$E, "Not Found", 2) -> 25.36 | D47: =_xlfn.XLOOKUP("*" & $A47 & "*",'OEWS - National May 2024'!$A:$A,'OEWS - National May 2024'!$E:$E, "Not Found", 2) -> 27.45 | E47: =_xlfn.XLOOKUP("*" & $A47 & "*",'OEWS - National May 2024'!$A:$A,'OEWS - National May 2024'!$B:$B, "Not Found", 2) -> Roofers (47-2181)
A48: Mechanical Rough In | B48: =_xlfn.XLOOKUP("*" & $A48 & "*",'OEWS - California May 2024'!$A:$A,'OEWS - California May 2024'!$E:$E, "Not Found", 2) -> 33.8 | C48: =_xlfn.XLOOKUP("*" & $A48 & "*",'OEWS - Utah May 2024'!$A:$A,'OEWS - Utah May 2024'!$E:$E, "Not Found", 2) -> 28.5 | D48: =_xlfn.XLOOKUP("*" & $A48 & "*",'OEWS - National May 2024'!$A:$A,'OEWS - National May 2024'!$E:$E, "Not Found", 2) -> 29.63 | E48: =_xlfn.XLOOKUP("*" & $A48 & "*",'OEWS - National May 2024'!$A:$A,'OEWS - National May 2024'!$B:$B, "Not Found", 2) -> Installation, Maintenance, and Repair Occupations (49-0000)
A49: Electrical Rough In | B49: =_xlfn.XLOOKUP("*" & $A49 & "*",'OEWS - California May 2024'!$A:$A,'OEWS - California May 2024'!$E:$E, "Not Found", 2) -> 41.24 | C49: =_xlfn.XLOOKUP("*" & $A49 & "*",'OEWS - Utah May 2024'!$A:$A,'OEWS - Utah May 2024'!$E:$E, "Not Found", 2) -> 30.3 | D49: =_xlfn.XLOOKUP("*" & $A49 & "*",'OEWS - National May 2024'!$A:$A,'OEWS - National May 2024'!$E:$E, "Not Found", 2) -> 33.47 | E49: =_xlfn.XLOOKUP("*" & $A49 & "*",'OEWS - National May 2024'!$A:$A,'OEWS - National May 2024'!$B:$B, "Not Found", 2) -> Electricians (47-2111)
... A60: Exterior Roof Finishing | B60: =_xlfn.XLOOKUP("*" & $A60 & "*",'OEWS - California May 2024'!$A:$A,'OEWS - California May 2024'!$E:$E, "Not Found", 2) -> 32.73 | C60: =_xlfn.XLOOKUP("*" & $A60 & "*",'OEWS - Utah May 2024'!$A:$A,'OEWS - Utah May 2024'!$E:$E, "Not Found", 2) -> 25.36 | D60: =_xlfn.XLOOKUP("*" & $A60 & "*",'OEWS - National May 2024'!$A:$A,'OEWS - National May 2024'!$E:$E, "Not Found", 2) -> 27.45 | E60: =_xlfn.XLOOKUP("*" & $A60 & "*",'OEWS - National May 2024'!$A:$A,'OEWS - National May 2024'!$B:$B, "Not Found", 2) -> Roofers (47-2181)
A61: Transportation | E61: Using assumptions and calculations
A62: Assembly | B62: =_xlfn.XLOOKUP("*" & $A62 & "*",'OEWS - California May 2024'!$A:$A,'OEWS - California May 2024'!$E:$E, "Not Found", 2) -> 31.8 | C62: =_xlfn.XLOOKUP("*" & $A62 & "*",'OEWS - Utah May 2024'!$A:$A,'OEWS - Utah May 2024'!$E:$E, "Not Found", 2) -> 22.96 | D62: =_xlfn.XLOOKUP("*" & $A62 & "*",'OEWS - National May 2024'!$A:$A,'OEWS - National May 2024'!$E:$E, "Not Found", 2) -> 24.64 | E62: =_xlfn.XLOOKUP("*" & $A62 & "*",'OEWS - National May 2024'!$A:$A,'OEWS - National May 2024'!$B:$B, "Not Found", 2) -> Construction Laborers (47-2061)
A63: All Inspections | B63: =_xlfn.XLOOKUP("*" & $A63 & "*",'OEWS - California May 2024'!$A:$A,'OEWS - California May 2024'!$E:$E, "Not Found", 2) -> 49.76 | C63: =_xlfn.XLOOKUP("*" & $A63 & "*",'OEWS - Utah May 2024'!$A:$A,'OEWS - Utah May 2024'!$E:$E, "Not Found", 2) -> 34.32 | D63: =_xlfn.XLOOKUP("*" & $A63 & "*",'OEWS - National May 2024'!$A:$A,'OEWS - National May 2024'!$E:$E, "Not Found", 2) -> 36.75 | E63: =_xlfn.XLOOKUP("*" & $A63 & "*",'OEWS - National May 2024'!$A:$A,'OEWS - National May 2024'!$B:$B, "Not Found", 2) -> Construction and Building Inspectors (47-4011)

Sheet OEWS - National May 2024
B1: Multiple occupations for one geographical area
B3: Area: National
B4: Period: May 2024
A6: Capstone Construction Process Cat. | B6: Occupation (SOC code) | C6: Employment (1) | D6: Employment percent relative standard error (3) | E6: Hourly mean wage | F6: Annual mean wage (2) | G6: Wage percent relative standard error (3) | H6: Hourly 10th percentile wage | I6: Hourly 25th percentile wage | J6: Hourly median wage | K6: Hourly 75th percentile wage | L6: Hourly 90th percentile wage | M6: Annual 10th percentile wage (2) | N6: Annual 25th percentile wage (2) | O6: Annual median wage (2) | P6: Annual 75th percentile wage (2) | Q6: Annual 90th percentile wage (2)
B7: Construction and Extraction Occupations (47-0000) | C7: 6361720 | D7: 0.2 | E7: 30.73 | F7: 63920 | G7: 0.30000001 | H7: 18 | I7: 22.13 | J7: 28.06 | K7: 36.93 | L7: 48.28 | M7: 37440 | N7: 46030 | O7: 58360 | P7: 76820 | Q7: 100430
B8: First-Line Supervisors of Construction Trades and Extraction Workers (47-1011) | C8: 806080 | D8: 0.60000002 | E8: 40.62 | F8: 84500 | G8: 0.40000001 | H8: 24.66 | I8: 30 | J8: 37.83 | K8: 48.17 | L8: 60.91 | M8: 51290 | N8: 62400 | O8: 78690 | P8: 100200 | Q8: 126690
B9: Construction Trades Workers (47-2000) | C9: 4691890 | D9: 0.30000001 | E9: 29.6 | F9: 61560 | G9: 0.30000001 | H9: 17.91 | I9: 21.9 | J9: 27.16 | K9: 35.47 | L9: 46.47 | M9: 37260 | N9: 45560 | O9: 56490 | P9: 73780 | Q9: 96650
B10: Boilermakers (47-2011) | C10: 10170 | D10: 5.8000002 | E10: 36.97 | F10: 76900 | G10: 1.6 | H10: 23.26 | I10: 29.92 | J10: 35.26 | K10: 44.96 | L10: 51.73 | M10: 48390 | N10: 62230 | O10: 73340 | P10: 93520 | Q10: 107600
B11: Brickmasons, Blockmasons, and Stonemasons (47-2020) | C11: 62260 | D11: 2.9000001 | E11: 30.89 | F11: 64240 | G11: 1 | H11: 19.39 | I11: 23.41 | J11: 28.93 | K11: 36.7 | L11: 45.28 | M11: 40330 | N11: 48690 | O11: 60180 | P11: 76340 | Q11: 94190
B12: Brickmasons and Blockmasons (47-2021) | C12: 53520 | D12: 3.0999999 | E12: 31.44 | F12: 65390 | G12: 1 | H12: 19.87 | I12: 23.76 | J12: 29.23 | K12: 37.16 | L12: 45.94 | M12: 41330 | N12: 49430 | O12: 60800 | P12: 77290 | Q12: 95560
B13: Stonemasons (47-2022) | C13: 8750 | D13: 6.6999998 | E13: 27.51 | F13: 57220 | G13: 2 | H13: 17.99 | I13: 21.55 | J13: 25 | K13: 30.83 | L13: 40 | M13: 37420 | N13: 44820 | O13: 51990 | P13: 64120 | Q13: 83200
A14: Interior Wall framing Interior Wall sheathing Exterior Walls framing Exterior Wall sheathing Carpentry | B14: Carpenters (47-2031) | C14: 697740 | D14: 1.2 | E14: 30.79 | F14: 64040 | G14: 0.5 | H14: 18.64 | I14: 22.86 | J14: 28.51 | K14: 36.36 | L14: 47.3 | M14: 38760 | N14: 47550 | O14: 59310 | P14: 75620 | Q14: 98370
B15: Carpet, Floor, and Tile Installers and Finishers (47-2040) | C15: 82710 | D15: 2.4000001 | E15: 27.8 | F15: 57830 | G15: 1 | H15: 17.24 | I15: 20.92 | J15: 25 | K15: 31.64 | L15: 41.49 | M15: 35850 | N15: 43520 | O15: 52000 | P15: 65810 | Q15: 86290
B16: Carpet Installers (47-2041) | C16: 14980 | D16: 6.1999998 | E16: 26.85 | F16: 55860 | G16: 2.0999999 | H16: 15.78 | I16: 18.82 | J16: 23.97 | K16: 31.51 | L16: 40 | M16: 32830 | N16: 39140 | O16: 49850 | P16: 65530 | Q16: 83200
A17: Floor framing Floor sheathing | B17: Floor Layers, Except Carpet, Wood, and Hard Tiles (47-2042) | C17: 24850 | D17: 5.1999998 | E17: 29.11 | F17: 60550 | G17: 1.7 | H17: 17.88 | I17: 21.52 | J17: 26.13 | K17: 34.8 | L17: 46.72 | M17: 37190 | N17: 44760 | O17: 54340 | P17: 72390 | Q17: 97180
B18: Floor Sanders and Finishers (47-2043) | C18: 4140 | D18: 12.1 | E18: 24.46 | F18: 50880 | G18: 2.3 | H18: 17.21 | I18: 19.87 | J18: 23.63 | K18: 27.99 | L18: 31.98 | M18: 35790 | N18: 41320 | O18: 49150 | P18: 58230 | Q18: 66510
A19: Floor Finishing | B19: Tile and Stone Setters (47-2044) | C19: 38740 | D19: 4.0999999 | E19: 27.69 | F19: 57590 | G19: 1.5 | H19: 17.38 | I19: 21.41 | J19: 25.11 | K19: 31.24 | L19: 39.89 | M19: 36140 | N19: 44540 | O19: 52240 | P19: 64980 | Q19: 82960
B20: Cement Masons, Concrete Finishers, and Terrazzo Workers (47-2050) | C20: 206680 | D20: 1.6 | E20: 28.55 | F20: 59380 | G20: 0.60000002 | H20: 18.41 | I20: 22.13 | J20: 26.3 | K20: 31.68 | L20: 42.19 | M20: 38290 | N20: 46020 | O20: 54700 | P20: 65890 | Q20: 87760
B21: Cement Masons and Concrete Finishers (47-2051) | C21: 205230 | D21: 1.6 | E21: 28.54 | F21: 59360 | G21: 0.60000002 | H21: 18.41 | I21: 22.13 | J21: 26.28 | K21: 31.66 | L21: 42.13 | M21: 38290 | N21: 46020 | O21: 54660 | P21: 65840 | Q21: 87620
B22: Terrazzo Workers and Finishers (47-2053) | C22: 1450 | D22: 20.1 | E22: 29.97 | F22: 62330 | G22: 6.5 | H22: 18.92 | I22: 22.57 | J22: 27.53 | K22: 35.33 | L22: 50.24 | M22: 39360 | N22: 46940 | O22: 57260 | P22: 73490 | Q22: 104510
A23: Site Work Foundations Assembly | B23: Construction Laborers (47-2061) | C23: 1057660 | D23: 0.69999999 | E23: 24.64 | F23: 51260 | G23: 0.40000001 | H23: 16.44 | I23: 18.32 | J23: 22.47 | K23: 28.32 | L23: 37.28 | M23: 34200 | N23: 38100 | O23: 46730 | P23: 58910 | Q23: 77530
B24: Construction Equipment Operators (47-2070) | C24: 518000 | D24: 0.69999999 | E24: 31.1 | F24: 64680 | G24: 0.40000001 | H24: 19.16 | I24: 22.88 | J24: 28.04 | K24: 36.24 | L24: 48.04 | M24: 39850 | N24: 47590 | O24: 58320 | P24: 75370 | Q24: 99930
B25: Paving, Surfacing, and Tamping Equipment Operators (47-2071) | C25: 45680 | D25: 3.4000001 | E25: 28.2 | F25: 58660 | G25: 1.3 | H25: 18.29 | I25: 21.51 | J25: 24.83 | K25: 31.76 | L25: 43.32 | M25: 38030 | N25: 44740 | O25: 51650 | P25: 66060 | Q25: 90110
B26: Pile Driver Operators (47-2072) | C26: 3040 | D26: 9.8999996 | E26: 37.98 | F26: 79000 | G26: 3.0999999 | H26: 22.45 | I26: 26.32 | J26: 33.9 | K26: 49.98 | L26: 58.65 | M26: 46690 | N26: 54750 | O26: 70510 | P26: 103960 | Q26: 121990
B27: Operating Engineers and Other Construction Equipment Operators (47-2073) | C27: 469270 | D27: 0.80000001 | E27: 31.34 | F27: 65180 | G27: 0.40000001 | H27: 19.27 | I27: 22.97 | J27: 28.23 | K27: 36.42 | L27: 48.41 | M27: 40080 | N27: 47780 | O27: 58710 | P27: 75750 | Q27: 100690
B28: Drywall Installers, Ceiling Tile Installers, and Tapers (47-2080) | C28: 95400 | D28: 2.2 | E28: 30.68 | F28: 63800 | G28: 1 | H28: 18.35 | I28: 22.63 | J28: 28.27 | K28: 35.78 | L28: 49.48 | M28: 38160 | N28: 47070 | O28: 58800 | P28: 74410 | Q28: 102920
A29: Drywall | B29: Drywall and Ceiling Tile Installers (47-2081) | C29: 82900 | D29: 2.2 | E29: 30.2 | F29: 62810 | G29: 1 | H29: 18.18 | I29: 22.54 | J29: 27.95 | K29: 34.93 | L29: 48.74 | M29: 37810 | N29: 46880 | O29: 58140 | P29: 72660 | Q29: 101380
B30: Tapers (47-2082) | C30: 12500 | D30: 7.5999999 | E30: 33.84 | F30: 70390 | G30: 2 | H30: 20.89 | I30: 24.42 | J30: 31.11 | K30: 39.9 | L30: 51.04 | M30: 43450 | N30: 50780 | O30: 64700 | P30: 82990 | Q30: 106160
A31: Electrical Rough in Electrical Finishing | B31: Electricians (47-2111) | C31: 742580 | D31: 0.69999999 | E31: 33.47 | F31: 69630 | G31: 0.5 | H31: 18.96 | I31: 23.47 | J31: 29.98 | K31: 39.29 | L31: 50.98 | M31: 39430 | N31: 48820 | O31: 62350 | P31: 81730 | Q31: 106030
B32: Glaziers (47-2121) | C32: 57000 | D32: 3.0999999 | E32: 28.97 | F32: 60260 | G32: 1.8 | H32: 18.13 | I32: 21.89 | J32: 26.65 | K32: 32.84 | L32: 47.49 | M32: 37710 | N32: 45530 | O32: 55440 | P32: 68300 | Q32: 98780
B33: Insulation Workers (47-2130) | C33: 64250 | D33: 2.9000001 | E33: 27.63 | F33: 57470 | G33: 1.3 | H33: 17.76 | I33: 21.28 | J33: 24.39 | K33: 30.67 | L33: 40 | M33: 36950 | N33: 44260 | O33: 50730 | P33: 63800 | Q33: 83200
A34: Insulation | B34: Insulation Workers, Floor, Ceiling, and Wall (47-2131) | C34: 38610 | D34: 3.5 | E34: 25.69 | F34: 53440 | G34: 1.5 | H34: 17.28 | I34: 19.36 | J34: 23.41 | K34: 29.05 | L34: 37.1 | M34: 35950 | N34: 40270 | O34: 48680 | P34: 60420 | Q34: 77160
B35: Insulation Workers, Mechanical (47-2132) | C35: 25640 | D35: 5.4000001 | E35: 30.55 | F35: 63540 | G35: 2.2 | H35: 18.97 | I35: 22.83 | J35: 27.52 | K35: 36.2 | L35: 45.25 | M35: 39450 | N35: 47480 | O35: 57250 | P35: 75300 | Q35: 94110
B36: Painters and Paperhangers (47-2140) | C36: 225700 | D36: 1.6 | E36: 25.82 | F36: 53700 | G36: 0.69999999 | H36: 17.63 | I36: 20.43 | J36: 23.39 | K36: 28.97 | L36: 36.8 | M36: 36680 | N36: 42480 | O36: 48660 | P36: 60270 | Q36: 76540
A37: Painting | B37: Painters, Construction and Maintenance (47-2141) | C37: 224180 | D37: 1.6 | E37: 25.82 | F37: 53710 | G37: 0.69999999 | H37: 17.63 | I37: 20.44 | J37: 23.4 | K37: 28.97 | L37: 36.8 | M37: 36680 | N37: 42510 | O37: 48660 | P37: 60270 | Q37: 76550
B38: Paperhangers (47-2142) | C38: 1520 | D38: 13.7 | E38: 24.95 | F38: 51900 | G38: 3.9000001 | H38: 16.84 | I38: 19.68 | J38: 23.2 | K38: 28.11 | L38: 33.4 | M38: 35020 | N38: 40930 | O38: 48260 | P38: 58470 | Q38: 69470
B39: Pipelayers, Plumbers, Pipefitters, and Steamfitters (47-2150) | C39: 489520 | D39: 1.1 | E39: 33.11 | F39: 68870 | G39: 0.60000002 | H39: 19.17 | I39: 23.25 | J39: 29.91 | K39: 38.88 | L39: 50.03 | M39: 39880 | N39: 48360 | O39: 62210 | P39: 80880 | Q39: 104050
B40: Pipelayers (47-2151) | C40: 33580 | D40: 3.9000001 | E40: 26.09 | F40: 54270 | G40: 1.3 | H40: 17.71 | I40: 20.35 | J40: 23.42 | K40: 29.32 | L40: 38.81 | M40: 36840 | N40: 42320 | O40: 48710 | P40: 60980 | Q40: 80710
A41: Plumbing Rough In Plumbing Finishing | B41: Plumbers, Pipefitters, and Steamfitters (47-2152) | C41: 455940 | D41: 1.2 | E41: 33.63 | F41: 69940 | G41: 0.60000002 | H41: 19.55 | I41: 23.49 | J41: 30.27 | K41: 39.37 | L41: 50.55 | M41: 40670 | N41: 48860 | O41: 62970 | P41: 81900 | Q41: 105150
A42: Exterior Wall Finishing | B42: Plasterers and Stucco Masons (47-2161) | C42: 20880 | D42: 5.1999998 | E42: 29.33 | F42: 61000 | G42: 1.6 | H42: 18.56 | I42: 22.59 | J42: 26.93 | K42: 34.72 | L42: 44.68 | M42: 38610 | N42: 46990 | O42: 56020 | P42: 72210 | Q42: 92930
B43: Reinforcing Iron and Rebar Workers (47-2171) | C43: 14140 | D43: 8 | E43: 30.11 | F43: 62640 | G43: 2.5 | H43: 18.97 | I43: 22.74 | J43: 28.5 | K43: 35.67 | L43: 45.93 | M43: 39470 | N43: 47300 | O43: 59280 | P43: 74190 | Q43: 95530
A44: Roof framing Roof sheathing and waterproofing Exterior Roof Finishing | B44: Roofers (47-2181) | C44: 136740 | D44: 1.4 | E44: 27.45 | F44: 57090 | G44: 0.80000001 | H44: 17.82 | I44: 21.78 | J44: 24.51 | K44: 30.78 | L44: 38.84 | M44: 37060 | N44: 45300 | O44: 50970 | P44: 64010 | Q44: 80780
B45: Sheet Metal Workers (47-2211) | C45: 117470 | D45: 2 | E45: 31.78 | F45: 66110 | G45: 0.80000001 | H45: 18.28 | I45: 22.74 | J45: 29.26 | K45: 38.28 | L45: 49.37 | M45: 38030 | N45: 47290 | O45: 60850 | P45: 79620 | Q45: 102680
B46: Structural Iron and Steel Workers (47-2221) | C46: 64720 | D46: 3 | E46: 33.3 | F46: 69270 | G46: 1.2 | H46: 20.19 | I46: 23.6 | J46: 30.14 | K46: 39.8 | L46: 51.69 | M46: 42000 | N46: 49090 | O46: 62700 | P46: 82780 | Q46: 107520
B47: Solar Photovoltaic Installers (47-2231) | C47: 28280 | D47: 5.1999998 | E47: 27.59 | F47: 57380 | G47: 1.6 | H47: 18.79 | I47: 22.13 | J47: 24.93 | K47: 30.3 | L47: 38.53 | M47: 39070 | N47: 46040 | O47: 51860 | P47: 63020 | Q47: 80150
B48: Helpers, Construction Trades (47-3010) | C48: 186250 | D48: 1.6 | E48: 20.74 | F48: 43140 | G48: 0.69999999 | H48: 15.08 | I48: 17.44 | J48: 19.44 | K48: 22.94 | L48: 27.64 | M48: 31360 | N48: 36280 | O48: 40430 | P48: 47710 | Q48: 57480
B49: Helpers--Brickmasons, Blockmasons, Stonemasons, and Tile and Marble Setters (47-3011) | C49: 15660 | D49: 6.3000002 | E49: 23.91 | F49: 49730 | G49: 1.5 | H49: 17.1 | I49: 18.56 | J49: 22.35 | K49: 27.93 | L49: 32.85 | M49: 35570 | N49: 38600 | O49: 46480 | P49: 58080 | Q49: 68330
B50: Helpers--Carpenters (47-3012) | C50: 24610 | D50: 7.6999998 | E50: 20.23 | F50: 42080 | G50: 1.9 | H50: 15.16 | I50: 17.24 | J50: 20 | K50: 22.49 | L50: 25.18 | M50: 31540 | N50: 35870 | O50: 41600 | P50: 46780 | Q50: 52380
B51: Helpers--Electricians (47-3013) | C51: 64440 | D51: 3 | E51: 20.62 | F51: 42900 | G51: 0.89999998 | H51: 15 | I51: 17.5 | J51: 19.18 | K51: 22.85 | L51: 27.29 | M51: 31200 | N51: 36400 | O51: 39890 | P51: 47520 | Q51: 56770
B52: Helpers--Painters, Paperhangers, Plasterers, and Stucco Masons (47-3014) | C52: 7220 | D52: 8 | E52: 19.65 | F52: 40880 | G52: 2.2 | H52: 15.08 | I52: 16.94 | J52: 18.34 | K52: 21.78 | L52: 24.87 | M52: 31360 | N52: 35230 | O52: 38140 | P52: 45290 | Q52: 51720
B53: Helpers--Pipelayers, Plumbers, Pipefitters, and Steamfitters (47-3015) | C53: 43640 | D53: 4 | E53: 20.06 | F53: 41720 | G53: 0.89999998 | H53: 14.93 | I53: 17.19 | J53: 18.88 | K53: 22.38 | L53: 26.37 | M53: 31050 | N53: 35750 | O53: 39270 | P53: 46550 | Q53: 54860
B54: Helpers--Roofers (47-3016) | C54: 5170 | D54: 10.1 | E54: 20.23 | F54: 42070 | G54: 3.0999999 | H54: 13.36 | I54: 16.73 | J54: 19.51 | K54: 22.87 | L54: 26.59 | M54: 27780 | N54: 34800 | O54: 40590 | P54: 47570 | Q54: 55310
B55: Helpers, Construction Trades, All Other (47-3019) | C55: 25510 | D55: 4 | E55: 21.17 | F55: 44040 | G55: 1.2 | H55: 15 | I55: 17.5 | J55: 19.6 | K55: 23.32 | L55: 28.5 | M55: 31200 | N55: 36400 | O55: 40760 | P55: 48500 | Q55: 59280
B56: Other Construction and Related Workers (47-4000) | C56: 464570 | D56: 0.89999998 | E56: 30.15 | F56: 62700 | G56: 0.40000001 | H56: 17.95 | I56: 21.84 | J56: 27.17 | K56: 35.84 | L56: 47.73 | M56: 37330 | N56: 45430 | O56: 56520 | P56: 74540 | Q56: 99280
A57: All Inspections | B57: Construction and Building Inspectors (47-4011) | C57: 137210 | D57: 2 | E57: 36.75 | F57: 76430 | G57: 0.80000001 | H57: 22.38 | I57: 27.55 | J57: 34.67 | K57: 44.39 | L57: 54 | M57: 46560 | N57: 57300 | O57: 72120 | P57: 92330 | Q57: 112320
B58: Elevator and Escalator Installers and Repairers (47-4021) | C58: 23340 | D58: 6.0999999 | E58: 50.42 | F58: 104860 | G58: 1.7 | H58: 26.31 | I58: 36.88 | J58: 51.24 | K58: 63.34 | L58: 71.76 | M58: 54720 | N58: 76700 | O58: 106580 | P58: 131740 | Q58: 149250
B59: Fence Erectors (47-4031) | C59: 22640 | D59: 6.5 | E59: 24.31 | F59: 50550 | G59: 1.6 | H59: 16.87 | I59: 18.77 | J59: 22.57 | K59: 27.44 | L59: 35.89 | M59: 35090 | N59: 39040 | O59: 46940 | P59: 57070 | Q59: 74660
B60: Hazardous Materials Removal Workers (47-4041) | C60: 50570 | D60: 2.5999999 | E60: 26.8 | F60: 55740 | G60: 1.2 | H60: 17.95 | I60: 20.53 | J60: 23.31 | K60: 29.88 | L60: 39.65 | M60: 37330 | N60: 42710 | O60: 48490 | P60: 62150 | Q60: 82480
B61: Highway Maintenance Workers (47-4051) | C61: 151750 | D61: 1.1 | E61: 24.72 | F61: 51410 | G61: 0.40000001 | H61: 16.84 | I61: 19.97 | J61: 23.59 | K61: 28.66 | L61: 33.27 | M61: 35030 | N61: 41540 | O61: 49070 | P61: 59600 | Q61: 69210
B62: Rail-Track Laying and Maintenance Equipment Operators (47-4061) | C62: 16480 | D62: 1.6 | E62: 32.82 | F62: 68270 | G62: 0.5 | H62: 21.98 | I62: 24.82 | J62: 32.39 | K62: 38.14 | L62: 40.79 | M62: 45720 | N62: 51630 | O62: 67370 | P62: 79330 | Q62: 84840
B63: Septic Tank Servicers and Sewer Pipe Cleaners (47-4071) | C63: 29050 | D63: 2.7 | E63: 25.35 | F63: 52730 | G63: 0.69999999 | H63: 17.55 | I63: 20.53 | J63: 23.62 | K63: 29 | L63: 35.42 | M63: 36500 | N63: 42700 | O63: 49140 | P63: 60320 | Q63: 73670
B64: Miscellaneous Construction and Related Workers (47-4090) | C64: 33530 | D64: 4.8000002 | E64: 25.44 | F64: 52910 | G64: 1.9 | H64: 16.9 | I64: 19.23 | J64: 23.14 | K64: 29.31 | L64: 37.28 | M64: 35160 | N64: 39990 | O64: 48120 | P64: 60960 | Q64: 77540
B65: Extraction Workers (47-5000) | C65: 212920 | D65: 1.5 | E65: 28.39 | F65: 59040 | G65: 0.60000002 | H65: 18.19 | I65: 22.2 | J65: 26.93 | K65: 32.63 | L65: 39.88 | M65: 37820 | N65: 46180 | O65: 56020 | P65: 67870 | Q65: 82950
B66: Derrick, Rotary Drill, and Service Unit Operators, Oil and Gas (47-5010) | C66: 68250 | D66: 3 | E66: 30.45 | F66: 63330 | G66: 0.89999998 | H66: 19.4 | I66: 23.05 | J66: 28.68 | K66: 35.84 | L66: 44.23 | M66: 40340 | N66: 47930 | O66: 59660 | P66: 74550 | Q66: 91990
B67: Derrick Operators, Oil and Gas (47-5011) | C67: 11040 | D67: 6.1999998 | E67: 30.05 | F67: 62490 | G67: 1.6 | H67: 20.64 | I67: 23.77 | J67: 30.16 | K67: 35.01 | L67: 40.68 | M67: 42930 | N67: 49440 | O67: 62740 | P67: 72820 | Q67: 84620
B68: Rotary Drill Operators, Oil and Gas (47-5012) | C68: 13090 | D68: 8.3999996 | E68: 33.69 | F68: 70080 | G68: 2 | H68: 20.56 | I68: 25.29 | J68: 31.26 | K68: 39.21 | L68: 47.36 | M68: 42750 | N68: 52600 | O68: 65010 | P68: 81550 | Q68: 98510
B69: Service Unit Operators, Oil and Gas (47-5013) | C69: 44120 | D69: 3.5999999 | E69: 29.58 | F69: 61530 | G69: 1.1 | H69: 19.24 | I69: 22.75 | J69: 27.88 | K69: 33.9 | L69: 45.11 | M69: 40010 | N69: 47330 | O69: 57980 | P69: 70510 | Q69: 93820
... B82: Extraction Workers, All Other (47-5099) | C82: 6070 | D82: 8.5 | E82: 26.34 | F82: 54780 | G82: 2.3 | H82: 17.17 | I82: 18.81 | J82: 24.09 | K82: 31.42 | L82: 38.84 | M82: 35720 | N82: 39120 | O82: 50110 | P82: 65350 | Q82: 80780
A83: Mechanical Rough In Mechanical Finishing | B83: Installation, Maintenance, and Repair Occupations (49-0000) | C83: 6045020 | D83: 0.2 | E83: 29.63 | F83: 61640 | G83: 0.2 | H83: 17.4 | I83: 21.64 | J83: 27.99 | K83: 36.11 | L83: 45.39 | M83: 36190 | N83: 45000 | O83: 58230 | P83: 75100 | Q83: 94420
B84: First-Line Supervisors of Mechanics, Installers, and Repairers (49-1011) | C84: 600680 | D84: 0.5 | E84: 39.87 | F84: 82930 | G84: 0.30000001 | H84: 23.3 | I84: 29.44 | J84: 37.64 | K84: 47.9 | L84: 59.75 | M84: 48460 | N84: 61240 | O84: 78300 | P84: 99630 | Q84: 124280
B85: Footnotes:
B86: (1) Estimates for detailed occupations do not sum to the totals because the totals include occupations not shown separately. Estimates do not include self-employed workers.
B87: (2) Annual wages have been calculated by multiplying the corresponding hourly wage by 2,080 hours.
B88: (3) The relative standard error (RSE) is a measure of the reliability of a survey statistic. The smaller the relative standard error, the more precise the estimate.
B90: SOC code: Standard Occupational Classification code -- see http://www.bls.gov/soc/home.htm
B92: Data extracted on February 12, 2026

Sheet OEWS - California May 2024
B1: Multiple occupations for one geographical area
B3: Area: California
B4: Period: May 2024
A6: Capstone Construction Process Cat. | B6: Occupation (SOC code) | C6: Employment (1) | D6: Employment percent relative standard error (3) | E6: Hourly mean wage | F6: Annual mean wage (2) | G6: Wage percent relative standard error (3) | H6: Hourly 10th percentile wage | I6: Hourly 25th percentile wage | J6: Hourly median wage | K6: Hourly 75th percentile wage | L6: Hourly 90th percentile wage | M6: Annual 10th percentile wage (2) | N6: Annual 25th percentile wage (2) | O6: Annual median wage (2) | P6: Annual 75th percentile wage (2) | Q6: Annual 90th percentile wage (2) | R6: Employment per 1,000 jobs | S6: Location Quotient
B7: Construction and Extraction Occupations (47-0000) | C7: 679190 | D7: 0.69999999 | E7: 37.46 | F7: 77920 | G7: 0.69999999 | H7: 21.92 | I7: 25.96 | J7: 34.23 | K7: 46.23 | L7: 60.03 | M7: 45590 | N7: 53990 | O7: 71200 | P7: 96170 | Q7: 124870 | R7: 37.612 | S7: 0.91000003
B8: First-Line Supervisors of Construction Trades and Extraction Workers (47-1011) | C8: 72660 | D8: 2.2 | E8: 49.04 | F8: 101990 | G8: 0.89999998 | H8: 29.11 | I8: 36.73 | J8: 46.67 | K8: 60.31 | L8: 73.96 | M8: 60540 | N8: 76390 | O8: 97080 | P8: 125450 | Q8: 153830 | R8: 4.0240002 | S8: 0.76999998
B9: Boilermakers (47-2011) | C9: 690 | D9: 28.1 | E9: 52.12 | F9: 108420 | G9: 2.5999999 | H9: 35.91 | I9: 51.66 | J9: 51.73 | K9: 58.77 | L9: 61.07 | M9: 74690 | N9: 107450 | O9: 107600 | P9: 122240 | Q9: 127020 | R9: 0.037999999 | S9: 0.57999998
B10: Brickmasons and Blockmasons (47-2021) | C10: 3480 | D10: 18.700001 | E10: 34.81 | F10: 72410 | G10: 4.6999998 | H10: 23.06 | I10: 27 | J10: 31.93 | K10: 39.02 | L10: 51.68 | M10: 47950 | N10: 56160 | O10: 66420 | P10: 81170 | Q10: 107490 | R10: 0.192 | S10: 0.55000001
B11: Stonemasons (47-2022) | C11: 790 | D11: 23.700001 | E11: 31.78 | F11: 66110 | G11: 3.5 | H11: 22.78 | I11: 25.21 | J11: 31.19 | K11: 35.86 | L11: 39.56 | M11: 47370 | N11: 52430 | O11: 64880 | P11: 74590 | Q11: 82280 | R11: 0.044 | S11: 0.77999997
A12: Interior Wall framing Interior Wall sheathing Exterior Walls framing Exterior Wall sheathing Carpentry | B12: Carpenters (47-2031) | C12: 106500 | D12: 3.4000001 | E12: 37.35 | F12: 77680 | G12: 1.4 | H12: 22.68 | I12: 27.84 | J12: 35.97 | K12: 45.85 | L12: 57.3 | M12: 47170 | N12: 57900 | O12: 74820 | P12: 95360 | Q12: 119190 | R12: 5.8979998 | S12: 1.3
B13: Carpet Installers (47-2041) | C13: 2600 | D13: 19 | E13: 26.58 | F13: 55280 | G13: 3.9000001 | H13: 17.04 | I13: 17.94 | J13: 26.36 | K13: 31.44 | L13: 37.77 | M13: 35430 | N13: 37320 | O13: 54840 | P13: 65390 | Q13: 78560 | R13: 0.14399999 | S13: 1.48
A14: Floor framing Floor sheathing | B14: Floor Layers, Except Carpet, Wood, and Hard Tiles (47-2042) | C14: 6360 | D14: 11.8 | E14: 34.68 | F14: 72130 | G14: 4 | H14: 19.26 | I14: 24.15 | J14: 29.22 | K14: 46.49 | L14: 57.16 | M14: 40070 | N14: 50220 | O14: 60780 | P14: 96690 | Q14: 118900 | R14: 0.352 | S14: 2.1800001
B15: Floor Sanders and Finishers (47-2043) | C15: (8) - | D15: (8) - | E15: 28.27 | F15: 58800 | G15: 20.4 | H15: 19.1 | I15: 19.18 | J15: 21.72 | K15: 37.98 | L15: 40.73 | M15: 39730 | N15: 39900 | O15: 45180 | P15: 78990 | Q15: 84730 | R15: (8) - | S15: (8) -
A16: Floor Finishing | B16: Tile and Stone Setters (47-2044) | C16: 7250 | D16: 7.1999998 | E16: 29.12 | F16: 60580 | G16: 2.4000001 | H16: 19 | I16: 22.92 | J16: 27.65 | K16: 32.32 | L16: 38.71 | M16: 39530 | N16: 47670 | O16: 57510 | P16: 67220 | Q16: 80510 | R16: 0.40099999 | S16: 1.6
B17: Cement Masons and Concrete Finishers (47-2051) | C17: 29030 | D17: 5.1999998 | E17: 34.82 | F17: 72430 | G17: 1.7 | H17: 21.82 | I17: 24.95 | J17: 30.9 | K17: 42.51 | L17: 48.6 | M17: 45380 | N17: 51890 | O17: 64280 | P17: 88420 | Q17: 101090 | R17: 1.608 | S17: 1.21
B18: Terrazzo Workers and Finishers (47-2053) | C18: 220 | D18: 30.799999 | E18: 20.19 | F18: 42000 | G18: 1.5 | H18: 16.7 | I18: 16.97 | J18: 19.39 | K18: 22.57 | L18: 23.46 | M18: 34740 | N18: 35290 | O18: 40330 | P18: 46940 | Q18: 48790 | R18: 0.012 | S18: 1.3200001
A19: Site Work Foundations Assembly | B19: Construction Laborers (47-2061) | C19: 85370 | D19: 3.0999999 | E19: 31.8 | F19: 66140 | G19: 1.2 | H19: 20.39 | I19: 23.01 | J19: 29.11 | K19: 37.88 | L19: 45.29 | M19: 42410 | N19: 47850 | O19: 60540 | P19: 78790 | Q19: 94200 | R19: 4.7270002 | S19: 0.69
B20: Paving, Surfacing, and Tamping Equipment Operators (47-2071) | C20: 1920 | D20: 10.4 | E20: 43.28 | F20: 90010 | G20: 3.7 | H20: 24.78 | I20: 29.19 | J20: 38.2 | K20: 59.36 | L20: 63.58 | M20: 51540 | N20: 60720 | O20: 79460 | P20: 123470 | Q20: 132240 | R20: 0.106 | S20: 0.36000001
B21: Pile Driver Operators (47-2072) | C21: 790 | D21: 30.9 | E21: 50.83 | F21: 105720 | G21: 4.3000002 | H21: 32.7 | I21: 42.56 | J21: 50.94 | K21: 59.32 | L21: 64.01 | M21: 68010 | N21: 88520 | O21: 105950 | P21: 123380 | Q21: 133140 | R21: 0.044 | S21: 2.22
B22: Operating Engineers and Other Construction Equipment Operators (47-2073) | C22: 36040 | D22: 3.4000001 | E22: 45.04 | F22: 93680 | G22: 1.2 | H22: 26.31 | I22: 31.66 | J22: 42.85 | K22: 58.93 | L22: 63.08 | M22: 54730 | N22: 65840 | O22: 89120 | P22: 122570 | Q22: 131200 | R22: 1.9960001 | S22: 0.66000003
A23: Drywall | B23: Drywall and Ceiling Tile Installers (47-2081) | C23: 27350 | D23: 4.3000002 | E23: 36.64 | F23: 76210 | G23: 1.8 | H23: 22.09 | I23: 27.9 | J23: 31.67 | K23: 44.96 | L23: 58.72 | M23: 45950 | N23: 58020 | O23: 65880 | P23: 93520 | Q23: 122130 | R23: 1.515 | S23: 2.8199999
B24: Tapers (47-2082) | C24: 3790 | D24: 10 | E24: 35.73 | F24: 74310 | G24: 3.5 | H24: 21.49 | I24: 28.22 | J24: 33.49 | K24: 39.24 | L24: 53.39 | M24: 44690 | N24: 58700 | O24: 69670 | P24: 81630 | Q24: 111040 | R24: 0.20999999 | S24: 2.5899999
A25: Electrical Rough in Electrical Finishing | B25: Electricians (47-2111) | C25: 73420 | D25: 3 | E25: 41.24 | F25: 85780 | G25: 2.0999999 | H25: 22.42 | I25: 28.57 | J25: 36.8 | K25: 49.87 | L25: 65.73 | M25: 46630 | N25: 59420 | O25: 76540 | P25: 103720 | Q25: 136710 | R25: 4.066 | S25: 0.83999997
B26: Glaziers (47-2121) | C26: 7880 | D26: 9.6000004 | E26: 36.53 | F26: 75980 | G26: 3.7 | H26: 23 | I26: 27.86 | J26: 31.66 | K26: 48.33 | L26: 57.16 | M26: 47840 | N26: 57940 | O26: 65850 | P26: 100520 | Q26: 118880 | R26: 0.43599999 | S26: 1.1799999
A27: Insulation | B27: Insulation Workers, Floor, Ceiling, and Wall (47-2131) | C27: 2190 | D27: 14.1 | E27: 24.74 | F27: 51450 | G27: 4.3000002 | H27: 17.77 | I27: 18.47 | J27: 21.45 | K27: 27.59 | L27: 37.7 | M27: 36960 | N27: 38420 | O27: 44620 | P27: 57390 | Q27: 78420 | R27: 0.121 | S27: 0.47999999
B28: Insulation Workers, Mechanical (47-2132) | C28: 1260 | D28: 37.700001 | E28: 55.23 | F28: 114870 | G28: 13.1 | H28: 23.35 | I28: 35.42 | J28: 57.64 | K28: 74.55 | L28: 84.95 | M28: 48570 | N28: 73680 | O28: 119890 | P28: 155060 | Q28: 176690 | R28: 0.07 | S28: 0.41999999
A29: Painting | B29: Painters, Construction and Maintenance (47-2141) | C29: 37780 | D29: 3 | E29: 29.36 | F29: 61070 | G29: 1.5 | H29: 20.3 | I29: 22.95 | J29: 27.62 | K29: 32.89 | L29: 43.21 | M29: 42230 | N29: 47730 | O29: 57450 | P29: 68410 | Q29: 89870 | R29: 2.092 | S29: 1.4400001
B30: Paperhangers (47-2142) | C30: (8) - | D30: (8) - | E30: 31.46 | F30: 65440 | G30: 10.1 | H30: 20.47 | I30: 23.2 | J30: 27.56 | K30: 36.54 | L30: 51.48 | M30: 42570 | N30: 48260 | O30: 57330 | P30: 75990 | Q30: 107090 | R30: (8) - | S30: (8) -
B31: Pipelayers (47-2151) | C31: 1720 | D31: 23.299999 | E31: 37.02 | F31: 77000 | G31: 5.6999998 | H31: 22.8 | I31: 27.02 | J31: 37.54 | K31: 47.49 | L31: 54.34 | M31: 47420 | N31: 56200 | O31: 78090 | P31: 98770 | Q31: 113030 | R31: 0.094999999 | S31: 0.44
A32: Plumbing Rough In Plumbing Finishing | B32: Plumbers, Pipefitters, and Steamfitters (47-2152) | C32: 45460 | D32: 5.4000001 | E32: 37.67 | F32: 78350 | G32: 2 | H32: 21.87 | I32: 27.45 | J32: 32.88 | K32: 45.83 | L32: 60.96 | M32: 45480 | N32: 57090 | O32: 68390 | P32: 95320 | Q32: 126790 | R32: 2.517 | S32: 0.85000002
A33: Exterior Wall Finishing | B33: Plasterers and Stucco Masons (47-2161) | C33: 8370 | D33: 9.1999998 | E33: 31.08 | F33: 64640 | G33: 2.5999999 | H33: 20.09 | I33: 23.38 | J33: 29.03 | K33: 36.46 | L33: 47.22 | M33: 41790 | N33: 48630 | O33: 60370 | P33: 75840 | Q33: 98220 | R33: 0.46399999 | S33: 3.4200001
B34: Reinforcing Iron and Rebar Workers (47-2171) | C34: 1660 | D34: 19.6 | E34: 32.96 | F34: 68560 | G34: 5.8000002 | H34: 21.27 | I34: 23.66 | J34: 29.54 | K34: 45.02 | L34: 48.4 | M34: 44240 | N34: 49210 | O34: 61440 | P34: 93630 | Q34: 100660 | R34: 0.092 | S34: 1
A35: Roof framing Roof sheathing and waterproofing Exterior Roof Finishing | B35: Roofers (47-2181) | C35: 21110 | D35: 3.9000001 | E35: 32.73 | F35: 68080 | G35: 2.7 | H35: 22.64 | I35: 28.2 | J35: 30.31 | K35: 36.79 | L35: 45.71 | M35: 47090 | N35: 58650 | O35: 63040 | P35: 76520 | Q35: 95080 | R35: 1.169 | S35: 1.3200001
B36: Sheet Metal Workers (47-2211) | C36: 9180 | D36: 10.1 | E36: 41.6 | F36: 86530 | G36: 2.0999999 | H36: 22.5 | I36: 28.72 | J36: 38.28 | K36: 51.75 | L36: 63.57 | M36: 46800 | N36: 59730 | O36: 79630 | P36: 107640 | Q36: 132220 | R36: 0.50800002 | S36: 0.67000002
B37: Structural Iron and Steel Workers (47-2221) | C37: 6970 | D37: 11.7 | E37: 36.37 | F37: 75650 | G37: 4.3000002 | H37: 22.16 | I37: 23.79 | J37: 34.64 | K37: 48.86 | L37: 52.17 | M37: 46100 | N37: 49480 | O37: 72050 | P37: 101640 | Q37: 108510 | R37: 0.38600001 | S37: 0.92000002
B38: Solar Photovoltaic Installers (47-2231) | C38: 8970 | D38: 12.8 | E38: 31.94 | F38: 66440 | G38: 2.4000001 | H38: 23.1 | I38: 25.73 | J38: 29.23 | K38: 37.12 | L38: 45.62 | M38: 48050 | N38: 53510 | O38: 60790 | P38: 77220 | Q38: 94890 | R38: 0.49599999 | S38: 2.71
B39: Helpers--Brickmasons, Blockmasons, Stonemasons, and Tile and Marble Setters (47-3011) | C39: 3900 | D39: 11.2 | E39: 26.36 | F39: 54820 | G39: 2.2 | H39: 18.24 | I39: 21.87 | J39: 24.87 | K39: 29.74 | L39: 35.8 | M39: 37930 | N39: 45480 | O39: 51720 | P39: 61860 | Q39: 74460 | R39: 0.21600001 | S39: 2.1300001
B40: Helpers--Carpenters (47-3012) | C40: 2250 | D40: 24.4 | E40: 24.49 | F40: 50940 | G40: 3.7 | H40: 17.77 | I40: 20.55 | J40: 22 | K40: 25.34 | L40: 40.8 | M40: 36950 | N40: 42740 | O40: 45760 | P40: 52710 | Q40: 84860 | R40: 0.124 | S40: 0.77999997
B41: Helpers--Electricians (47-3013) | C41: 1790 | D41: 38.700001 | E41: 25.36 | F41: 52760 | G41: 10.3 | H41: 17.79 | I41: 18.58 | J41: 22.86 | K41: 28.34 | L41: 38.66 | M41: 36990 | N41: 38650 | O41: 47540 | P41: 58940 | Q41: 80410 | R41: 0.098999999 | S41: 0.23999999
B42: Helpers--Painters, Paperhangers, Plasterers, and Stucco Masons (47-3014) | C42: 1920 | D42: 16.1 | E42: 23.32 | F42: 48510 | G42: 2.3 | H42: 18.06 | I42: 19 | J42: 21.99 | K42: 24.39 | L42: 27.9 | M42: 37570 | N42: 39520 | O42: 45730 | P42: 50730 | Q42: 58040 | R42: 0.106 | S42: 2.27
B43: Helpers--Pipelayers, Plumbers, Pipefitters, and Steamfitters (47-3015) | C43: 2230 | D43: 20.5 | E43: 24.9 | F43: 51790 | G43: 4.5 | H43: 18.62 | I43: 21.22 | J43: 24.02 | K43: 29.15 | L43: 30.75 | M43: 38720 | N43: 44140 | O43: 49970 | P43: 60630 | Q43: 63970 | R43: 0.124 | S43: 0.44
B44: Helpers--Roofers (47-3016) | C44: 910 | D44: 29.700001 | E44: 24.73 | F44: 51430 | G44: 3.5 | H44: 18.21 | I44: 22.2 | J44: 25.54 | K44: 27.63 | L44: 29.13 | M44: 37880 | N44: 46180 | O44: 53130 | P44: 57480 | Q44: 60590 | R44: 0.050999999 | S44: 1.51
B45: Helpers, Construction Trades, All Other (47-3019) | C45: 4050 | D45: 11.5 | E45: 23.95 | F45: 49810 | G45: 2.2 | H45: 18.2 | I45: 19.37 | J45: 22.42 | K45: 26.13 | L45: 31.08 | M45: 37850 | N45: 40290 | O45: 46640 | P45: 54340 | Q45: 64640 | R45: 0.22400001 | S45: 1.35
A46: All Inspections | B46: Construction and Building Inspectors (47-4011) | C46: 14010 | D46: 6.5999999 | E46: 49.76 | F46: 103500 | G46: 2.8 | H46: 25.23 | I46: 36 | J46: 48.64 | K46: 61.78 | L46: 78 | M46: 52480 | N46: 74890 | O46: 101160 | P46: 128490 | Q46: 162240 | R46: 0.77600002 | S46: 0.87
A47: Mechanical Rough In Mechanical Finishing | B47: Installation, Maintenance, and Repair Occupations (49-0000) | C47: 544790 | D47: 1.1 | E47: 33.8 | F47: 70310 | G47: 0.60000002 | H47: 19.13 | I47: 23.24 | J47: 30.55 | K47: 39.43 | L47: 50.89 | M47: 39800 | N47: 48340 | O47: 63550 | P47: 82020 | Q47: 105840 | R47: 30.169001 | S47: 0.76999998
B48: First-Line Supervisors of Mechanics, Installers, and Repairers (49-1011) | C48: 51520 | D48: 4.4000001 | E48: 46.25 | F48: 96200 | G48: 1.2 | H48: 27.29 | I48: 33.75 | J48: 43.21 | K48: 55.74 | L48: 71.68 | M48: 56760 | N48: 70190 | O48: 89880 | P48: 115940 | Q48: 149090 | R48: 2.8529999 | S48: 0.73000002
B49: Footnotes:
B50: (1) Estimates for detailed occupations do not sum to the totals because the totals include occupations not shown separately. Estimates do not include self-employed workers.
B51: (2) Annual wages have been calculated by multiplying the corresponding hourly wage by 2,080 hours.
B52: (3) The relative standard error (RSE) is a measure of the reliability of a survey statistic. The smaller the relative standard error, the more precise the estimate.
B53: (8) Estimate not released.
B55: SOC code: Standard Occupational Classification code -- see http://www.bls.gov/soc/home.htm
A57: All Inspections | B57: Data extracted on February 13, 2026
A83: Mechanical Rough In Mechanical Finishing

Sheet OEWS - Utah May 2024
B1: Multiple occupations for one geographical area
B3: Area: Utah
B4: Period: May 2024
A6: Capstone Construction Process Cat. | B6: Occupation (SOC code) | C6: Employment (1) | D6: Employment percent relative standard error (3) | E6: Hourly mean wage | F6: Annual mean wage (2) | G6: Wage percent relative standard error (3) | H6: Hourly 10th percentile wage | I6: Hourly 25th percentile wage | J6: Hourly median wage | K6: Hourly 75th percentile wage | L6: Hourly 90th percentile wage | M6: Annual 10th percentile wage (2) | N6: Annual 25th percentile wage (2) | O6: Annual median wage (2) | P6: Annual 75th percentile wage (2) | Q6: Annual 90th percentile wage (2) | R6: Employment per 1,000 jobs | S6: Location Quotient
B7: Construction and Extraction Occupations (47-0000) | C7: 111490 | D7: 1.6 | E7: 27.78 | F7: 57770 | G7: 0.69999999 | H7: 17.87 | I7: 21.94 | J7: 25.85 | K7: 31.94 | L7: 38.88 | M7: 37170 | N7: 45630 | O7: 53780 | P7: 66430 | Q7: 80860 | R7: 65.208 | S7: 1.58
B8: First-Line Supervisors of Construction Trades and Extraction Workers (47-1011) | C8: 13250 | D8: 3.3 | E8: 38.09 | F8: 79230 | G8: 1.1 | H8: 24.97 | I8: 29.85 | J8: 36.58 | K8: 44.99 | L8: 53.69 | M8: 51940 | N8: 62080 | O8: 76080 | P8: 93580 | Q8: 111680 | R8: 7.7490001 | S8: 1.48
B9: Brickmasons and Blockmasons (47-2021) | C9: 1810 | D9: 18.1 | E9: 27.69 | F9: 57590 | G9: 3.0999999 | H9: 18.84 | I9: 23.31 | J9: 27.09 | K9: 31.8 | L9: 35.56 | M9: 39180 | N9: 48480 | O9: 56340 | P9: 66150 | Q9: 73960 | R9: 1.059 | S9: 3.05
B10: Stonemasons (47-2022) | C10: 330 | D10: 35.700001 | E10: 26.8 | F10: 55750 | G10: 7.6999998 | H10: 17.5 | I10: 19.05 | J10: 24.34 | K10: 28.27 | L10: 38.92 | M10: 36400 | N10: 39620 | O10: 50630 | P10: 58800 | Q10: 80950 | R10: 0.192 | S10: 3.3800001
A11: Interior Wall framing Interior Wall sheathing Exterior Walls framing Exterior Wall sheathing Carpentry | B11: Carpenters (47-2031) | C11: 14040 | D11: 5.8000002 | E11: 26.26 | F11: 54620 | G11: 1.3 | H11: 18.37 | I11: 21.85 | J11: 24.86 | K11: 29.67 | L11: 35.66 | M11: 38200 | N11: 45450 | O11: 51720 | P11: 61720 | Q11: 74180 | R11: 8.2119999 | S11: 1.8099999
B12: Carpet Installers (47-2041) | C12: 350 | D12: 23.799999 | E12: 21.13 | F12: 43950 | G12: 8.8999996 | H12: 14.81 | I12: 17.08 | J12: 20.81 | K12: 23.07 | L12: 30.06 | M12: 30810 | N12: 35520 | O12: 43270 | P12: 47990 | Q12: 62530 | R12: 0.207 | S12: 2.1300001
A13: Floor framing Floor sheathing | B13: Floor Layers, Except Carpet, Wood, and Hard Tiles (47-2042) | C13: 260 | D13: 30 | E13: 22.81 | F13: 47450 | G13: 7.5 | H13: 15.25 | I13: 17.04 | J13: 21.12 | K13: 25.08 | L13: 35.32 | M13: 31730 | N13: 35450 | O13: 43930 | P13: 52170 | Q13: 73470 | R13: 0.152 | S13: 0.94
A14: Floor Finishing | B14: Tile and Stone Setters (47-2044) | C14: 1950 | D14: 11.3 | E14: 24.67 | F14: 51320 | G14: 4.4000001 | H14: 14.95 | I14: 18.47 | J14: 23.46 | K14: 29 | L14: 36.68 | M14: 31100 | N14: 38410 | O14: 48790 | P14: 60320 | Q14: 76280 | R14: 1.138 | S14: 4.5300002
B15: Cement Masons and Concrete Finishers (47-2051) | C15: 5700 | D15: 9.1000004 | E15: 26.49 | F15: 55100 | G15: 1.4 | H15: 21.57 | I15: 22.74 | J15: 26.7 | K15: 29.64 | L15: 31.81 | M15: 44860 | N15: 47290 | O15: 55540 | P15: 61650 | Q15: 66160 | R15: 3.3329999 | S15: 2.5
A16: Site Work Foundations Assembly | B16: Construction Laborers (47-2061) | C16: 22230 | D16: 6.6999998 | E16: 22.96 | F16: 47750 | G16: 2 | H16: 15.68 | I16: 18.25 | J16: 22.16 | K16: 24.84 | L16: 30.69 | M16: 32610 | N16: 37960 | O16: 46100 | P16: 51660 | Q16: 63840 | R16: 12.999 | S16: 1.9
B17: Paving, Surfacing, and Tamping Equipment Operators (47-2071) | C17: 540 | D17: 30.6 | E17: 25.63 | F17: 53320 | G17: 3.7 | H17: 20.72 | I17: 21.53 | J17: 23.02 | K17: 30.01 | L17: 33.78 | M17: 43110 | N17: 44780 | O17: 47890 | P17: 62420 | Q17: 70270 | R17: 0.317 | S17: 1.0700001
B18: Operating Engineers and Other Construction Equipment Operators (47-2073) | C18: 6320 | D18: 4.3000002 | E18: 28.28 | F18: 58820 | G18: 0.89999998 | H18: 21.94 | I18: 24.17 | J18: 28.73 | K18: 30.69 | L18: 35.21 | M18: 45630 | N18: 50270 | O18: 59760 | P18: 63840 | Q18: 73240 | R18: 3.6949999 | S18: 1.21
A19: Drywall | B19: Drywall and Ceiling Tile Installers (47-2081) | C19: 1830 | D19: 12.7 | E19: 24.65 | F19: 51270 | G19: 2.0999999 | H19: 17.24 | I19: 19 | J19: 24.45 | K19: 28.43 | L19: 33 | M19: 35850 | N19: 39520 | O19: 50860 | P19: 59140 | Q19: 68630 | R19: 1.0700001 | S19: 1.99
B20: Tapers (47-2082) | C20: 400 | D20: 25.9 | E20: 25.91 | F20: 53880 | G20: 4.5999999 | H20: 17.12 | I20: 19.26 | J20: 26.24 | K20: 29.39 | L20: 36.32 | M20: 35600 | N20: 40060 | O20: 54580 | P20: 61120 | Q20: 75540 | R20: 0.234 | S20: 2.8800001
A21: Electrical Rough in Electrical Finishing | B21: Electricians (47-2111) | C21: 11360 | D21: 6.0999999 | E21: 30.3 | F21: 63010 | G21: 1.7 | H21: 18.38 | I21: 22.94 | J21: 29.53 | K21: 37.5 | L21: 39.62 | M21: 38230 | N21: 47720 | O21: 61430 | P21: 78000 | Q21: 82410 | R21: 6.6430001 | S21: 1.38
B22: Glaziers (47-2121) | C22: 740 | D22: 22.6 | E22: 26.31 | F22: 54720 | G22: 3.5999999 | H22: 20.44 | I22: 22.62 | J22: 24.35 | K22: 28.86 | L22: 31.61 | M22: 42510 | N22: 47050 | O22: 50640 | P22: 60030 | Q22: 65750 | R22: 0.43099999 | S22: 1.16
A23: Insulation | B23: Insulation Workers, Floor, Ceiling, and Wall (47-2131) | C23: 350 | D23: 29.4 | E23: 22.48 | F23: 46760 | G23: 1.9 | H23: 18.14 | I23: 19.05 | J23: 23.23 | K23: 24.44 | L23: 27.35 | M23: 37740 | N23: 39620 | O23: 48330 | P23: 50830 | Q23: 56880 | R23: 0.205 | S23: 0.81999999
B24: Insulation Workers, Mechanical (47-2132) | C24: 350 | D24: 25 | E24: 23.24 | F24: 48340 | G24: 7.1999998 | H24: 16.94 | I24: 20.39 | J24: 22.02 | K24: 28.03 | L24: 29.48 | M24: 35230 | N24: 42420 | O24: 45800 | P24: 58300 | Q24: 61320 | R24: 0.20299999 | S24: 1.22
A25: Painting | B25: Painters, Construction and Maintenance (47-2141) | C25: 3350 | D25: 5.6999998 | E25: 22.24 | F25: 46270 | G25: 1.6 | H25: 17.37 | I25: 18.02 | J25: 22.07 | K25: 23.82 | L25: 28.74 | M25: 36130 | N25: 37480 | O25: 45900 | P25: 49540 | Q25: 59780 | R25: 1.957 | S25: 1.35
B26: Pipelayers (47-2151) | C26: 710 | D26: 18.799999 | E26: 25.43 | F26: 52890 | G26: 1 | H26: 23.01 | I26: 23.45 | J26: 24.61 | K26: 26.92 | L26: 28.94 | M26: 47860 | N26: 48780 | O26: 51180 | P26: 55990 | Q26: 60190 | R26: 0.41499999 | S26: 1.91
A27: Plumbing Rough In Plumbing Finishing | B27: Plumbers, Pipefitters, and Steamfitters (47-2152) | C27: 6770 | D27: 8 | E27: 30.1 | F27: 62600 | G27: 1.7 | H27: 19.12 | I27: 23.28 | J27: 29.65 | K27: 37 | L27: 39.16 | M27: 39770 | N27: 48410 | O27: 61680 | P27: 76970 | Q27: 81460 | R27: 3.9579999 | S27: 1.34
A28: Exterior Wall Finishing | B28: Plasterers and Stucco Masons (47-2161) | C28: 1200 | D28: 16.700001 | E28: 27.61 | F28: 57420 | G28: 5.0999999 | H28: 17.3 | I28: 23.03 | J28: 25.56 | K28: 34.23 | L28: 38.12 | M28: 35980 | N28: 47910 | O28: 53170 | P28: 71210 | Q28: 79280 | R28: 0.699 | S28: 5.1599998
B29: Reinforcing Iron and Rebar Workers (47-2171) | C29: 280 | D29: 35.200001 | E29: 24.64 | F29: 51240 | G29: 7.6999998 | H29: 20.66 | I29: 21.65 | J29: 24.04 | K29: 26.4 | L29: 30.23 | M29: 42970 | N29: 45030 | O29: 49990 | P29: 54900 | Q29: 62880 | R29: 0.16599999 | S29: 1.8099999
A30: Roof framing Roof sheathing and waterproofing Exterior Roof Finishing | B30: Roofers (47-2181) | C30: 2940 | D30: 7 | E30: 25.36 | F30: 52750 | G30: 2.7 | H30: 16.24 | I30: 21.78 | J30: 23.94 | K30: 30.09 | L30: 37.81 | M30: 33770 | N30: 45310 | O30: 49800 | P30: 62590 | Q30: 78640 | R30: 1.722 | S30: 1.9400001
B31: Sheet Metal Workers (47-2211) | C31: 1870 | D31: 17 | E31: 29.96 | F31: 62310 | G31: 3.0999999 | H31: 20.04 | I31: 23.25 | J31: 29.08 | K31: 36.66 | L31: 42.26 | M31: 41680 | N31: 48360 | O31: 60490 | P31: 76250 | Q31: 87900 | R31: 1.091 | S31: 1.4299999
B32: Structural Iron and Steel Workers (47-2221) | C32: 1200 | D32: 17.700001 | E32: 24.01 | F32: 49940 | G32: 5.1999998 | H32: 16.26 | I32: 18.34 | J32: 23 | K32: 30.82 | L32: 32.38 | M32: 33820 | N32: 38150 | O32: 47840 | P32: 64110 | Q32: 67350 | R32: 0.704 | S32: 1.6799999
B33: Solar Photovoltaic Installers (47-2231) | C33: 540 | D33: 21.299999 | E33: 25.86 | F33: 53790 | G33: 4.9000001 | H33: 17.65 | I33: 20 | J33: 23.06 | K33: 30.25 | L33: 37.31 | M33: 36710 | N33: 41600 | O33: 47960 | P33: 62920 | Q33: 77600 | R33: 0.31799999 | S33: 1.74
B34: Helpers--Brickmasons, Blockmasons, Stonemasons, and Tile and Marble Setters (47-3011) | C34: 380 | D34: 22.6 | E34: 23.21 | F34: 48290 | G34: 4.5999999 | H34: 17.89 | I34: 19.49 | J34: 23.12 | K34: 25.02 | L34: 31.17 | M34: 37220 | N34: 40550 | O34: 48090 | P34: 52050 | Q34: 64830 | R34: 0.223 | S34: 2.2
B35: Helpers--Carpenters (47-3012) | C35: 620 | D35: 47.799999 | E35: 20.58 | F35: 42800 | G35: 5.9000001 | H35: 14 | I35: 19.34 | J35: 20.72 | K35: 21.71 | L35: 25 | M35: 29130 | N35: 40240 | O35: 43090 | P35: 45160 | Q35: 52000 | R35: 0.36399999 | S35: 2.28
B36: Helpers--Electricians (47-3013) | C36: 310 | D36: 46.200001 | E36: 21.4 | F36: 44500 | G36: 8.8000002 | H36: 18.08 | I36: 19.18 | J36: 20.25 | K36: 24.01 | L36: 29.83 | M36: 37610 | N36: 39880 | O36: 42120 | P36: 49940 | Q36: 62050 | R36: 0.17900001 | S36: 0.43000001
B37: Helpers--Painters, Paperhangers, Plasterers, and Stucco Masons (47-3014) | C37: 150 | D37: 32.400002 | E37: 19.61 | F37: 40780 | G37: 1 | H37: 16.7 | I37: 17 | J37: 19.53 | K37: 20.47 | L37: 21.18 | M37: 34730 | N37: 35360 | O37: 40620 | P37: 42570 | Q37: 44050 | R37: 0.089000002 | S37: 1.9
B38: Helpers--Pipelayers, Plumbers, Pipefitters, and Steamfitters (47-3015) | C38: 240 | D38: 33.200001 | E38: 20.43 | F38: 42500 | G38: 6.0999999 | H38: 13.15 | I38: 14.13 | J38: 21.55 | K38: 23.84 | L38: 26.2 | M38: 27360 | N38: 29390 | O38: 44810 | P38: 49580 | Q38: 54500 | R38: 0.141 | S38: 0.5
B39: Helpers, Construction Trades, All Other (47-3019) | C39: 230 | D39: 24.6 | E39: 18.83 | F39: 39170 | G39: 6.5999999 | H39: 11 | I39: 15.41 | J39: 17.54 | K39: 24.04 | L39: 25.22 | M39: 22890 | N39: 32060 | O39: 36490 | P39: 49990 | Q39: 52460 | R39: 0.13600001 | S39: 0.81999999
A40: All Inspections | B40: Construction and Building Inspectors (47-4011) | C40: 1260 | D40: 8.3999996 | E40: 34.32 | F40: 71390 | G40: 1.8 | H40: 20.88 | I40: 27.06 | J40: 34.15 | K40: 40.37 | L40: 48.11 | M40: 43420 | N40: 56280 | O40: 71040 | P40: 83970 | Q40: 100070 | R40: 0.73900002 | S40: 0.82999998
A41: Mechanical Rough In Mechanical Finishing | B41: Installation, Maintenance, and Repair Occupations (49-0000) | C41: 66680 | D41: 1.5 | E41: 28.5 | F41: 59270 | G41: 0.60000002 | H41: 17.06 | I41: 21.31 | J41: 27.46 | K41: 34.63 | L41: 41.03 | M41: 35490 | N41: 44320 | O41: 57110 | P41: 72040 | Q41: 85350 | R41: 38.998001 | S41: 0.99000001
B42: First-Line Supervisors of Mechanics, Installers, and Repairers (49-1011) | C42: 6410 | D42: 3.9000001 | E42: 38.77 | F42: 80650 | G42: 1.2 | H42: 23.18 | I42: 29 | J42: 37.2 | K42: 46.69 | L42: 58.28 | M42: 48210 | N42: 60320 | O42: 77380 | P42: 97120 | Q42: 121220 | R42: 3.75 | S42: 0.95999998
B43: Footnotes:
B44: (1) Estimates for detailed occupations do not sum to the totals because the totals include occupations not shown separately. Estimates do not include self-employed workers.
B45: (2) Annual wages have been calculated by multiplying the corresponding hourly wage by 2,080 hours.
B46: (3) The relative standard error (RSE) is a measure of the reliability of a survey statistic. The smaller the relative standard error, the more precise the estimate.
B48: SOC code: Standard Occupational Classification code -- see http://www.bls.gov/soc/home.htm
B50: Data extracted on February 13, 2026
A57: All Inspections
A83: Mechanical Rough In Mechanical Finishing

Sheet Process Lookup
A1: Select a Process | C1: Configuration | D1: Process Cost | E1: Process Profit | F1: Process Selling Price | G1: Profit Margin of Process | I1: Unit of measure | K1: Notes
A2: Site Work | C2: LA - Site Built | D2: {=_xlfn.XLOOKUP( $A$2, INDIRECT("'" & C2 & "'!A:A"), INDIRECT( "'" & C2 & "'!" & IF(ISNUMBER(SEARCH("Local",C2)),"F","G") & ":" & IF(ISNUMBER(SEARCH("Local",C2)),"F","G") ) )} -> 24.32 | E2: {=_xlfn.XLOOKUP( $A$2, INDIRECT("'" & $C2 & "'!A:A"), INDIRECT( "'" & $C2 & "'!" & IF(ISNUMBER(SEARCH("Local",$C2)),"E","F") & ":" & IF(ISNUMBER(SEARCH("Local",$C2)),"E","F") ) )*INDIRECT("'" & $C2 & "'!C41")} -> 3.0064626 | F2: =E2+D2 -> 27.326463 | G2: =E2/F2 -> 0.11002019 | I2: ='Parameter Adjustment'!Z2 -> Square foot | K2: *Go to parameter adjustment page to move
C3: LA - Local | D3: {=_xlfn.XLOOKUP( $A$2, INDIRECT("'" & C3 & "'!A:A"), INDIRECT( "'" & C3 & "'!" & IF(ISNUMBER(SEARCH("Local",C3)),"F","G") & ":" & IF(ISNUMBER(SEARCH("Local",C3)),"F","G") ) )} -> 24.32 | E3: {=_xlfn.XLOOKUP( $A$2, INDIRECT("'" & $C3 & "'!A:A"), INDIRECT( "'" & $C3 & "'!" & IF(ISNUMBER(SEARCH("Local",$C3)),"E","F") & ":" & IF(ISNUMBER(SEARCH("Local",$C3)),"E","F") ) )*INDIRECT("'" & $C3 & "'!C41")} -> #VALUE! | F3: =E3+D3 -> #VALUE! | G3: =E3/F3 -> #VALUE!
C4: SLC - Site Built | D4: {=_xlfn.XLOOKUP( $A$2, INDIRECT("'" & C4 & "'!A:A"), INDIRECT( "'" & C4 & "'!" & IF(ISNUMBER(SEARCH("Local",C4)),"F","G") & ":" & IF(ISNUMBER(SEARCH("Local",C4)),"F","G") ) )} -> 11.4 | E4: {=_xlfn.XLOOKUP( $A$2, INDIRECT("'" & $C4 & "'!A:A"), INDIRECT( "'" & $C4 & "'!" & IF(ISNUMBER(SEARCH("Local",$C4)),"E","F") & ":" & IF(ISNUMBER(SEARCH("Local",$C4)),"E","F") ) )*INDIRECT("'" & $C4 & "'!C41")} -> 1.4092793 | F4: =E4+D4 -> 12.809279 | G4: =E4/F4 -> 0.11002019
C5: SLC - Local | D5: {=_xlfn.XLOOKUP( $A$2, INDIRECT("'" & C5 & "'!A:A"), INDIRECT( "'" & C5 & "'!" & IF(ISNUMBER(SEARCH("Local",C5)),"F","G") & ":" & IF(ISNUMBER(SEARCH("Local",C5)),"F","G") ) )} -> 11.4 | E5: {=_xlfn.XLOOKUP( $A$2, INDIRECT("'" & $C5 & "'!A:A"), INDIRECT( "'" & $C5 & "'!" & IF(ISNUMBER(SEARCH("Local",$C5)),"E","F") & ":" & IF(ISNUMBER(SEARCH("Local",$C5)),"E","F") ) )*INDIRECT("'" & $C5 & "'!C41")} -> 0.47104954 | F5: =E5+D5 -> 11.87105 | G5: =E5/F5 -> 0.03968053
C6: NA - Site Built | D6: {=_xlfn.XLOOKUP( $A$2, INDIRECT("'" & C6 & "'!A:A"), INDIRECT( "'" & C6 & "'!" & IF(ISNUMBER(SEARCH("Local",C6)),"F","G") & ":" & IF(ISNUMBER(SEARCH("Local",C6)),"F","G") ) )} -> 12.236 | E6: {=_xlfn.XLOOKUP( $A$2, INDIRECT("'" & $C6 & "'!A:A"), INDIRECT( "'" & $C6 & "'!" & IF(ISNUMBER(SEARCH("Local",$C6)),"E","F") & ":" & IF(ISNUMBER(SEARCH("Local",$C6)),"E","F") ) )*INDIRECT("'" & $C6 & "'!C41")} -> 1.5126265 | F6: =E6+D6 -> 13.748626 | G6: =E6/F6 -> 0.11002019
C7: NA - Local | D7: {=_xlfn.XLOOKUP( $A$2, INDIRECT("'" & C7 & "'!A:A"), INDIRECT( "'" & C7 & "'!" & IF(ISNUMBER(SEARCH("Local",C7)),"F","G") & ":" & IF(ISNUMBER(SEARCH("Local",C7)),"F","G") ) )} -> 12.236 | E7: {=_xlfn.XLOOKUP( $A$2, INDIRECT("'" & $C7 & "'!A:A"), INDIRECT( "'" & $C7 & "'!" & IF(ISNUMBER(SEARCH("Local",$C7)),"E","F") & ":" & IF(ISNUMBER(SEARCH("Local",$C7)),"E","F") ) )*INDIRECT("'" & $C7 & "'!C41")} -> #VALUE! | F7: =E7+D7 -> #VALUE! | G7: =E7/F7 -> #VALUE!

Sheet Detail Results
A1: Select a Scenario | C1: Process | D1: Cost | E1: Profit | F1: Selling Price | G1: Profit Margin | I1: Unit of measure* | K1: Notes
A2: SLC - Local | C2: Site Work | D2: {=INDIRECT("'" & $A$2 & "'!" & IF(ISNUMBER(SEARCH("Local",$A$2)),"F","G") & ROW()+1)} -> 11.4 | E2: {=_xlfn.XLOOKUP( C2, INDIRECT("'" & $A$2 & "'!A:A"), INDIRECT( "'" & $A$2 & "'!" & IF(ISNUMBER(SEARCH("Local",$A$2)),"E","F") & ":" & IF(ISNUMBER(SEARCH("Local",$A$2)),"E","F") ) )*INDIRECT("'" & $A$2 & "'!C41")} -> 0.47104954 | F2: =E2+D2 -> 11.87105 | G2: =IF(F2=0, "", E2/F2) -> 0.03968053 | I2: ='Parameter Adjustment'!Z2 -> Square foot | K2: *Go to parameter adjustment page to move
C3: Foundations | D3: {=INDIRECT("'" & $A$2 & "'!" & IF(ISNUMBER(SEARCH("Local",$A$2)),"F","G") & ROW()+1)} -> 15.75 | E3: {=_xlfn.XLOOKUP( C3, INDIRECT("'" & $A$2 & "'!A:A"), INDIRECT( "'" & $A$2 & "'!" & IF(ISNUMBER(SEARCH("Local",$A$2)),"E","F") & ":" & IF(ISNUMBER(SEARCH("Local",$A$2)),"E","F") ) )*INDIRECT("'" & $A$2 & "'!C41")} -> 0.75925748 | F3: =E3+D3 -> 16.509257 | G3: =IF(F3=0, "", E3/F3) -> 0.045989802
C4: Floor framing | D4: {=INDIRECT("'" & $A$2 & "'!" & IF(ISNUMBER(SEARCH("Local",$A$2)),"F","G") & ROW()+1)} -> 2.80125 | E4: {=_xlfn.XLOOKUP( C4, INDIRECT("'" & $A$2 & "'!A:A"), INDIRECT( "'" & $A$2 & "'!" & IF(ISNUMBER(SEARCH("Local",$A$2)),"E","F") & ":" & IF(ISNUMBER(SEARCH("Local",$A$2)),"E","F") ) )*INDIRECT("'" & $A$2 & "'!C41")} -> 0.11574803 | F4: =E4+D4 -> 2.916998 | G4: =IF(F4=0, "", E4/F4) -> 0.03968053
C5: Floor sheathing | D5: {=INDIRECT("'" & $A$2 & "'!" & IF(ISNUMBER(SEARCH("Local",$A$2)),"F","G") & ROW()+1)} -> 2.80125 | E5: {=_xlfn.XLOOKUP( C5, INDIRECT("'" & $A$2 & "'!A:A"), INDIRECT( "'" & $A$2 & "'!" & IF(ISNUMBER(SEARCH("Local",$A$2)),"E","F") & ":" & IF(ISNUMBER(SEARCH("Local",$A$2)),"E","F") ) )*INDIRECT("'" & $A$2 & "'!C41")} -> 0.11574803 | F5: =E5+D5 -> 2.916998 | G5: =IF(F5=0, "", E5/F5) -> 0.03968053
C6: Interior Wall framing | D6: {=INDIRECT("'" & $A$2 & "'!" & IF(ISNUMBER(SEARCH("Local",$A$2)),"F","G") & ROW()+1)} -> 2.80125 | E6: {=_xlfn.XLOOKUP( C6, INDIRECT("'" & $A$2 & "'!A:A"), INDIRECT( "'" & $A$2 & "'!" & IF(ISNUMBER(SEARCH("Local",$A$2)),"E","F") & ":" & IF(ISNUMBER(SEARCH("Local",$A$2)),"E","F") ) )*INDIRECT("'" & $A$2 & "'!C41")} -> 0.11574803 | F6: =E6+D6 -> 2.916998 | G6: =IF(F6=0, "", E6/F6) -> 0.03968053
C7: Interior Wall sheathing | D7: {=INDIRECT("'" & $A$2 & "'!" & IF(ISNUMBER(SEARCH("Local",$A$2)),"F","G") & ROW()+1)} -> 2.80125 | E7: {=_xlfn.XLOOKUP( C7, INDIRECT("'" & $A$2 & "'!A:A"), INDIRECT( "'" & $A$2 & "'!" & IF(ISNUMBER(SEARCH("Local",$A$2)),"E","F") & ":" & IF(ISNUMBER(SEARCH("Local",$A$2)),"E","F") ) )*INDIRECT("'" & $A$2 & "'!C41")} -> 0.11574803 | F7: =E7+D7 -> 2.916998 | G7: =IF(F7=0, "", E7/F7) -> 0.03968053
C8: Exterior Walls framing | D8: {=INDIRECT("'" & $A$2 & "'!" & IF(ISNUMBER(SEARCH("Local",$A$2)),"F","G") & ROW()+1)} -> 2.80125 | E8: {=_xlfn.XLOOKUP( C8, INDIRECT("'" & $A$2 & "'!A:A"), INDIRECT( "'" & $A$2 & "'!" & IF(ISNUMBER(SEARCH("Local",$A$2)),"E","F") & ":" & IF(ISNUMBER(SEARCH("Local",$A$2)),"E","F") ) )*INDIRECT("'" & $A$2 & "'!C41")} -> 0.11574803 | F8: =E8+D8 -> 2.916998 | G8: =IF(F8=0, "", E8/F8) -> 0.03968053
C9: Exterior Wall sheathing | D9: {=INDIRECT("'" & $A$2 & "'!" & IF(ISNUMBER(SEARCH("Local",$A$2)),"F","G") & ROW()+1)} -> 2.80125 | E9: {=_xlfn.XLOOKUP( C9, INDIRECT("'" & $A$2 & "'!A:A"), INDIRECT( "'" & $A$2 & "'!" & IF(ISNUMBER(SEARCH("Local",$A$2)),"E","F") & ":" & IF(ISNUMBER(SEARCH("Local",$A$2)),"E","F") ) )*INDIRECT("'" & $A$2 & "'!C41")} -> 0.11574803 | F9: =E9+D9 -> 2.916998 | G9: =IF(F9=0, "", E9/F9) -> 0.03968053
C10: Roof framing | D10: {=INDIRECT("'" & $A$2 & "'!" & IF(ISNUMBER(SEARCH("Local",$A$2)),"F","G") & ROW()+1)} -> 2.80125 | E10: {=_xlfn.XLOOKUP( C10, INDIRECT("'" & $A$2 & "'!A:A"), INDIRECT( "'" & $A$2 & "'!" & IF(ISNUMBER(SEARCH("Local",$A$2)),"E","F") & ":" & IF(ISNUMBER(SEARCH("Local",$A$2)),"E","F") ) )*INDIRECT("'" & $A$2 & "'!C41")} -> 0.11574803 | F10: =E10+D10 -> 2.916998 | G10: =IF(F10=0, "", E10/F10) -> 0.03968053
C11: Roof sheathing and waterproofing | D11: {=INDIRECT("'" & $A$2 & "'!" & IF(ISNUMBER(SEARCH("Local",$A$2)),"F","G") & ROW()+1)} -> 2.80125 | E11: {=_xlfn.XLOOKUP( C11, INDIRECT("'" & $A$2 & "'!A:A"), INDIRECT( "'" & $A$2 & "'!" & IF(ISNUMBER(SEARCH("Local",$A$2)),"E","F") & ":" & IF(ISNUMBER(SEARCH("Local",$A$2)),"E","F") ) )*INDIRECT("'" & $A$2 & "'!C41")} -> 0.11574803 | F11: =E11+D11 -> 2.916998 | G11: =IF(F11=0, "", E11/F11) -> 0.03968053
C12: Mechanical Rough In | D12: {=INDIRECT("'" & $A$2 & "'!" & IF(ISNUMBER(SEARCH("Local",$A$2)),"F","G") & ROW()+1)} -> 8.505 | E12: {=_xlfn.XLOOKUP( C12, INDIRECT("'" & $A$2 & "'!A:A"), INDIRECT( "'" & $A$2 & "'!" & IF(ISNUMBER(SEARCH("Local",$A$2)),"E","F") & ":" & IF(ISNUMBER(SEARCH("Local",$A$2)),"E","F") ) )*INDIRECT("'" & $A$2 & "'!C41")} -> 0.17571387 | F12: =E12+D12 -> 8.6807139 | G12: =IF(F12=0, "", E12/F12) -> 0.020241869
C13: Electrical Rough In | D13: {=INDIRECT("'" & $A$2 & "'!" & IF(ISNUMBER(SEARCH("Local",$A$2)),"F","G") & ROW()+1)} -> 8.64 | E13: {=_xlfn.XLOOKUP( C13, INDIRECT("'" & $A$2 & "'!A:A"), INDIRECT( "'" & $A$2 & "'!" & IF(ISNUMBER(SEARCH("Local",$A$2)),"E","F") & ":" & IF(ISNUMBER(SEARCH("Local",$A$2)),"E","F") ) )*INDIRECT("'" & $A$2 & "'!C41")} -> 0.17850298 | F13: =E13+D13 -> 8.818503 | G13: =IF(F13=0, "", E13/F13) -> 0.020241869
C14: Plumbing Rough In | D14: {=INDIRECT("'" & $A$2 & "'!" & IF(ISNUMBER(SEARCH("Local",$A$2)),"F","G") & ROW()+1)} -> 8.505 | E14: {=_xlfn.XLOOKUP( C14, INDIRECT("'" & $A$2 & "'!A:A"), INDIRECT( "'" & $A$2 & "'!" & IF(ISNUMBER(SEARCH("Local",$A$2)),"E","F") & ":" & IF(ISNUMBER(SEARCH("Local",$A$2)),"E","F") ) )*INDIRECT("'" & $A$2 & "'!C41")} -> 0.17571387 | F14: =E14+D14 -> 8.6807139 | G14: =IF(F14=0, "", E14/F14) -> 0.020241869
... C27: All Inspections | D27: {=INDIRECT("'" & $A$2 & "'!" & IF(ISNUMBER(SEARCH("Local",$A$2)),"F","G") & ROW()+1)} -> 2.52 | E27: {=_xlfn.XLOOKUP( C27, INDIRECT("'" & $A$2 & "'!A:A"), INDIRECT( "'" & $A$2 & "'!" & IF(ISNUMBER(SEARCH("Local",$A$2)),"E","F") & ":" & IF(ISNUMBER(SEARCH("Local",$A$2)),"E","F") ) )*INDIRECT("'" & $A$2 & "'!C41")} -> 0 | F27: =E27+D27 -> 2.52 | G27: =IF(F27=0, "", E27/F27) -> 0
C28: Total Cost | D28: =SUM(D2:D27) -> 139.595 | E28: =SUM(E2:E27) -> 4.5186667 | F28: =SUM(F2:F27) -> 144.11367 | G28: =E28/F28 -> 0.03135488

Sheet List Options
A1: Unit of measure | C1: Scenarios | E1: Processes
A2: 1,000 square-foot home | C2: LA - Site Built | E2: Site Work
A3: Square foot | C3: LA - Local | E3: Foundations
C4: SLC - Site Built | E4: Floor framing
C5: SLC - Local | E5: Floor sheathing
C6: NA - Site Built | E6: Interior Wall framing
C7: NA - Local | E7: Interior Wall sheathing
E8: Exterior Walls framing
E9: Exterior Wall sheathing
E10: Roof framing
E11: Roof sheathing and waterproofing
E12: Mechanical Rough In
E13: Electrical Rough In
E14: Plumbing Rough In
E15: Insulation
E16: Drywall
E17: Mechanical Finishing
E18: Electrical Finishing
E19: Plumbing Finishing
... E27: All Inspections

Sheet LA - Site Built
B1: Costs | H1: Time | J1: assume 8 hours per day | K1: Working hours * hourly rate
A2: Construction Process | B2: % Material Cost | C2: % Labor Cost | D2: Material Cost | E2: Labor Cost | F2: % of Total Cost | G2: Total Cost | H2: % of Total Time | I2: Total Time (days) | J2: Total Time per Employee (working hours) | K2: Total Labor Cost per Employee
A3: Site Work | B3: ='Parameter Adjustment'!B3 -> 0.6 | C3: ='Parameter Adjustment'!C3 -> 0.4 | D3: ='Parameter Adjustment'!$N$8*B3*$F3 -> 14.592 | E3: ='Parameter Adjustment'!$N$8*C3*$F3 -> 9.728 | F3: ='Parameter Adjustment'!D3 -> 0.076 | G3: =SUM(D3:E3) -> 24.32 | H3: ='Parameter Adjustment'!E3 -> 0.10810811 | I3: =H3*'Parameter Adjustment'!$P$2 -> 22.702703 | J3: =I3*8 -> 181.62162 | K3: =J3*_xlfn.XLOOKUP(A3,'Parameter Adjustment'!$A$38:$A$63,'Parameter Adjustment'!$B$38:$B$63) -> 5775.5676
A4: Foundations | B4: ='Parameter Adjustment'!B4 -> 0.7 | C4: ='Parameter Adjustment'!C4 -> 0.3 | D4: ='Parameter Adjustment'!$N$8*B4*$F4 -> 23.52 | E4: ='Parameter Adjustment'!$N$8*C4*$F4 -> 10.08 | F4: ='Parameter Adjustment'!D4 -> 0.105 | G4: =SUM(D4:E4) -> 33.6 | H4: ='Parameter Adjustment'!E4 -> 0.10810811 | I4: =H4*'Parameter Adjustment'!$P$2 -> 22.702703 | J4: =I4*8 -> 181.62162 | K4: =J4*_xlfn.XLOOKUP(A4,'Parameter Adjustment'!$A$38:$A$63,'Parameter Adjustment'!$B$38:$B$63) -> 5775.5676
A5: Floor framing | B5: ='Parameter Adjustment'!B5 -> 0.6 | C5: ='Parameter Adjustment'!C5 -> 0.4 | D5: ='Parameter Adjustment'!$N$8*B5*$F5 -> 3.984 | E5: ='Parameter Adjustment'!$N$8*C5*$F5 -> 2.656 | F5: ='Parameter Adjustment'!D5 -> 0.02075 | G5: =SUM(D5:E5) -> 6.64 | H5: ='Parameter Adjustment'!E5 -> 0.032432432 | I5: =H5*'Parameter Adjustment'!$P$2 -> 6.8108108 | J5: =I5*8 -> 54.486486 | K5: =J5*_xlfn.XLOOKUP(A5,'Parameter Adjustment'!$A$38:$A$63,'Parameter Adjustment'!$B$38:$B$63) -> 1889.5914
A6: Floor sheathing | B6: ='Parameter Adjustment'!B6 -> 0.6 | C6: ='Parameter Adjustment'!C6 -> 0.4 | D6: ='Parameter Adjustment'!$N$8*B6*$F6 -> 3.984 | E6: ='Parameter Adjustment'!$N$8*C6*$F6 -> 2.656 | F6: ='Parameter Adjustment'!D6 -> 0.02075 | G6: =SUM(D6:E6) -> 6.64 | H6: ='Parameter Adjustment'!E6 -> 0.016216216 | I6: =H6*'Parameter Adjustment'!$P$2 -> 3.4054054 | J6: =I6*8 -> 27.243243 | K6: =J6*_xlfn.XLOOKUP(A6,'Parameter Adjustment'!$A$38:$A$63,'Parameter Adjustment'!$B$38:$B$63) -> 944.79568
A7: Interior Wall framing | B7: ='Parameter Adjustment'!B7 -> 0.6 | C7: ='Parameter Adjustment'!C7 -> 0.4 | D7: ='Parameter Adjustment'!$N$8*B7*$F7 -> 3.984 | E7: ='Parameter Adjustment'!$N$8*C7*$F7 -> 2.656 | F7: ='Parameter Adjustment'!D7 -> 0.02075 | G7: =SUM(D7:E7) -> 6.64 | H7: ='Parameter Adjustment'!E7 -> 0.040540541 | I7: =H7*'Parameter Adjustment'!$P$2 -> 8.5135135 | J7: =I7*8 -> 68.108108 | K7: =J7*_xlfn.XLOOKUP(A7,'Parameter Adjustment'!$A$38:$A$63,'Parameter Adjustment'!$B$38:$B$63) -> 2543.8378
A8: Interior Wall sheathing | B8: ='Parameter Adjustment'!B8 -> 0.6 | C8: ='Parameter Adjustment'!C8 -> 0.4 | D8: ='Parameter Adjustment'!$N$8*B8*$F8 -> 3.984 | E8: ='Parameter Adjustment'!$N$8*C8*$F8 -> 2.656 | F8: ='Parameter Adjustment'!D8 -> 0.02075 | G8: =SUM(D8:E8) -> 6.64 | H8: ='Parameter Adjustment'!E8 -> 0.016216216 | I8: =H8*'Parameter Adjustment'!$P$2 -> 3.4054054 | J8: =I8*8 -> 27.243243 | K8: =J8*_xlfn.XLOOKUP(A8,'Parameter Adjustment'!$A$38:$A$63,'Parameter Adjustment'!$B$38:$B$63) -> 1017.5351
A9: Exterior Walls framing | B9: ='Parameter Adjustment'!B9 -> 0.6 | C9: ='Parameter Adjustment'!C9 -> 0.4 | D9: ='Parameter Adjustment'!$N$8*B9*$F9 -> 3.984 | E9: ='Parameter Adjustment'!$N$8*C9*$F9 -> 2.656 | F9: ='Parameter Adjustment'!D9 -> 0.02075 | G9: =SUM(D9:E9) -> 6.64 | H9: ='Parameter Adjustment'!E9 -> 0.091891892 | I9: =H9*'Parameter Adjustment'!$P$2 -> 19.297297 | J9: =I9*8 -> 154.37838 | K9: =J9*_xlfn.XLOOKUP(A9,'Parameter Adjustment'!$A$38:$A$63,'Parameter Adjustment'!$B$38:$B$63) -> 5766.0324
A10: Exterior Wall sheathing | B10: ='Parameter Adjustment'!B10 -> 0.6 | C10: ='Parameter Adjustment'!C10 -> 0.4 | D10: ='Parameter Adjustment'!$N$8*B10*$F10 -> 3.984 | E10: ='Parameter Adjustment'!$N$8*C10*$F10 -> 2.656 | F10: ='Parameter Adjustment'!D10 -> 0.02075 | G10: =SUM(D10:E10) -> 6.64 | H10: ='Parameter Adjustment'!E10 -> 0.027027027 | I10: =H10*'Parameter Adjustment'!$P$2 -> 5.6756757 | J10: =I10*8 -> 45.405405 | K10: =J10*_xlfn.XLOOKUP(A10,'Parameter Adjustment'!$A$38:$A$63,'Parameter Adjustment'!$B$38:$B$63) -> 1695.8919
A11: Roof framing | B11: ='Parameter Adjustment'!B11 -> 0.6 | C11: ='Parameter Adjustment'!C11 -> 0.4 | D11: ='Parameter Adjustment'!$N$8*B11*$F11 -> 3.984 | E11: ='Parameter Adjustment'!$N$8*C11*$F11 -> 2.656 | F11: ='Parameter Adjustment'!D11 -> 0.02075 | G11: =SUM(D11:E11) -> 6.64 | H11: ='Parameter Adjustment'!E11 -> 0.032432432 | I11: =H11*'Parameter Adjustment'!$P$2 -> 6.8108108 | J11: =I11*8 -> 54.486486 | K11: =J11*_xlfn.XLOOKUP(A11,'Parameter Adjustment'!$A$38:$A$63,'Parameter Adjustment'!$B$38:$B$63) -> 1783.3427
A12: Roof sheathing and waterproofing | B12: ='Parameter Adjustment'!B12 -> 0.6 | C12: ='Parameter Adjustment'!C12 -> 0.4 | D12: ='Parameter Adjustment'!$N$8*B12*$F12 -> 3.984 | E12: ='Parameter Adjustment'!$N$8*C12*$F12 -> 2.656 | F12: ='Parameter Adjustment'!D12 -> 0.02075 | G12: =SUM(D12:E12) -> 6.64 | H12: ='Parameter Adjustment'!E12 -> 0.027027027 | I12: =H12*'Parameter Adjustment'!$P$2 -> 5.6756757 | J12: =I12*8 -> 45.405405 | K12: =J12*_xlfn.XLOOKUP(A12,'Parameter Adjustment'!$A$38:$A$63,'Parameter Adjustment'!$B$38:$B$63) -> 1486.1189
A13: Mechanical Rough In | B13: ='Parameter Adjustment'!B13 -> 0.3 | C13: ='Parameter Adjustment'!C13 -> 0.7 | D13: ='Parameter Adjustment'!$N$8*B13*$F13 -> 6.048 | E13: ='Parameter Adjustment'!$N$8*C13*$F13 -> 14.112 | F13: ='Parameter Adjustment'!D13 -> 0.063 | G13: =SUM(D13:E13) -> 20.16 | H13: ='Parameter Adjustment'!E13 -> 0.045945946 | I13: =H13*'Parameter Adjustment'!$P$2 -> 9.6486486 | J13: =I13*8 -> 77.189189 | K13: =J13*_xlfn.XLOOKUP(A13,'Parameter Adjustment'!$A$38:$A$63,'Parameter Adjustment'!$B$38:$B$63) -> 2608.9946
A14: Electrical Rough In | B14: ='Parameter Adjustment'!B14 -> 0.3 | C14: ='Parameter Adjustment'!C14 -> 0.7 | D14: ='Parameter Adjustment'!$N$8*B14*$F14 -> 6.144 | E14: ='Parameter Adjustment'!$N$8*C14*$F14 -> 14.336 | F14: ='Parameter Adjustment'!D14 -> 0.064 | G14: =SUM(D14:E14) -> 20.48 | H14: ='Parameter Adjustment'!E14 -> 0.02972973 | I14: =H14*'Parameter Adjustment'!$P$2 -> 6.2432432 | J14: =I14*8 -> 49.945946 | K14: =J14*_xlfn.XLOOKUP(A14,'Parameter Adjustment'!$A$38:$A$63,'Parameter Adjustment'!$B$38:$B$63) -> 2059.7708
... A25: Exterior Roof Finishing | B25: ='Parameter Adjustment'!B25 -> 0.6 | C25: ='Parameter Adjustment'!C25 -> 0.4 | D25: ='Parameter Adjustment'!$N$8*B25*$F25 -> 7.488 | E25: ='Parameter Adjustment'!$N$8*C25*$F25 -> 4.992 | F25: ='Parameter Adjustment'!D25 -> 0.039 | G25: =SUM(D25:E25) -> 12.48 | H25: ='Parameter Adjustment'!E25 -> 0.027027027 | I25: =H25*'Parameter Adjustment'!$P$2 -> 5.6756757 | J25: =I25*8 -> 45.405405 | K25: =J25*_xlfn.XLOOKUP(A25,'Parameter Adjustment'!$A$38:$A$63,'Parameter Adjustment'!$B$38:$B$63) -> 1486.1189
A26: Transportation | B26: ='Parameter Adjustment'!B26 -> 0 | C26: ='Parameter Adjustment'!C26 -> 0 | D26: ='Parameter Adjustment'!$N$8*B26*$F26 -> 0 | E26: ='Parameter Adjustment'!$N$8*C26*$F26 -> 0 | F26: ='Parameter Adjustment'!D26 -> 0 | H26: ='Parameter Adjustment'!E26 -> 0 | I26: =H26*'Parameter Adjustment'!$P$2 -> 0 | K26: =J26*_xlfn.XLOOKUP(A26,'Parameter Adjustment'!$A$38:$A$63,'Parameter Adjustment'!$B$38:$B$63) -> 0
A27: On-site Installation | B27: ='Parameter Adjustment'!B27 -> 0 | C27: ='Parameter Adjustment'!C27 -> 0 | D27: ='Parameter Adjustment'!$N$8*B27*$F27 -> 0 | E27: ='Parameter Adjustment'!$N$8*C27*$F27 -> 0 | F27: ='Parameter Adjustment'!D27 -> 0 | G27: =SUM(D27:E27) -> 0 | H27: ='Parameter Adjustment'!E27 -> 0 | I27: =H27*'Parameter Adjustment'!$P$2 -> 0
A28: All Inspections | B28: ='Parameter Adjustment'!B28 -> 0 | C28: ='Parameter Adjustment'!C28 -> 1 | D28: ='Parameter Adjustment'!$N$8*B28*$F28 -> 0 | E28: ='Parameter Adjustment'!$N$8*C28*$F28 -> 26.88 | F28: ='Parameter Adjustment'!D28 -> 0.084 | G28: =SUM(D28:E28) -> 26.88 | H28: ='Parameter Adjustment'!E28 -> 0.059459459 | I28: =H28*'Parameter Adjustment'!$P$2 -> 12.486486 | J28: =I28*8 -> 99.891892 | K28: =J28*_xlfn.XLOOKUP(A28,'Parameter Adjustment'!$A$38:$A$63,'Parameter Adjustment'!$B$38:$B$63) -> 4970.6205
A29: =_xlfn.CONCAT("Total Construction Costs (",'Parameter Adjustment'!$Z$2,")") -> Total Construction Costs (Square foot) | D29: =SUM(D3:D28) -> 151.296 | E29: =SUM(E3:E28) -> 168.704 | F29: =SUM(F3:F28) -> 1 | G29: =SUM(G3:G28) -> 320 | H29: =SUM(H3:H28) -> 1 | I29: =SUM(I3:I28) -> 210 | J29: =SUM(J3:J28) -> 1680 | K29: =SUM(K3:K28) -> 59637.185
A33: Profit Calculation | B33: Value | C33: Percentage
A34: Total Construction Costs | B34: =G29 -> 320 | C34: =B34/$B$37 -> 0.64254257
A35: Other Costs | B35: ='Profit Calculation'!B11*'Profit Calculation'!E10*IF('Parameter Adjustment'!Z2="1,000 square-foot home",1000,1) -> 123.22906 | C35: =B35/$B$37 -> 0.24743724
A36: Profit | B36: ='Profit Calculation'!B12*'Profit Calculation'!E10*IF('Parameter Adjustment'!Z2="1,000 square-foot home",1000,1) -> 54.792417 | C36: =B36/$B$37 -> 0.11002019
A37: Total Selling Price | B37: =SUM(B34:B36) -> 498.02148 | C37: =B37/$B$37 -> 1
A40: Cost Type | B40: % of Total Costs | C40: Profit | D40: Percentage
A41: Total Construction Costs | B41: =B34/SUM(B34:B35) -> 0.72197432 | C41: =B41*B36 -> 39.558718 | D41: =C41/B37 -> 0.07943175
A42: Other Costs | B42: =B35/SUM(B34:B35) -> 0.27802568 | C42: =B42*B36 -> 15.233699 | D42: =C42/B37 -> 0.030588438
A43: Total | B43: =SUM(B41:B42) -> 1 | C43: =SUM(C41:C42) -> 54.792417 | D43: =SUM(D41:D42) -> 0.11002019

Sheet LA - Local
B1: Costs | G1: Time | J1: assume 8 hours per day | K1: Working hours * hourly rate
A2: Construction Process | B2: % Cost Savings | C2: Material Cost | D2: Labor Cost | E2: % of Total Cost | F2: Total Cost | G2: % Time Savings | H2: % of Total Time | I2: Total Time (days) | J2: Total Time per Employee (working hours) | K2: Total Labor Cost per Employee
A3: Site Work | B3: ='Parameter Adjustment'!F3 -> 0 | C3: ='LA - Site Built'!D3*(1-$B3) -> 14.592 | D3: ='LA - Site Built'!E3*(1-$B3) -> 9.728 | E3: =C3/C$29 -> 0.10424525 | F3: =SUM(C3:D3) -> 24.32 | G3: ='Parameter Adjustment'!I3 -> 1 | H3: =I3/$I$29 -> 0 | I3: ='NA - Site Built'!I3*(1-G3) -> 0 | J3: =I3*8 -> 0 | K3: =J3*_xlfn.XLOOKUP(A3,'Parameter Adjustment'!$A$38:$A$63,'Parameter Adjustment'!$B$38:$B$63) -> 0
A4: Foundations | B4: ='Parameter Adjustment'!F4 -> 0 | C4: ='LA - Site Built'!D4*(1-$B4) -> 23.52 | D4: ='LA - Site Built'!E4*(1-$B4) -> 10.08 | E4: =C4/C$29 -> 0.16802688 | F4: =SUM(C4:D4) -> 33.6 | G4: ='Parameter Adjustment'!I4 -> 1 | H4: =I4/$I$29 -> 0 | I4: ='NA - Site Built'!I4*(1-G4) -> 0 | J4: =I4*8 -> 0 | K4: =J4*_xlfn.XLOOKUP(A4,'Parameter Adjustment'!$A$38:$A$63,'Parameter Adjustment'!$B$38:$B$63) -> 0
A5: Floor framing | B5: ='Parameter Adjustment'!F5 -> 0.1 | C5: ='LA - Site Built'!D5*(1-$B5) -> 3.5856 | D5: ='LA - Site Built'!E5*(1-$B5) -> 2.3904 | E5: =C5/C$29 -> 0.025615527 | F5: =SUM(C5:D5) -> 5.976 | G5: ='Parameter Adjustment'!I5 -> 0.2 | H5: =I5/$I$29 -> 0.034664191 | I5: ='NA - Site Built'!I5*(1-G5) -> 5.4486486 | J5: =I5*8 -> 43.589189 | K5: =J5*_xlfn.XLOOKUP(A5,'Parameter Adjustment'!$A$38:$A$63,'Parameter Adjustment'!$B$38:$B$63) -> 1511.6731
A6: Floor sheathing | B6: ='Parameter Adjustment'!F6 -> 0.1 | C6: ='LA - Site Built'!D6*(1-$B6) -> 3.5856 | D6: ='LA - Site Built'!E6*(1-$B6) -> 2.3904 | E6: =C6/C$29 -> 0.025615527 | F6: =SUM(C6:D6) -> 5.976 | G6: ='Parameter Adjustment'!I6 -> 0.2 | H6: =I6/$I$29 -> 0.017332095 | I6: ='NA - Site Built'!I6*(1-G6) -> 2.7243243 | J6: =I6*8 -> 21.794595 | K6: =J6*_xlfn.XLOOKUP(A6,'Parameter Adjustment'!$A$38:$A$63,'Parameter Adjustment'!$B$38:$B$63) -> 755.83654
A7: Interior Wall framing | B7: ='Parameter Adjustment'!F7 -> 0.1 | C7: ='LA - Site Built'!D7*(1-$B7) -> 3.5856 | D7: ='LA - Site Built'!E7*(1-$B7) -> 2.3904 | E7: =C7/C$29 -> 0.025615527 | F7: =SUM(C7:D7) -> 5.976 | G7: ='Parameter Adjustment'!I7 -> 0.2 | H7: =I7/$I$29 -> 0.043330238 | I7: ='NA - Site Built'!I7*(1-G7) -> 6.8108108 | J7: =I7*8 -> 54.486486 | K7: =J7*_xlfn.XLOOKUP(A7,'Parameter Adjustment'!$A$38:$A$63,'Parameter Adjustment'!$B$38:$B$63) -> 2035.0703
A8: Interior Wall sheathing | B8: ='Parameter Adjustment'!F8 -> 0.1 | C8: ='LA - Site Built'!D8*(1-$B8) -> 3.5856 | D8: ='LA - Site Built'!E8*(1-$B8) -> 2.3904 | E8: =C8/C$29 -> 0.025615527 | F8: =SUM(C8:D8) -> 5.976 | G8: ='Parameter Adjustment'!I8 -> 0.2 | H8: =I8/$I$29 -> 0.017332095 | I8: ='NA - Site Built'!I8*(1-G8) -> 2.7243243 | J8: =I8*8 -> 21.794595 | K8: =J8*_xlfn.XLOOKUP(A8,'Parameter Adjustment'!$A$38:$A$63,'Parameter Adjustment'!$B$38:$B$63) -> 814.02811
A9: Exterior Walls framing | B9: ='Parameter Adjustment'!F9 -> 0.1 | C9: ='LA - Site Built'!D9*(1-$B9) -> 3.5856 | D9: ='LA - Site Built'!E9*(1-$B9) -> 2.3904 | E9: =C9/C$29 -> 0.025615527 | F9: =SUM(C9:D9) -> 5.976 | G9: ='Parameter Adjustment'!I9 -> 0.2 | H9: =I9/$I$29 -> 0.098215207 | I9: ='NA - Site Built'!I9*(1-G9) -> 15.437838 | J9: =I9*8 -> 123.5027 | K9: =J9*_xlfn.XLOOKUP(A9,'Parameter Adjustment'!$A$38:$A$63,'Parameter Adjustment'!$B$38:$B$63) -> 4612.8259
A10: Exterior Wall sheathing | B10: ='Parameter Adjustment'!F10 -> 0.1 | C10: ='LA - Site Built'!D10*(1-$B10) -> 3.5856 | D10: ='LA - Site Built'!E10*(1-$B10) -> 2.3904 | E10: =C10/C$29 -> 0.025615527 | F10: =SUM(C10:D10) -> 5.976 | G10: ='Parameter Adjustment'!I10 -> 0.2 | H10: =I10/$I$29 -> 0.028886826 | I10: ='NA - Site Built'!I10*(1-G10) -> 4.5405405 | J10: =I10*8 -> 36.324324 | K10: =J10*_xlfn.XLOOKUP(A10,'Parameter Adjustment'!$A$38:$A$63,'Parameter Adjustment'!$B$38:$B$63) -> 1356.7135
A11: Roof framing | B11: ='Parameter Adjustment'!F11 -> 0.1 | C11: ='LA - Site Built'!D11*(1-$B11) -> 3.5856 | D11: ='LA - Site Built'!E11*(1-$B11) -> 2.3904 | E11: =C11/C$29 -> 0.025615527 | F11: =SUM(C11:D11) -> 5.976 | G11: ='Parameter Adjustment'!I11 -> 0.2 | H11: =I11/$I$29 -> 0.034664191 | I11: ='NA - Site Built'!I11*(1-G11) -> 5.4486486 | J11: =I11*8 -> 43.589189 | K11: =J11*_xlfn.XLOOKUP(A11,'Parameter Adjustment'!$A$38:$A$63,'Parameter Adjustment'!$B$38:$B$63) -> 1426.6742
A12: Roof sheathing and waterproofing | B12: ='Parameter Adjustment'!F12 -> 0.1 | C12: ='LA - Site Built'!D12*(1-$B12) -> 3.5856 | D12: ='LA - Site Built'!E12*(1-$B12) -> 2.3904 | E12: =C12/C$29 -> 0.025615527 | F12: =SUM(C12:D12) -> 5.976 | G12: ='Parameter Adjustment'!I12 -> 0.2 | H12: =I12/$I$29 -> 0.028886826 | I12: ='NA - Site Built'!I12*(1-G12) -> 4.5405405 | J12: =I12*8 -> 36.324324 | K12: =J12*_xlfn.XLOOKUP(A12,'Parameter Adjustment'!$A$38:$A$63,'Parameter Adjustment'!$B$38:$B$63) -> 1188.8951
A13: Mechanical Rough In | B13: ='Parameter Adjustment'!F13 -> 0.1 | C13: ='LA - Site Built'!D13*(1-$B13) -> 5.4432 | D13: ='LA - Site Built'!E13*(1-$B13) -> 12.7008 | E13: =C13/C$29 -> 0.038886222 | F13: =SUM(C13:D13) -> 18.144 | G13: ='Parameter Adjustment'!I13 -> 0.2 | H13: =I13/$I$29 -> 0.049107603 | I13: ='NA - Site Built'!I13*(1-G13) -> 7.7189189 | J13: =I13*8 -> 61.751351 | K13: =J13*_xlfn.XLOOKUP(A13,'Parameter Adjustment'!$A$38:$A$63,'Parameter Adjustment'!$B$38:$B$63) -> 2087.1957
A14: Electrical Rough In | B14: ='Parameter Adjustment'!F14 -> 0.1 | C14: ='LA - Site Built'!D14*(1-$B14) -> 5.5296 | D14: ='LA - Site Built'!E14*(1-$B14) -> 12.9024 | E14: =C14/C$29 -> 0.039503463 | F14: =SUM(C14:D14) -> 18.432 | G14: ='Parameter Adjustment'!I14 -> 0.2 | H14: =I14/$I$29 -> 0.031775508 | I14: ='NA - Site Built'!I14*(1-G14) -> 4.9945946 | J14: =I14*8 -> 39.956757 | K14: =J14*_xlfn.XLOOKUP(A14,'Parameter Adjustment'!$A$38:$A$63,'Parameter Adjustment'!$B$38:$B$63) -> 1647.8166
... A25: Exterior Roof Finishing | B25: ='Parameter Adjustment'!F25 -> 0.1 | C25: ='LA - Site Built'!D25*(1-$B25) -> 6.7392 | D25: ='LA - Site Built'!E25*(1-$B25) -> 4.4928 | E25: =C25/C$29 -> 0.048144846 | F25: =SUM(C25:D25) -> 11.232 | G25: ='Parameter Adjustment'!I25 -> 0.2 | H25: =I25/$I$29 -> 0.028886826 | I25: ='NA - Site Built'!I25*(1-G25) -> 4.5405405 | J25: =I25*8 -> 36.324324 | K25: =J25*_xlfn.XLOOKUP(A25,'Parameter Adjustment'!$A$38:$A$63,'Parameter Adjustment'!$B$38:$B$63) -> 1188.8951
A26: Transportation | B26: ='Parameter Adjustment'!F26 -> 0 | C26: ='LA - Site Built'!D26*(1-$B26) -> 0 | D26: ='Parameter Adjustment'!S3*'Parameter Adjustment'!T3/IF('Parameter Adjustment'!Z2="1,000 square-foot home",1,1000) -> 0.7 | E26: =C26/C$29 -> 0 | F26: =SUM(C26:D26) -> 0.7 | G26: ='Parameter Adjustment'!I26 -> 0 | H26: =I26/$I$29 -> 0.019085938 | I26: 3 | K26: =F26 -> 0.7
A27: On-site Installation | B27: ='Parameter Adjustment'!F27 -> 0 | C27: ='LA - Site Built'!D27*(1-$B27) -> 0 | D27: ='Parameter Adjustment'!X2*'Parameter Adjustment'!X3/IF('Parameter Adjustment'!Z2="1,000 square-foot home",1,1000) -> 10 | E27: =C27/C$29 -> 0 | F27: =SUM(C27:D27) -> 10 | G27: ='Parameter Adjustment'!I27 -> 0 | H27: =I27/$I$29 -> 0.19085938 | I27: 30 | J27: =I27*8 -> 240 | K27: =J27*_xlfn.XLOOKUP("Assembly",'Parameter Adjustment'!$A$38:$A$63,'Parameter Adjustment'!$B$38:$B$63) -> 7632
A28: All Inspections | B28: ='Parameter Adjustment'!F28 -> 0.8 | C28: ='LA - Site Built'!D28*(1-$B28) -> 0 | D28: ='LA - Site Built'!E28*(1-$B28) -> 5.376 | E28: =C28/C$29 -> 0 | F28: =SUM(C28:D28) -> 5.376 | G28: ='Parameter Adjustment'!I28 -> 0.8 | H28: =I28/$I$29 -> 0.015887754 | I28: ='NA - Site Built'!I28*(1-G28) -> 2.4972973 | J28: =I28*8 -> 19.978378 | K28: =J28*_xlfn.XLOOKUP(A28,'Parameter Adjustment'!$A$38:$A$63,'Parameter Adjustment'!$B$38:$B$63) -> 994.12411
A29: =_xlfn.CONCAT("Total Construction Costs (",'Parameter Adjustment'!$Z$2,")") -> Total Construction Costs (Square foot) | C29: =SUM(C3:C28) -> 139.9776 | D29: =SUM(D3:D28) -> 145.6984 | E29: =SUM(E3:E28) -> 1 | F29: =SUM(F3:F28) -> 285.676 | H29: =SUM(H3:H28) -> 1 | I29: =SUM(I3:I28) -> 157.18378 | J29: =SUM(J3:J28) -> 1233.4703 | K29: =SUM(K3:K28) -> 43119.167
A33: Profit Calculation | B33: Value | C33: Percentage
A34: Total Construction Costs | B34: =F29 -> 285.676 | C34: =B34/$B$38 -> 0.57362184
A35: Other Costs | B35: ='Profit Calculation'!B11*'Profit Calculation'!E10*IF('Parameter Adjustment'!Z2="1,000 square-foot home",1000,1) -> 123.22906 | C35: =B35/$B$38 -> 0.24743724
A36: Fixed Costs | B36: =IF('Parameter Adjustment'!$Z$2="Square foot",'Parameter Adjustment'!AJ3,'Parameter Adjustment'!AJ3*1000) -> 32.048 | C36: =B36/$B$38 -> 0.064350638
A37: Profit | B37: =B38-B34-B35-B36 -> 57.068417 | C37: =B37/$B$38 -> 0.11459027
A38: Total Selling Price | B38: ='LA - Site Built'!B37 -> 498.02148 | C38: =B38/$B$38 -> 1
A41: Cost Type | B41: % of Total Costs | C41: Profit | D41: Profit Margin
A42: Total Construction Costs | B42: =B34/SUM($B$34:$B$36) -> 0.64786034 | C42: =B42*$B$37 -> 36.972364 | D42: =C42/$B$38 -> 0.074238493
A43: Other Costs | B43: =B35/SUM($B$34:$B$36) -> 0.27946073 | C43: =B43*$B$37 -> 15.948381 | D43: =C43/$B$38 -> 0.032023481
A44: Fixed Costs | B44: =B36/SUM($B$34:$B$36) -> 0.072678937 | C44: =B44*$B$37 -> 4.1476719 | D44: =C44/$B$38 -> 0.0083282992
A45: Total | B45: =SUM(B42:B44) -> 1 | C45: =SUM(C42:C44) -> 57.068417 | D45: =SUM(D42:D44) -> 0.11459027

Sheet SLC - Site Built
B1: Costs | H1: Time | J1: assume 8 hours per day | K1: Working hours * hourly rate
A2: Construction Process | B2: % Material Cost | C2: % Labor Cost | D2: Material Cost | E2: Labor Cost | F2: % of Total Cost | G2: Total Cost | H2: % of Total Time | I2: Total Time (days) | J2: Total Time per Employee (working hours) | K2: Total Labor Cost per Employee
A3: Site Work | B3: ='Parameter Adjustment'!B3 -> 0.6 | C3: ='Parameter Adjustment'!C3 -> 0.4 | D3: ='Parameter Adjustment'!$N$12*B3*$F3 -> 6.84 | E3: ='Parameter Adjustment'!$N$12*C3*$F3 -> 4.56 | F3: ='Parameter Adjustment'!D3 -> 0.076 | G3: =SUM(D3:E3) -> 11.4 | H3: ='Parameter Adjustment'!E3 -> 0.10810811 | I3: =H3*'Parameter Adjustment'!$P$2 -> 22.702703 | J3: =I3*8 -> 181.62162 | K3: =J3*_xlfn.XLOOKUP(A3,'Parameter Adjustment'!$A$38:$A$63,'Parameter Adjustment'!$C$38:$C$63) -> 4170.0324
A4: Foundations | B4: ='Parameter Adjustment'!B4 -> 0.7 | C4: ='Parameter Adjustment'!C4 -> 0.3 | D4: ='Parameter Adjustment'!$N$12*B4*$F4 -> 11.025 | E4: ='Parameter Adjustment'!$N$12*C4*$F4 -> 4.725 | F4: ='Parameter Adjustment'!D4 -> 0.105 | G4: =SUM(D4:E4) -> 15.75 | H4: ='Parameter Adjustment'!E4 -> 0.10810811 | I4: =H4*'Parameter Adjustment'!$P$2 -> 22.702703 | J4: =I4*8 -> 181.62162 | K4: =J4*_xlfn.XLOOKUP(A4,'Parameter Adjustment'!$A$38:$A$63,'Parameter Adjustment'!$C$38:$C$63) -> 4170.0324
A5: Floor framing | B5: ='Parameter Adjustment'!B5 -> 0.6 | C5: ='Parameter Adjustment'!C5 -> 0.4 | D5: ='Parameter Adjustment'!$N$12*B5*$F5 -> 1.8675 | E5: ='Parameter Adjustment'!$N$12*C5*$F5 -> 1.245 | F5: ='Parameter Adjustment'!D5 -> 0.02075 | G5: =SUM(D5:E5) -> 3.1125 | H5: ='Parameter Adjustment'!E5 -> 0.032432432 | I5: =H5*'Parameter Adjustment'!$P$2 -> 6.8108108 | J5: =I5*8 -> 54.486486 | K5: =J5*_xlfn.XLOOKUP(A5,'Parameter Adjustment'!$A$38:$A$63,'Parameter Adjustment'!$C$38:$C$63) -> 1242.8368
A6: Floor sheathing | B6: ='Parameter Adjustment'!B6 -> 0.6 | C6: ='Parameter Adjustment'!C6 -> 0.4 | D6: ='Parameter Adjustment'!$N$12*B6*$F6 -> 1.8675 | E6: ='Parameter Adjustment'!$N$12*C6*$F6 -> 1.245 | F6: ='Parameter Adjustment'!D6 -> 0.02075 | G6: =SUM(D6:E6) -> 3.1125 | H6: ='Parameter Adjustment'!E6 -> 0.016216216 | I6: =H6*'Parameter Adjustment'!$P$2 -> 3.4054054 | J6: =I6*8 -> 27.243243 | K6: =J6*_xlfn.XLOOKUP(A6,'Parameter Adjustment'!$A$38:$A$63,'Parameter Adjustment'!$C$38:$C$63) -> 621.41838
A7: Interior Wall framing | B7: ='Parameter Adjustment'!B7 -> 0.6 | C7: ='Parameter Adjustment'!C7 -> 0.4 | D7: ='Parameter Adjustment'!$N$12*B7*$F7 -> 1.8675 | E7: ='Parameter Adjustment'!$N$12*C7*$F7 -> 1.245 | F7: ='Parameter Adjustment'!D7 -> 0.02075 | G7: =SUM(D7:E7) -> 3.1125 | H7: ='Parameter Adjustment'!E7 -> 0.040540541 | I7: =H7*'Parameter Adjustment'!$P$2 -> 8.5135135 | J7: =I7*8 -> 68.108108 | K7: =J7*_xlfn.XLOOKUP(A7,'Parameter Adjustment'!$A$38:$A$63,'Parameter Adjustment'!$C$38:$C$63) -> 1788.5189
A8: Interior Wall sheathing | B8: ='Parameter Adjustment'!B8 -> 0.6 | C8: ='Parameter Adjustment'!C8 -> 0.4 | D8: ='Parameter Adjustment'!$N$12*B8*$F8 -> 1.8675 | E8: ='Parameter Adjustment'!$N$12*C8*$F8 -> 1.245 | F8: ='Parameter Adjustment'!D8 -> 0.02075 | G8: =SUM(D8:E8) -> 3.1125 | H8: ='Parameter Adjustment'!E8 -> 0.016216216 | I8: =H8*'Parameter Adjustment'!$P$2 -> 3.4054054 | J8: =I8*8 -> 27.243243 | K8: =J8*_xlfn.XLOOKUP(A8,'Parameter Adjustment'!$A$38:$A$63,'Parameter Adjustment'!$C$38:$C$63) -> 715.40757
A9: Exterior Walls framing | B9: ='Parameter Adjustment'!B9 -> 0.6 | C9: ='Parameter Adjustment'!C9 -> 0.4 | D9: ='Parameter Adjustment'!$N$12*B9*$F9 -> 1.8675 | E9: ='Parameter Adjustment'!$N$12*C9*$F9 -> 1.245 | F9: ='Parameter Adjustment'!D9 -> 0.02075 | G9: =SUM(D9:E9) -> 3.1125 | H9: ='Parameter Adjustment'!E9 -> 0.091891892 | I9: =H9*'Parameter Adjustment'!$P$2 -> 19.297297 | J9: =I9*8 -> 154.37838 | K9: =J9*_xlfn.XLOOKUP(A9,'Parameter Adjustment'!$A$38:$A$63,'Parameter Adjustment'!$C$38:$C$63) -> 4053.9762
A10: Exterior Wall sheathing | B10: ='Parameter Adjustment'!B10 -> 0.6 | C10: ='Parameter Adjustment'!C10 -> 0.4 | D10: ='Parameter Adjustment'!$N$12*B10*$F10 -> 1.8675 | E10: ='Parameter Adjustment'!$N$12*C10*$F10 -> 1.245 | F10: ='Parameter Adjustment'!D10 -> 0.02075 | G10: =SUM(D10:E10) -> 3.1125 | H10: ='Parameter Adjustment'!E10 -> 0.027027027 | I10: =H10*'Parameter Adjustment'!$P$2 -> 5.6756757 | J10: =I10*8 -> 45.405405 | K10: =J10*_xlfn.XLOOKUP(A10,'Parameter Adjustment'!$A$38:$A$63,'Parameter Adjustment'!$C$38:$C$63) -> 1192.3459
A11: Roof framing | B11: ='Parameter Adjustment'!B11 -> 0.6 | C11: ='Parameter Adjustment'!C11 -> 0.4 | D11: ='Parameter Adjustment'!$N$12*B11*$F11 -> 1.8675 | E11: ='Parameter Adjustment'!$N$12*C11*$F11 -> 1.245 | F11: ='Parameter Adjustment'!D11 -> 0.02075 | G11: =SUM(D11:E11) -> 3.1125 | H11: ='Parameter Adjustment'!E11 -> 0.032432432 | I11: =H11*'Parameter Adjustment'!$P$2 -> 6.8108108 | J11: =I11*8 -> 54.486486 | K11: =J11*_xlfn.XLOOKUP(A11,'Parameter Adjustment'!$A$38:$A$63,'Parameter Adjustment'!$C$38:$C$63) -> 1381.7773
A12: Roof sheathing and waterproofing | B12: ='Parameter Adjustment'!B12 -> 0.6 | C12: ='Parameter Adjustment'!C12 -> 0.4 | D12: ='Parameter Adjustment'!$N$12*B12*$F12 -> 1.8675 | E12: ='Parameter Adjustment'!$N$12*C12*$F12 -> 1.245 | F12: ='Parameter Adjustment'!D12 -> 0.02075 | G12: =SUM(D12:E12) -> 3.1125 | H12: ='Parameter Adjustment'!E12 -> 0.027027027 | I12: =H12*'Parameter Adjustment'!$P$2 -> 5.6756757 | J12: =I12*8 -> 45.405405 | K12: =J12*_xlfn.XLOOKUP(A12,'Parameter Adjustment'!$A$38:$A$63,'Parameter Adjustment'!$C$38:$C$63) -> 1151.4811
A13: Mechanical Rough In | B13: ='Parameter Adjustment'!B13 -> 0.3 | C13: ='Parameter Adjustment'!C13 -> 0.7 | D13: ='Parameter Adjustment'!$N$12*B13*$F13 -> 2.835 | E13: ='Parameter Adjustment'!$N$12*C13*$F13 -> 6.615 | F13: ='Parameter Adjustment'!D13 -> 0.063 | G13: =SUM(D13:E13) -> 9.45 | H13: ='Parameter Adjustment'!E13 -> 0.045945946 | I13: =H13*'Parameter Adjustment'!$P$2 -> 9.6486486 | J13: =I13*8 -> 77.189189 | K13: =J13*_xlfn.XLOOKUP(A13,'Parameter Adjustment'!$A$38:$A$63,'Parameter Adjustment'!$C$38:$C$63) -> 2199.8919
A14: Electrical Rough In | B14: ='Parameter Adjustment'!B14 -> 0.3 | C14: ='Parameter Adjustment'!C14 -> 0.7 | D14: ='Parameter Adjustment'!$N$12*B14*$F14 -> 2.88 | E14: ='Parameter Adjustment'!$N$12*C14*$F14 -> 6.72 | F14: ='Parameter Adjustment'!D14 -> 0.064 | G14: =SUM(D14:E14) -> 9.6 | H14: ='Parameter Adjustment'!E14 -> 0.02972973 | I14: =H14*'Parameter Adjustment'!$P$2 -> 6.2432432 | J14: =I14*8 -> 49.945946 | K14: =J14*_xlfn.XLOOKUP(A14,'Parameter Adjustment'!$A$38:$A$63,'Parameter Adjustment'!$C$38:$C$63) -> 1513.3622
... A25: Exterior Roof Finishing | B25: ='Parameter Adjustment'!B25 -> 0.6 | C25: ='Parameter Adjustment'!C25 -> 0.4 | D25: ='Parameter Adjustment'!$N$12*B25*$F25 -> 3.51 | E25: ='Parameter Adjustment'!$N$12*C25*$F25 -> 2.34 | F25: ='Parameter Adjustment'!D25 -> 0.039 | G25: =SUM(D25:E25) -> 5.85 | H25: ='Parameter Adjustment'!E25 -> 0.027027027 | I25: =H25*'Parameter Adjustment'!$P$2 -> 5.6756757 | J25: =I25*8 -> 45.405405 | K25: =J25*_xlfn.XLOOKUP(A25,'Parameter Adjustment'!$A$38:$A$63,'Parameter Adjustment'!$C$38:$C$63) -> 1151.4811
A26: Transportation | B26: ='Parameter Adjustment'!B26 -> 0 | C26: ='Parameter Adjustment'!C26 -> 0 | D26: ='Parameter Adjustment'!$N$12*B26*$F26 -> 0 | E26: ='Parameter Adjustment'!$N$12*C26*$F26 -> 0 | F26: ='Parameter Adjustment'!D26 -> 0 | H26: ='Parameter Adjustment'!E26 -> 0 | I26: =H26*'Parameter Adjustment'!$P$2 -> 0
A27: On-site Installation | B27: ='Parameter Adjustment'!B27 -> 0 | C27: ='Parameter Adjustment'!C27 -> 0 | D27: ='Parameter Adjustment'!$N$12*B27*$F27 -> 0 | E27: ='Parameter Adjustment'!$N$12*C27*$F27 -> 0 | F27: ='Parameter Adjustment'!D27 -> 0 | G27: =SUM(D27:E27) -> 0 | H27: ='Parameter Adjustment'!E27 -> 0 | I27: =H27*'Parameter Adjustment'!$P$2 -> 0
A28: All Inspections | B28: ='Parameter Adjustment'!B28 -> 0 | C28: ='Parameter Adjustment'!C28 -> 1 | D28: ='Parameter Adjustment'!$N$12*B28*$F28 -> 0 | E28: ='Parameter Adjustment'!$N$12*C28*$F28 -> 12.6 | F28: ='Parameter Adjustment'!D28 -> 0.084 | G28: =SUM(D28:E28) -> 12.6 | H28: ='Parameter Adjustment'!E28 -> 0.059459459 | I28: =H28*'Parameter Adjustment'!$P$2 -> 12.486486 | J28: =I28*8 -> 99.891892 | K28: =J28*_xlfn.XLOOKUP(A28,'Parameter Adjustment'!$A$38:$A$63,'Parameter Adjustment'!$C$38:$C$63) -> 3428.2897
A29: =_xlfn.CONCAT("Total Construction Costs (",'Parameter Adjustment'!$Z$2,")") -> Total Construction Costs (Square foot) | D29: =SUM(D3:D28) -> 70.92 | E29: =SUM(E3:E28) -> 79.08 | F29: =SUM(F3:F28) -> 1 | G29: =SUM(G3:G28) -> 150 | H29: =SUM(H3:H28) -> 1 | I29: =SUM(I3:I28) -> 210 | J29: =SUM(J3:J28) -> 1680 | K29: =SUM(K3:K28) -> 44389.323
A33: Profit Calculation | B33: Value | C33: Percentage
A34: Total Construction Costs | B34: =G29 -> 150 | C34: =B34/$B$37 -> 0.64254257
A35: Other Costs | B35: ='Profit Calculation'!B11*'Profit Calculation'!F10*IF('Parameter Adjustment'!Z2="1,000 square-foot home",1000,1) -> 57.763623 | C35: =B35/$B$37 -> 0.24743724
A36: Profit | B36: ='Profit Calculation'!B12*'Profit Calculation'!F10*IF('Parameter Adjustment'!Z2="1,000 square-foot home",1000,1) -> 25.683945 | C36: =B36/$B$37 -> 0.11002019
A37: Total Selling Price | B37: =SUM(B34:B36) -> 233.44757 | C37: =B37/$B$37 -> 1
A40: Cost Type | B40: % of Total Costs | C40: Profit | D40: Percentage
A41: Total Construction Costs | B41: =B34/SUM(B34:B35) -> 0.72197432 | C41: =B41*B36 -> 18.543149 | D41: =C41/B37 -> 0.07943175
A42: Other Costs | B42: =B35/SUM(B34:B35) -> 0.27802568 | C42: =B42*B36 -> 7.1407965 | D42: =C42/B37 -> 0.030588438
A43: Total | B43: =SUM(B41:B42) -> 1 | C43: =SUM(C41:C42) -> 25.683945 | D43: =SUM(D41:D42) -> 0.11002019

Sheet SLC - Local
B1: Costs | G1: Time | J1: assume 8 hours per day | K1: Working hours * hourly rate
A2: Construction Process | B2: % Cost Savings | C2: Material Cost | D2: Labor Cost | E2: % of Total Cost | F2: Total Cost | G2: % Time Savings | H2: % of Total Time | I2: Total Time (days) | J2: Total Time per Employee (working hours) | K2: Total Labor Cost per Employee
A3: Site Work | B3: ='Parameter Adjustment'!F3 -> 0 | C3: ='SLC - Site Built'!D3*(1-$B3) -> 6.84 | D3: ='SLC - Site Built'!E3*(1-$B3) -> 4.56 | E3: =C3/C$29 -> 0.10424525 | F3: =SUM(C3:D3) -> 11.4 | G3: ='Parameter Adjustment'!I3 -> 1 | H3: =I3/$I$29 -> 0 | I3: ='NA - Site Built'!I3*(1-G3) -> 0 | J3: =I3*8 -> 0 | K3: =J3*_xlfn.XLOOKUP(A3,'Parameter Adjustment'!$A$38:$A$63,'Parameter Adjustment'!$C$38:$C$63) -> 0
A4: Foundations | B4: ='Parameter Adjustment'!F4 -> 0 | C4: ='SLC - Site Built'!D4*(1-$B4) -> 11.025 | D4: ='SLC - Site Built'!E4*(1-$B4) -> 4.725 | E4: =C4/C$29 -> 0.16802688 | F4: =SUM(C4:D4) -> 15.75 | G4: ='Parameter Adjustment'!I4 -> 1 | H4: =I4/$I$29 -> 0 | I4: ='NA - Site Built'!I4*(1-G4) -> 0 | J4: =I4*8 -> 0 | K4: =J4*_xlfn.XLOOKUP(A4,'Parameter Adjustment'!$A$38:$A$63,'Parameter Adjustment'!$C$38:$C$63) -> 0
A5: Floor framing | B5: ='Parameter Adjustment'!F5 -> 0.1 | C5: ='SLC - Site Built'!D5*(1-$B5) -> 1.68075 | D5: ='SLC - Site Built'!E5*(1-$B5) -> 1.1205 | E5: =C5/C$29 -> 0.025615527 | F5: =SUM(C5:D5) -> 2.80125 | G5: ='Parameter Adjustment'!I5 -> 0.2 | H5: =I5/$I$29 -> 0.034664191 | I5: ='NA - Site Built'!I5*(1-G5) -> 5.4486486 | J5: =I5*8 -> 43.589189 | K5: =J5*_xlfn.XLOOKUP(A5,'Parameter Adjustment'!$A$38:$A$63,'Parameter Adjustment'!$C$38:$C$63) -> 994.26941
A6: Floor sheathing | B6: ='Parameter Adjustment'!F6 -> 0.1 | C6: ='SLC - Site Built'!D6*(1-$B6) -> 1.68075 | D6: ='SLC - Site Built'!E6*(1-$B6) -> 1.1205 | E6: =C6/C$29 -> 0.025615527 | F6: =SUM(C6:D6) -> 2.80125 | G6: ='Parameter Adjustment'!I6 -> 0.2 | H6: =I6/$I$29 -> 0.017332095 | I6: ='NA - Site Built'!I6*(1-G6) -> 2.7243243 | J6: =I6*8 -> 21.794595 | K6: =J6*_xlfn.XLOOKUP(A6,'Parameter Adjustment'!$A$38:$A$63,'Parameter Adjustment'!$C$38:$C$63) -> 497.1347
A7: Interior Wall framing | B7: ='Parameter Adjustment'!F7 -> 0.1 | C7: ='SLC - Site Built'!D7*(1-$B7) -> 1.68075 | D7: ='SLC - Site Built'!E7*(1-$B7) -> 1.1205 | E7: =C7/C$29 -> 0.025615527 | F7: =SUM(C7:D7) -> 2.80125 | G7: ='Parameter Adjustment'!I7 -> 0.2 | H7: =I7/$I$29 -> 0.043330238 | I7: ='NA - Site Built'!I7*(1-G7) -> 6.8108108 | J7: =I7*8 -> 54.486486 | K7: =J7*_xlfn.XLOOKUP(A7,'Parameter Adjustment'!$A$38:$A$63,'Parameter Adjustment'!$C$38:$C$63) -> 1430.8151
A8: Interior Wall sheathing | B8: ='Parameter Adjustment'!F8 -> 0.1 | C8: ='SLC - Site Built'!D8*(1-$B8) -> 1.68075 | D8: ='SLC - Site Built'!E8*(1-$B8) -> 1.1205 | E8: =C8/C$29 -> 0.025615527 | F8: =SUM(C8:D8) -> 2.80125 | G8: ='Parameter Adjustment'!I8 -> 0.2 | H8: =I8/$I$29 -> 0.017332095 | I8: ='NA - Site Built'!I8*(1-G8) -> 2.7243243 | J8: =I8*8 -> 21.794595 | K8: =J8*_xlfn.XLOOKUP(A8,'Parameter Adjustment'!$A$38:$A$63,'Parameter Adjustment'!$C$38:$C$63) -> 572.32605
A9: Exterior Walls framing | B9: ='Parameter Adjustment'!F9 -> 0.1 | C9: ='SLC - Site Built'!D9*(1-$B9) -> 1.68075 | D9: ='SLC - Site Built'!E9*(1-$B9) -> 1.1205 | E9: =C9/C$29 -> 0.025615527 | F9: =SUM(C9:D9) -> 2.80125 | G9: ='Parameter Adjustment'!I9 -> 0.2 | H9: =I9/$I$29 -> 0.098215207 | I9: ='NA - Site Built'!I9*(1-G9) -> 15.437838 | J9: =I9*8 -> 123.5027 | K9: =J9*_xlfn.XLOOKUP(A9,'Parameter Adjustment'!$A$38:$A$63,'Parameter Adjustment'!$C$38:$C$63) -> 3243.181
A10: Exterior Wall sheathing | B10: ='Parameter Adjustment'!F10 -> 0.1 | C10: ='SLC - Site Built'!D10*(1-$B10) -> 1.68075 | D10: ='SLC - Site Built'!E10*(1-$B10) -> 1.1205 | E10: =C10/C$29 -> 0.025615527 | F10: =SUM(C10:D10) -> 2.80125 | G10: ='Parameter Adjustment'!I10 -> 0.2 | H10: =I10/$I$29 -> 0.028886826 | I10: ='NA - Site Built'!I10*(1-G10) -> 4.5405405 | J10: =I10*8 -> 36.324324 | K10: =J10*_xlfn.XLOOKUP(A10,'Parameter Adjustment'!$A$38:$A$63,'Parameter Adjustment'!$C$38:$C$63) -> 953.87676
A11: Roof framing | B11: ='Parameter Adjustment'!F11 -> 0.1 | C11: ='SLC - Site Built'!D11*(1-$B11) -> 1.68075 | D11: ='SLC - Site Built'!E11*(1-$B11) -> 1.1205 | E11: =C11/C$29 -> 0.025615527 | F11: =SUM(C11:D11) -> 2.80125 | G11: ='Parameter Adjustment'!I11 -> 0.2 | H11: =I11/$I$29 -> 0.034664191 | I11: ='NA - Site Built'!I11*(1-G11) -> 5.4486486 | J11: =I11*8 -> 43.589189 | K11: =J11*_xlfn.XLOOKUP(A11,'Parameter Adjustment'!$A$38:$A$63,'Parameter Adjustment'!$C$38:$C$63) -> 1105.4218
A12: Roof sheathing and waterproofing | B12: ='Parameter Adjustment'!F12 -> 0.1 | C12: ='SLC - Site Built'!D12*(1-$B12) -> 1.68075 | D12: ='SLC - Site Built'!E12*(1-$B12) -> 1.1205 | E12: =C12/C$29 -> 0.025615527 | F12: =SUM(C12:D12) -> 2.80125 | G12: ='Parameter Adjustment'!I12 -> 0.2 | H12: =I12/$I$29 -> 0.028886826 | I12: ='NA - Site Built'!I12*(1-G12) -> 4.5405405 | J12: =I12*8 -> 36.324324 | K12: =J12*_xlfn.XLOOKUP(A12,'Parameter Adjustment'!$A$38:$A$63,'Parameter Adjustment'!$C$38:$C$63) -> 921.18486
A13: Mechanical Rough In | B13: ='Parameter Adjustment'!F13 -> 0.1 | C13: ='SLC - Site Built'!D13*(1-$B13) -> 2.5515 | D13: ='SLC - Site Built'!E13*(1-$B13) -> 5.9535 | E13: =C13/C$29 -> 0.038886222 | F13: =SUM(C13:D13) -> 8.505 | G13: ='Parameter Adjustment'!I13 -> 0.2 | H13: =I13/$I$29 -> 0.049107603 | I13: ='NA - Site Built'!I13*(1-G13) -> 7.7189189 | J13: =I13*8 -> 61.751351 | K13: =J13*_xlfn.XLOOKUP(A13,'Parameter Adjustment'!$A$38:$A$63,'Parameter Adjustment'!$C$38:$C$63) -> 1759.9135
A14: Electrical Rough In | B14: ='Parameter Adjustment'!F14 -> 0.1 | C14: ='SLC - Site Built'!D14*(1-$B14) -> 2.592 | D14: ='SLC - Site Built'!E14*(1-$B14) -> 6.048 | E14: =C14/C$29 -> 0.039503463 | F14: =SUM(C14:D14) -> 8.64 | G14: ='Parameter Adjustment'!I14 -> 0.2 | H14: =I14/$I$29 -> 0.031775508 | I14: ='NA - Site Built'!I14*(1-G14) -> 4.9945946 | J14: =I14*8 -> 39.956757 | K14: =J14*_xlfn.XLOOKUP(A14,'Parameter Adjustment'!$A$38:$A$63,'Parameter Adjustment'!$C$38:$C$63) -> 1210.6897
... A25: Exterior Roof Finishing | B25: ='Parameter Adjustment'!F25 -> 0.1 | C25: ='SLC - Site Built'!D25*(1-$B25) -> 3.159 | D25: ='SLC - Site Built'!E25*(1-$B25) -> 2.106 | E25: =C25/C$29 -> 0.048144846 | F25: =SUM(C25:D25) -> 5.265 | G25: ='Parameter Adjustment'!I25 -> 0.2 | H25: =I25/$I$29 -> 0.028886826 | I25: ='NA - Site Built'!I25*(1-G25) -> 4.5405405 | J25: =I25*8 -> 36.324324 | K25: =J25*_xlfn.XLOOKUP(A25,'Parameter Adjustment'!$A$38:$A$63,'Parameter Adjustment'!$C$38:$C$63) -> 921.18486
A26: Transportation | B26: ='Parameter Adjustment'!F26 -> 0 | C26: ='SLC - Site Built'!D26*(1-$B26) -> 0 | D26: ='Parameter Adjustment'!S3*'Parameter Adjustment'!T3/IF('Parameter Adjustment'!Z2="1,000 square-foot home",1,1000) -> 0.7 | E26: =C26/C$29 -> 0 | F26: =SUM(C26:D26) -> 0.7 | G26: ='Parameter Adjustment'!I26 -> 0 | H26: =I26/$I$29 -> 0.019085938 | I26: 3 | J26: =I26*8 -> 24 | K26: =F26 -> 0.7
A27: On-site Installation | B27: ='Parameter Adjustment'!F27 -> 0 | C27: ='SLC - Site Built'!D27*(1-$B27) -> 0 | D27: ='Parameter Adjustment'!X2*'Parameter Adjustment'!X3/IF('Parameter Adjustment'!Z2="1,000 square-foot home",1,1000) -> 10 | E27: =C27/C$29 -> 0 | F27: =SUM(C27:D27) -> 10 | G27: ='Parameter Adjustment'!I27 -> 0 | H27: =I27/$I$29 -> 0.19085938 | I27: 30 | J27: =I27*8 -> 240 | K27: =J27*_xlfn.XLOOKUP("Assembly",'Parameter Adjustment'!$A$38:$A$63,'Parameter Adjustment'!$C$38:$C$63) -> 5510.4
A28: All Inspections | B28: ='Parameter Adjustment'!F28 -> 0.8 | C28: ='SLC - Site Built'!D28*(1-$B28) -> 0 | D28: ='SLC - Site Built'!E28*(1-$B28) -> 2.52 | E28: =C28/C$29 -> 0 | F28: =SUM(C28:D28) -> 2.52 | G28: ='Parameter Adjustment'!I28 -> 0.8 | H28: =I28/$I$29 -> 0.015887754 | I28: ='NA - Site Built'!I28*(1-G28) -> 2.4972973 | J28: =I28*8 -> 19.978378 | K28: =J28*_xlfn.XLOOKUP(A28,'Parameter Adjustment'!$A$38:$A$63,'Parameter Adjustment'!$C$38:$C$63) -> 685.65795
A29: =_xlfn.CONCAT("Total Construction Costs (",'Parameter Adjustment'!$Z$2,")") -> Total Construction Costs (Square foot) | C29: =SUM(C3:C28) -> 65.6145 | D29: =SUM(D3:D28) -> 73.9805 | E29: =SUM(E3:E28) -> 1 | F29: =SUM(F3:F28) -> 139.595 | H29: =SUM(H3:H28) -> 1 | I29: =SUM(I3:I28) -> 157.18378 | J29: =SUM(J3:J28) -> 1257.4703 | K29: =SUM(K3:K28) -> 32293.533
A31: Profit Calculation | B31: Value | C31: Percentage
A32: Total Construction Costs | B32: =F29 -> 139.595 | C32: =B32/$B$36 -> 0.59797153
A33: Other Costs | B33: ='Profit Calculation'!B11*'Profit Calculation'!F10*IF('Parameter Adjustment'!Z2="1,000 square-foot home",1000,1) -> 57.763623 | C33: =B33/$B$36 -> 0.24743724
A34: Fixed Costs | B34: =IF('Parameter Adjustment'!$Z$2="Square foot",'Parameter Adjustment'!AJ4,'Parameter Adjustment'!AJ4*1000) -> 19.152 | C34: =B34/$B$36 -> 0.082039835
A35: Profit | B35: =B36-B32-B33-B34 -> 16.936945 | C35: =B35/$B$36 -> 0.07255139
A36: Total Selling Price | B36: ='SLC - Site Built'!B37 -> 233.44757 | C36: =B36/$B$36 -> 1
A39: Cost Type | B39: % of Total Costs | C39: Profit | D39: Profit Margin
A40: Total Construction Costs | B40: =B32/SUM($B$32:$B$34) -> 0.64474896 | C40: =B40*$B$35 -> 10.920078 | D40: =C40/$B$36 -> 0.046777433
A41: Other Costs | B41: =B33/SUM($B$32:$B$34) -> 0.26679348 | C41: =B41*$B$35 -> 4.5186667 | D41: =C41/$B$36 -> 0.019356238
A42: Fixed Costs | B42: =B34/SUM($B$32:$B$34) -> 0.088457553 | C42: =B42*$B$35 -> 1.4982008 | D42: =C42/$B$36 -> 0.0064177184
A43: Total | B43: =SUM(B40:B42) -> 1 | C43: =SUM(C40:C42) -> 16.936945 | D43: =SUM(D40:D42) -> 0.07255139

Sheet NA - Site Built
B1: Costs | H1: Time | J1: assume 8 hours per day | K1: Working hours * hourly rate
A2: Construction Process | B2: % Material Cost | C2: % Labor Cost | D2: Material Cost | E2: Labor Cost | F2: % of Total Cost | G2: Total Cost | H2: % of Total Time | I2: Total Time (days) | J2: Total Time per Employee (working hours) | K2: Total Labor Cost per Employee
A3: Site Work | B3: ='Parameter Adjustment'!B3 -> 0.6 | C3: ='Parameter Adjustment'!C3 -> 0.4 | D3: ='Parameter Adjustment'!$N$4*B3*$F3 -> 7.3416 | E3: ='Parameter Adjustment'!$N$4*C3*$F3 -> 4.8944 | F3: ='Parameter Adjustment'!D3 -> 0.076 | G3: =SUM(D3:E3) -> 12.236 | H3: ='Parameter Adjustment'!E3 -> 0.10810811 | I3: =H3*'Parameter Adjustment'!$P$2 -> 22.702703 | J3: =I3*8 -> 181.62162 | K3: =J3*_xlfn.XLOOKUP(A3,'Parameter Adjustment'!$A$38:$A$63,'Parameter Adjustment'!$D$38:$D$63) -> 4475.1568
A4: Foundations | B4: ='Parameter Adjustment'!B4 -> 0.7 | C4: ='Parameter Adjustment'!C4 -> 0.3 | D4: ='Parameter Adjustment'!$N$4*B4*$F4 -> 11.8335 | E4: ='Parameter Adjustment'!$N$4*C4*$F4 -> 5.0715 | F4: ='Parameter Adjustment'!D4 -> 0.105 | G4: =SUM(D4:E4) -> 16.905 | H4: ='Parameter Adjustment'!E4 -> 0.10810811 | I4: =H4*'Parameter Adjustment'!$P$2 -> 22.702703 | J4: =I4*8 -> 181.62162 | K4: =J4*_xlfn.XLOOKUP(A4,'Parameter Adjustment'!$A$38:$A$63,'Parameter Adjustment'!$D$38:$D$63) -> 4475.1568
A5: Floor framing | B5: ='Parameter Adjustment'!B5 -> 0.6 | C5: ='Parameter Adjustment'!C5 -> 0.4 | D5: ='Parameter Adjustment'!$N$4*B5*$F5 -> 2.00445 | E5: ='Parameter Adjustment'!$N$4*C5*$F5 -> 1.3363 | F5: ='Parameter Adjustment'!D5 -> 0.02075 | G5: =SUM(D5:E5) -> 3.34075 | H5: ='Parameter Adjustment'!E5 -> 0.032432432 | I5: =H5*'Parameter Adjustment'!$P$2 -> 6.8108108 | J5: =I5*8 -> 54.486486 | K5: =J5*_xlfn.XLOOKUP(A5,'Parameter Adjustment'!$A$38:$A$63,'Parameter Adjustment'!$D$38:$D$63) -> 1586.1016
A6: Floor sheathing | B6: ='Parameter Adjustment'!B6 -> 0.6 | C6: ='Parameter Adjustment'!C6 -> 0.4 | D6: ='Parameter Adjustment'!$N$4*B6*$F6 -> 2.00445 | E6: ='Parameter Adjustment'!$N$4*C6*$F6 -> 1.3363 | F6: ='Parameter Adjustment'!D6 -> 0.02075 | G6: =SUM(D6:E6) -> 3.34075 | H6: ='Parameter Adjustment'!E6 -> 0.016216216 | I6: =H6*'Parameter Adjustment'!$P$2 -> 3.4054054 | J6: =I6*8 -> 27.243243 | K6: =J6*_xlfn.XLOOKUP(A6,'Parameter Adjustment'!$A$38:$A$63,'Parameter Adjustment'!$D$38:$D$63) -> 793.05081
A7: Interior Wall framing | B7: ='Parameter Adjustment'!B7 -> 0.6 | C7: ='Parameter Adjustment'!C7 -> 0.4 | D7: ='Parameter Adjustment'!$N$4*B7*$F7 -> 2.00445 | E7: ='Parameter Adjustment'!$N$4*C7*$F7 -> 1.3363 | F7: ='Parameter Adjustment'!D7 -> 0.02075 | G7: =SUM(D7:E7) -> 3.34075 | H7: ='Parameter Adjustment'!E7 -> 0.040540541 | I7: =H7*'Parameter Adjustment'!$P$2 -> 8.5135135 | J7: =I7*8 -> 68.108108 | K7: =J7*_xlfn.XLOOKUP(A7,'Parameter Adjustment'!$A$38:$A$63,'Parameter Adjustment'!$D$38:$D$63) -> 2097.0486
A8: Interior Wall sheathing | B8: ='Parameter Adjustment'!B8 -> 0.6 | C8: ='Parameter Adjustment'!C8 -> 0.4 | D8: ='Parameter Adjustment'!$N$4*B8*$F8 -> 2.00445 | E8: ='Parameter Adjustment'!$N$4*C8*$F8 -> 1.3363 | F8: ='Parameter Adjustment'!D8 -> 0.02075 | G8: =SUM(D8:E8) -> 3.34075 | H8: ='Parameter Adjustment'!E8 -> 0.016216216 | I8: =H8*'Parameter Adjustment'!$P$2 -> 3.4054054 | J8: =I8*8 -> 27.243243 | K8: =J8*_xlfn.XLOOKUP(A8,'Parameter Adjustment'!$A$38:$A$63,'Parameter Adjustment'!$D$38:$D$63) -> 838.81946
A9: Exterior Walls framing | B9: ='Parameter Adjustment'!B9 -> 0.6 | C9: ='Parameter Adjustment'!C9 -> 0.4 | D9: ='Parameter Adjustment'!$N$4*B9*$F9 -> 2.00445 | E9: ='Parameter Adjustment'!$N$4*C9*$F9 -> 1.3363 | F9: ='Parameter Adjustment'!D9 -> 0.02075 | G9: =SUM(D9:E9) -> 3.34075 | H9: ='Parameter Adjustment'!E9 -> 0.091891892 | I9: =H9*'Parameter Adjustment'!$P$2 -> 19.297297 | J9: =I9*8 -> 154.37838 | K9: =J9*_xlfn.XLOOKUP(A9,'Parameter Adjustment'!$A$38:$A$63,'Parameter Adjustment'!$D$38:$D$63) -> 4753.3103
A10: Exterior Wall sheathing | B10: ='Parameter Adjustment'!B10 -> 0.6 | C10: ='Parameter Adjustment'!C10 -> 0.4 | D10: ='Parameter Adjustment'!$N$4*B10*$F10 -> 2.00445 | E10: ='Parameter Adjustment'!$N$4*C10*$F10 -> 1.3363 | F10: ='Parameter Adjustment'!D10 -> 0.02075 | G10: =SUM(D10:E10) -> 3.34075 | H10: ='Parameter Adjustment'!E10 -> 0.027027027 | I10: =H10*'Parameter Adjustment'!$P$2 -> 5.6756757 | J10: =I10*8 -> 45.405405 | K10: =J10*_xlfn.XLOOKUP(A10,'Parameter Adjustment'!$A$38:$A$63,'Parameter Adjustment'!$D$38:$D$63) -> 1398.0324
A11: Roof framing | B11: ='Parameter Adjustment'!B11 -> 0.6 | C11: ='Parameter Adjustment'!C11 -> 0.4 | D11: ='Parameter Adjustment'!$N$4*B11*$F11 -> 2.00445 | E11: ='Parameter Adjustment'!$N$4*C11*$F11 -> 1.3363 | F11: ='Parameter Adjustment'!D11 -> 0.02075 | G11: =SUM(D11:E11) -> 3.34075 | H11: ='Parameter Adjustment'!E11 -> 0.032432432 | I11: =H11*'Parameter Adjustment'!$P$2 -> 6.8108108 | J11: =I11*8 -> 54.486486 | K11: =J11*_xlfn.XLOOKUP(A11,'Parameter Adjustment'!$A$38:$A$63,'Parameter Adjustment'!$D$38:$D$63) -> 1495.6541
A12: Roof sheathing and waterproofing | B12: ='Parameter Adjustment'!B12 -> 0.6 | C12: ='Parameter Adjustment'!C12 -> 0.4 | D12: ='Parameter Adjustment'!$N$4*B12*$F12 -> 2.00445 | E12: ='Parameter Adjustment'!$N$4*C12*$F12 -> 1.3363 | F12: ='Parameter Adjustment'!D12 -> 0.02075 | G12: =SUM(D12:E12) -> 3.34075 | H12: ='Parameter Adjustment'!E12 -> 0.027027027 | I12: =H12*'Parameter Adjustment'!$P$2 -> 5.6756757 | J12: =I12*8 -> 45.405405 | K12: =J12*_xlfn.XLOOKUP(A12,'Parameter Adjustment'!$A$38:$A$63,'Parameter Adjustment'!$D$38:$D$63) -> 1246.3784
A13: Mechanical Rough In | B13: ='Parameter Adjustment'!B13 -> 0.3 | C13: ='Parameter Adjustment'!C13 -> 0.7 | D13: ='Parameter Adjustment'!$N$4*B13*$F13 -> 3.0429 | E13: ='Parameter Adjustment'!$N$4*C13*$F13 -> 7.1001 | F13: ='Parameter Adjustment'!D13 -> 0.063 | G13: =SUM(D13:E13) -> 10.143 | H13: ='Parameter Adjustment'!E13 -> 0.045945946 | I13: =H13*'Parameter Adjustment'!$P$2 -> 9.6486486 | J13: =I13*8 -> 77.189189 | K13: =J13*_xlfn.XLOOKUP(A13,'Parameter Adjustment'!$A$38:$A$63,'Parameter Adjustment'!$D$38:$D$63) -> 2287.1157
A14: Electrical Rough In | B14: ='Parameter Adjustment'!B14 -> 0.3 | C14: ='Parameter Adjustment'!C14 -> 0.7 | D14: ='Parameter Adjustment'!$N$4*B14*$F14 -> 3.0912 | E14: ='Parameter Adjustment'!$N$4*C14*$F14 -> 7.2128 | F14: ='Parameter Adjustment'!D14 -> 0.064 | G14: =SUM(D14:E14) -> 10.304 | H14: ='Parameter Adjustment'!E14 -> 0.02972973 | I14: =H14*'Parameter Adjustment'!$P$2 -> 6.2432432 | J14: =I14*8 -> 49.945946 | K14: =J14*_xlfn.XLOOKUP(A14,'Parameter Adjustment'!$A$38:$A$63,'Parameter Adjustment'!$D$38:$D$63) -> 1671.6908
... A25: Exterior Roof Finishing | B25: ='Parameter Adjustment'!B25 -> 0.6 | C25: ='Parameter Adjustment'!C25 -> 0.4 | D25: ='Parameter Adjustment'!$N$4*B25*$F25 -> 3.7674 | E25: ='Parameter Adjustment'!$N$4*C25*$F25 -> 2.5116 | F25: ='Parameter Adjustment'!D25 -> 0.039 | G25: =SUM(D25:E25) -> 6.279 | H25: ='Parameter Adjustment'!E25 -> 0.027027027 | I25: =H25*'Parameter Adjustment'!$P$2 -> 5.6756757 | J25: =I25*8 -> 45.405405 | K25: =J25*_xlfn.XLOOKUP(A25,'Parameter Adjustment'!$A$38:$A$63,'Parameter Adjustment'!$D$38:$D$63) -> 1246.3784
A26: Transportation | B26: ='Parameter Adjustment'!B26 -> 0 | C26: ='Parameter Adjustment'!C26 -> 0 | D26: ='Parameter Adjustment'!$N$4*B26*$F26 -> 0 | E26: ='Parameter Adjustment'!$N$4*C26*$F26 -> 0 | F26: ='Parameter Adjustment'!D26 -> 0 | H26: ='Parameter Adjustment'!E26 -> 0 | I26: =H26*'Parameter Adjustment'!$P$2 -> 0
A27: On-site Installation | B27: ='Parameter Adjustment'!B27 -> 0 | C27: ='Parameter Adjustment'!C27 -> 0 | D27: ='Parameter Adjustment'!$N$4*B27*$F27 -> 0 | E27: ='Parameter Adjustment'!$N$4*C27*$F27 -> 0 | F27: ='Parameter Adjustment'!D27 -> 0 | G27: =SUM(D27:E27) -> 0 | H27: ='Parameter Adjustment'!E27 -> 0 | I27: =H27*'Parameter Adjustment'!$P$2 -> 0
A28: All Inspections | B28: ='Parameter Adjustment'!B28 -> 0 | C28: ='Parameter Adjustment'!C28 -> 1 | D28: ='Parameter Adjustment'!$N$4*B28*$F28 -> 0 | E28: ='Parameter Adjustment'!$N$4*C28*$F28 -> 13.524 | F28: ='Parameter Adjustment'!D28 -> 0.084 | G28: =SUM(D28:E28) -> 13.524 | H28: ='Parameter Adjustment'!E28 -> 0.059459459 | I28: =H28*'Parameter Adjustment'!$P$2 -> 12.486486 | J28: =I28*8 -> 99.891892 | K28: =J28*_xlfn.XLOOKUP(A28,'Parameter Adjustment'!$A$38:$A$63,'Parameter Adjustment'!$D$38:$D$63) -> 3671.027
A29: =_xlfn.CONCAT("Total Construction Costs (",'Parameter Adjustment'!$Z$2,")") -> Total Construction Costs (Square foot) | D29: =SUM(D3:D28) -> 76.1208 | E29: =SUM(E3:E28) -> 84.8792 | F29: =SUM(F3:F28) -> 1 | G29: =SUM(G3:G28) -> 161 | H29: =SUM(H3:H28) -> 1 | I29: =SUM(I3:I28) -> 210 | J29: =SUM(J3:J28) -> 1680 | K29: =SUM(K3:K28) -> 49467.736
A33: Profit Calculation | B33: Value | C33: Percentage
A34: Total Construction Costs | B34: =G29 -> 161 | C34: =B34/$B$37 -> 0.64254257
A35: Other Costs | B35: ='Profit Calculation'!B11*IF('Parameter Adjustment'!Z2="1,000 square-foot home",1000,1) -> 61.999622 | C35: =B35/$B$37 -> 0.24743724
A36: Profit | B36: ='Profit Calculation'!B12*IF('Parameter Adjustment'!Z2="1,000 square-foot home",1000,1) -> 27.567435 | C36: =B36/$B$37 -> 0.11002019
A37: Total Selling Price | B37: =SUM(B34:B36) -> 250.56706 | C37: =B37/$B$37 -> 1
A40: Cost Type | B40: % of Total Costs | C40: Profit | D40: Percentage
A41: Total Construction Costs | B41: =B34/SUM(B34:B35) -> 0.72197432 | C41: =B41*B36 -> 19.90298 | D41: =C41/B37 -> 0.07943175
A42: Other Costs | B42: =B35/SUM(B34:B35) -> 0.27802568 | C42: =B42*B36 -> 7.6644549 | D42: =C42/B37 -> 0.030588438
A43: Total | B43: =SUM(B41:B42) -> 1 | C43: =SUM(C41:C42) -> 27.567435 | D43: =SUM(D41:D42) -> 0.11002019

Sheet NA - Local
B1: Costs | G1: Time | J1: assume 8 hours per day | K1: Working hours * hourly rate
A2: Construction Process | B2: % Cost Savings | C2: Material Cost | D2: Labor Cost | E2: % of Total Cost | F2: Total Cost | G2: % Time Savings | H2: % of Total Time | I2: Total Time (days) | J2: Total Time per Employee (working hours) | K2: Total Labor Cost per Employee
A3: Site Work | B3: ='Parameter Adjustment'!F3 -> 0 | C3: ='NA - Site Built'!D3*(1-$B3) -> 7.3416 | D3: ='NA - Site Built'!E3*(1-$B3) -> 4.8944 | E3: =C3/C$29 -> 0.10424525 | F3: =SUM(C3:D3) -> 12.236 | G3: ='Parameter Adjustment'!I3 -> 1 | H3: =I3/$I$29 -> 0 | I3: ='NA - Site Built'!I3*(1-G3) -> 0 | J3: =I3*8 -> 0 | K3: =J3*_xlfn.XLOOKUP(A3,'Parameter Adjustment'!$A$38:$A$63,'Parameter Adjustment'!$D$38:$D$63) -> 0
A4: Foundations | B4: ='Parameter Adjustment'!F4 -> 0 | C4: ='NA - Site Built'!D4*(1-$B4) -> 11.8335 | D4: ='NA - Site Built'!E4*(1-$B4) -> 5.0715 | E4: =C4/C$29 -> 0.16802688 | F4: =SUM(C4:D4) -> 16.905 | G4: ='Parameter Adjustment'!I4 -> 1 | H4: =I4/$I$29 -> 0 | I4: ='NA - Site Built'!I4*(1-G4) -> 0 | J4: =I4*8 -> 0 | K4: =J4*_xlfn.XLOOKUP(A4,'Parameter Adjustment'!$A$38:$A$63,'Parameter Adjustment'!$D$38:$D$63) -> 0
A5: Floor framing | B5: ='Parameter Adjustment'!F5 -> 0.1 | C5: ='NA - Site Built'!D5*(1-$B5) -> 1.804005 | D5: ='NA - Site Built'!E5*(1-$B5) -> 1.20267 | E5: =C5/C$29 -> 0.025615527 | F5: =SUM(C5:D5) -> 3.006675 | G5: ='Parameter Adjustment'!I5 -> 0.2 | H5: =I5/$I$29 -> 0.034664191 | I5: ='NA - Site Built'!I5*(1-G5) -> 5.4486486 | J5: =I5*8 -> 43.589189 | K5: =J5*_xlfn.XLOOKUP(A5,'Parameter Adjustment'!$A$38:$A$63,'Parameter Adjustment'!$D$38:$D$63) -> 1268.8813
A6: Floor sheathing | B6: ='Parameter Adjustment'!F6 -> 0.1 | C6: ='NA - Site Built'!D6*(1-$B6) -> 1.804005 | D6: ='NA - Site Built'!E6*(1-$B6) -> 1.20267 | E6: =C6/C$29 -> 0.025615527 | F6: =SUM(C6:D6) -> 3.006675 | G6: ='Parameter Adjustment'!I6 -> 0.2 | H6: =I6/$I$29 -> 0.017332095 | I6: ='NA - Site Built'!I6*(1-G6) -> 2.7243243 | J6: =I6*8 -> 21.794595 | K6: =J6*_xlfn.XLOOKUP(A6,'Parameter Adjustment'!$A$38:$A$63,'Parameter Adjustment'!$D$38:$D$63) -> 634.44065
A7: Interior Wall framing | B7: ='Parameter Adjustment'!F7 -> 0.1 | C7: ='NA - Site Built'!D7*(1-$B7) -> 1.804005 | D7: ='NA - Site Built'!E7*(1-$B7) -> 1.20267 | E7: =C7/C$29 -> 0.025615527 | F7: =SUM(C7:D7) -> 3.006675 | G7: ='Parameter Adjustment'!I7 -> 0.2 | H7: =I7/$I$29 -> 0.043330238 | I7: ='NA - Site Built'!I7*(1-G7) -> 6.8108108 | J7: =I7*8 -> 54.486486 | K7: =J7*_xlfn.XLOOKUP(A7,'Parameter Adjustment'!$A$38:$A$63,'Parameter Adjustment'!$D$38:$D$63) -> 1677.6389
A8: Interior Wall sheathing | B8: ='Parameter Adjustment'!F8 -> 0.1 | C8: ='NA - Site Built'!D8*(1-$B8) -> 1.804005 | D8: ='NA - Site Built'!E8*(1-$B8) -> 1.20267 | E8: =C8/C$29 -> 0.025615527 | F8: =SUM(C8:D8) -> 3.006675 | G8: ='Parameter Adjustment'!I8 -> 0.2 | H8: =I8/$I$29 -> 0.017332095 | I8: ='NA - Site Built'!I8*(1-G8) -> 2.7243243 | J8: =I8*8 -> 21.794595 | K8: =J8*_xlfn.XLOOKUP(A8,'Parameter Adjustment'!$A$38:$A$63,'Parameter Adjustment'!$D$38:$D$63) -> 671.05557
A9: Exterior Walls framing | B9: ='Parameter Adjustment'!F9 -> 0.1 | C9: ='NA - Site Built'!D9*(1-$B9) -> 1.804005 | D9: ='NA - Site Built'!E9*(1-$B9) -> 1.20267 | E9: =C9/C$29 -> 0.025615527 | F9: =SUM(C9:D9) -> 3.006675 | G9: ='Parameter Adjustment'!I9 -> 0.2 | H9: =I9/$I$29 -> 0.098215207 | I9: ='NA - Site Built'!I9*(1-G9) -> 15.437838 | J9: =I9*8 -> 123.5027 | K9: =J9*_xlfn.XLOOKUP(A9,'Parameter Adjustment'!$A$38:$A$63,'Parameter Adjustment'!$D$38:$D$63) -> 3802.6482
A10: Exterior Wall sheathing | B10: ='Parameter Adjustment'!F10 -> 0.1 | C10: ='NA - Site Built'!D10*(1-$B10) -> 1.804005 | D10: ='NA - Site Built'!E10*(1-$B10) -> 1.20267 | E10: =C10/C$29 -> 0.025615527 | F10: =SUM(C10:D10) -> 3.006675 | G10: ='Parameter Adjustment'!I10 -> 0.2 | H10: =I10/$I$29 -> 0.028886826 | I10: ='NA - Site Built'!I10*(1-G10) -> 4.5405405 | J10: =I10*8 -> 36.324324 | K10: =J10*_xlfn.XLOOKUP(A10,'Parameter Adjustment'!$A$38:$A$63,'Parameter Adjustment'!$D$38:$D$63) -> 1118.4259
A11: Roof framing | B11: ='Parameter Adjustment'!F11 -> 0.1 | C11: ='NA - Site Built'!D11*(1-$B11) -> 1.804005 | D11: ='NA - Site Built'!E11*(1-$B11) -> 1.20267 | E11: =C11/C$29 -> 0.025615527 | F11: =SUM(C11:D11) -> 3.006675 | G11: ='Parameter Adjustment'!I11 -> 0.2 | H11: =I11/$I$29 -> 0.034664191 | I11: ='NA - Site Built'!I11*(1-G11) -> 5.4486486 | J11: =I11*8 -> 43.589189 | K11: =J11*_xlfn.XLOOKUP(A11,'Parameter Adjustment'!$A$38:$A$63,'Parameter Adjustment'!$D$38:$D$63) -> 1196.5232
A12: Roof sheathing and waterproofing | B12: ='Parameter Adjustment'!F12 -> 0.1 | C12: ='NA - Site Built'!D12*(1-$B12) -> 1.804005 | D12: ='NA - Site Built'!E12*(1-$B12) -> 1.20267 | E12: =C12/C$29 -> 0.025615527 | F12: =SUM(C12:D12) -> 3.006675 | G12: ='Parameter Adjustment'!I12 -> 0.2 | H12: =I12/$I$29 -> 0.028886826 | I12: ='NA - Site Built'!I12*(1-G12) -> 4.5405405 | J12: =I12*8 -> 36.324324 | K12: =J12*_xlfn.XLOOKUP(A12,'Parameter Adjustment'!$A$38:$A$63,'Parameter Adjustment'!$D$38:$D$63) -> 997.1027
A13: Mechanical Rough In | B13: ='Parameter Adjustment'!F13 -> 0.1 | C13: ='NA - Site Built'!D13*(1-$B13) -> 2.73861 | D13: ='NA - Site Built'!E13*(1-$B13) -> 6.39009 | E13: =C13/C$29 -> 0.038886222 | F13: =SUM(C13:D13) -> 9.1287 | G13: ='Parameter Adjustment'!I13 -> 0.2 | H13: =I13/$I$29 -> 0.049107603 | I13: ='NA - Site Built'!I13*(1-G13) -> 7.7189189 | J13: =I13*8 -> 61.751351 | K13: =J13*_xlfn.XLOOKUP(A13,'Parameter Adjustment'!$A$38:$A$63,'Parameter Adjustment'!$D$38:$D$63) -> 1829.6925
A14: Electrical Rough In | B14: ='Parameter Adjustment'!F14 -> 0.1 | C14: ='NA - Site Built'!D14*(1-$B14) -> 2.78208 | D14: ='NA - Site Built'!E14*(1-$B14) -> 6.49152 | E14: =C14/C$29 -> 0.039503463 | F14: =SUM(C14:D14) -> 9.2736 | G14: ='Parameter Adjustment'!I14 -> 0.2 | H14: =I14/$I$29 -> 0.031775508 | I14: ='NA - Site Built'!I14*(1-G14) -> 4.9945946 | J14: =I14*8 -> 39.956757 | K14: =J14*_xlfn.XLOOKUP(A14,'Parameter Adjustment'!$A$38:$A$63,'Parameter Adjustment'!$D$38:$D$63) -> 1337.3526
... A25: Exterior Roof Finishing | B25: ='Parameter Adjustment'!F25 -> 0.1 | C25: ='NA - Site Built'!D25*(1-$B25) -> 3.39066 | D25: ='NA - Site Built'!E25*(1-$B25) -> 2.26044 | E25: =C25/C$29 -> 0.048144846 | F25: =SUM(C25:D25) -> 5.6511 | G25: ='Parameter Adjustment'!I25 -> 0.2 | H25: =I25/$I$29 -> 0.028886826 | I25: ='NA - Site Built'!I25*(1-G25) -> 4.5405405 | J25: =I25*8 -> 36.324324 | K25: =J25*_xlfn.XLOOKUP(A25,'Parameter Adjustment'!$A$38:$A$63,'Parameter Adjustment'!$D$38:$D$63) -> 997.1027
A26: Transportation | B26: ='Parameter Adjustment'!F26 -> 0 | C26: ='NA - Site Built'!D26*(1-$B26) -> 0 | D26: ='Parameter Adjustment'!S3*'Parameter Adjustment'!T3/IF('Parameter Adjustment'!Z2="1,000 square-foot home",1,1000) -> 0.7 | E26: =C26/C$29 -> 0 | F26: =SUM(C26:D26) -> 0.7 | G26: ='Parameter Adjustment'!I26 -> 0 | H26: =I26/$I$29 -> 0.019085938 | I26: 3 | J26: =I26*8 -> 24 | K26: =F26 -> 0.7
A27: On-site Installation | B27: ='Parameter Adjustment'!F27 -> 0 | C27: ='NA - Site Built'!D27*(1-$B27) -> 0 | D27: ='Parameter Adjustment'!X2*'Parameter Adjustment'!X3/IF('Parameter Adjustment'!Z2="1,000 square-foot home",1,1000) -> 10 | E27: =C27/C$29 -> 0 | F27: =SUM(C27:D27) -> 10 | G27: ='Parameter Adjustment'!I27 -> 0 | H27: =I27/$I$29 -> 0.19085938 | I27: 30 | J27: =I27*8 -> 240 | K27: =J27*_xlfn.XLOOKUP("Assembly",'Parameter Adjustment'!$A$38:$A$63,'Parameter Adjustment'!$D$38:$D$63) -> 5913.6
A28: All Inspections | B28: ='Parameter Adjustment'!F28 -> 0.8 | C28: ='NA - Site Built'!D28*(1-$B28) -> 0 | D28: ='NA - Site Built'!E28*(1-$B28) -> 2.7048 | E28: =C28/C$29 -> 0 | F28: =SUM(C28:D28) -> 2.7048 | G28: ='Parameter Adjustment'!I28 -> 0.8 | H28: =I28/$I$29 -> 0.015887754 | I28: ='NA - Site Built'!I28*(1-G28) -> 2.4972973 | J28: =I28*8 -> 19.978378 | K28: =J28*_xlfn.XLOOKUP(A28,'Parameter Adjustment'!$A$38:$A$63,'Parameter Adjustment'!$D$38:$D$63) -> 734.20541
A29: =_xlfn.CONCAT("Total Construction Costs (",'Parameter Adjustment'!$Z$2,")") -> Total Construction Costs (Square foot) | C29: =SUM(C3:C28) -> 70.42623 | D29: =SUM(D3:D28) -> 78.62107 | E29: =SUM(E3:E28) -> 1 | F29: =SUM(F3:F28) -> 149.0473 | H29: =SUM(H3:H28) -> 1 | I29: =SUM(I3:I28) -> 157.18378 | J29: =SUM(J3:J28) -> 1257.4703 | K29: =SUM(K3:K28) -> 36125.622
A33: Profit Calculation | B33: Value | C33: Percentage
A34: Total Construction Costs | B34: =F29 -> 149.0473 | C34: =B34/$B$38 -> 0.59483997
A35: Other Costs | B35: ='Profit Calculation'!B11*IF('Parameter Adjustment'!Z2="1,000 square-foot home",1000,1) -> 61.999622 | C35: =B35/$B$38 -> 0.24743724
A36: Fixed Costs | B36: =IF('Parameter Adjustment'!$Z$2="Square foot",'Parameter Adjustment'!AJ4,'Parameter Adjustment'!AJ4*1000) -> 19.152 | C36: =B36/$B$38 -> 0.076434629
A37: Profit | B37: =B38-B34-B35-B36 -> 20.368135 | C37: =B37/$B$38 -> 0.081288159
A38: Total Selling Price | B38: ='NA - Site Built'!B37 -> 250.56706 | C38: =B38/$B$38 -> 1
A41: Cost Type | B41: % of Total Costs | C41: Profit | D41: Profit Margin
A42: Total Construction Costs | B42: =B34/SUM($B$34:$B$36) -> 0.64747175 | C42: =B42*$B$37 -> 13.187792 | D42: =C42/$B$38 -> 0.052631787
A43: Other Costs | B43: =B35/SUM($B$34:$B$36) -> 0.26933064 | C43: =B43*$B$37 -> 5.4857627 | D43: =C43/$B$38 -> 0.021893392
A44: Fixed Costs | B44: =B36/SUM($B$34:$B$36) -> 0.083197609 | C44: =B44*$B$37 -> 1.6945801 | D44: =C44/$B$38 -> 0.0067629805
A45: Total | B45: =SUM(B42:B44) -> 1 | C45: =SUM(C42:C44) -> 20.368135 | D45: =SUM(D42:D44) -> 0.081288159

Sheet Multi-Market Modular
B1: SLC Modular | L1: LA Modular | Y1: Assumptions:
A2: Construction Process | B2: % Cost Savings | C2: Material Cost | D2: Labor Cost | E2: % of Total Cost | F2: Total Cost | G2: % Time Savings | H2: % of Total Time | I2: Total Time (days) | J2: Total Time per Employee (working hours) | K2: Total Labor Cost per Employee | L2: Construction Process | M2: % Cost Savings | N2: Material Cost | O2: Labor Cost | P2: % of Total Cost | Q2: Total Cost | R2: % Time Savings | S2: % of Total Time | T2: Total Time (days) | U2: Total Time per Employee (working hours) | V2: Total Labor Cost per Employee | W2: Comments | Y2: Materials same for both markets (no change in quality, etc.)
A3: Site Work | B3: ='Parameter Adjustment'!J3 -> 0 | C3: ='SLC - Site Built'!$D3*(1-$B3) -> 6.84 | D3: ='SLC - Site Built'!$E3*(1-$B3) -> 4.56 | E3: =F3/F$29 -> 0.088667652 | F3: =SUM(C3:D3) -> 11.4 | G3: ='Parameter Adjustment'!I3 -> 1 | H3: =I3/$I$29 -> 0 | I3: ='NA - Site Built'!I3*(1-G3) -> 0 | J3: =I3*8 -> 0 | K3: =J3*_xlfn.XLOOKUP(A3,'Parameter Adjustment'!$A$38:$A$63,'Parameter Adjustment'!$C$38:$C$63) -> 0 | L3: Site Work | M3: ='Parameter Adjustment'!J3 -> 0 | N3: ='LA - Site Built'!$D3*(1-$M3) -> 14.592 | O3: ='LA - Site Built'!$E3*(1-$M3) -> 9.728 | P3: =Q3/Q$29 -> 0.14394578 | Q3: =SUM(N3:O3) -> 24.32 | R3: ='Parameter Adjustment'!I3 -> 1 | S3: =T3/T$29 -> 0 | T3: ='NA - Site Built'!I3*(1-R3) -> 0 | U3: =T3*8 -> 0 | V3: =U3*_xlfn.XLOOKUP(L3,'Parameter Adjustment'!$A$38:$A$63,'Parameter Adjustment'!$B$38:$B$63) -> 0 | W3: California | Y3: Same on-site installation costs
A4: Foundations | B4: ='Parameter Adjustment'!J4 -> 0 | C4: ='SLC - Site Built'!$D4*(1-$B4) -> 11.025 | D4: ='SLC - Site Built'!$E4*(1-$B4) -> 4.725 | E4: =F4/F$29 -> 0.12250136 | F4: =SUM(C4:D4) -> 15.75 | G4: ='Parameter Adjustment'!I4 -> 1 | H4: =I4/$I$29 -> 0 | I4: ='NA - Site Built'!I4*(1-G4) -> 0 | J4: =I4*8 -> 0 | K4: =J4*_xlfn.XLOOKUP(A4,'Parameter Adjustment'!$A$38:$A$63,'Parameter Adjustment'!$C$38:$C$63) -> 0 | L4: Foundations | M4: ='Parameter Adjustment'!J4 -> 0 | N4: ='LA - Site Built'!$D4*(1-$M4) -> 23.52 | O4: ='LA - Site Built'!$E4*(1-$M4) -> 10.08 | P4: =Q4/Q$29 -> 0.19887246 | Q4: =SUM(N4:O4) -> 33.6 | R4: ='Parameter Adjustment'!I4 -> 1 | S4: =T4/T$29 -> 0 | T4: ='NA - Site Built'!I4*(1-R4) -> 0 | U4: =T4*8 -> 0 | V4: =U4*_xlfn.XLOOKUP(L4,'Parameter Adjustment'!$A$38:$A$63,'Parameter Adjustment'!$B$38:$B$63) -> 0 | W4: California
A5: Floor framing | B5: ='Parameter Adjustment'!J5 -> 0.2 | C5: ='SLC - Site Built'!$D5*(1-$B5) -> 1.494 | D5: ='SLC - Site Built'!$E5*(1-$B5) -> 0.996 | E5: =F5/F$29 -> 0.019366882 | F5: =SUM(C5:D5) -> 2.49 | G5: ='Parameter Adjustment'!I5 -> 0.2 | H5: =I5/$I$29 -> 0.034664191 | I5: ='NA - Site Built'!I5*(1-G5) -> 5.4486486 | J5: =I5*8 -> 43.589189 | K5: =J5*_xlfn.XLOOKUP(A5,'Parameter Adjustment'!$A$38:$A$63,'Parameter Adjustment'!$C$38:$C$63) -> 994.26941 | L5: Floor framing | M5: ='Parameter Adjustment'!J5 -> 0.2 | N5: ='SLC - Site Built'!$D5*(1-$M5) -> 1.494 | O5: ='SLC - Site Built'!$E5*(1-$M5) -> 0.996 | P5: =Q5/Q$29 -> 0.01473787 | Q5: =SUM(N5:O5) -> 2.49 | R5: ='Parameter Adjustment'!I5 -> 0.2 | S5: =T5/T$29 -> 0.032205502 | T5: ='NA - Site Built'!I5*(1-R5) -> 5.4486486 | U5: =T5*8 -> 43.589189 | V5: =U5*_xlfn.XLOOKUP(L5,'Parameter Adjustment'!$A$38:$A$63,'Parameter Adjustment'!$C$38:$C$63) -> 994.26941 | W5: Utah
A6: Floor sheathing | B6: ='Parameter Adjustment'!J6 -> 0.2 | C6: ='SLC - Site Built'!$D6*(1-$B6) -> 1.494 | D6: ='SLC - Site Built'!$E6*(1-$B6) -> 0.996 | E6: =F6/F$29 -> 0.019366882 | F6: =SUM(C6:D6) -> 2.49 | G6: ='Parameter Adjustment'!I6 -> 0.2 | H6: =I6/$I$29 -> 0.017332095 | I6: ='NA - Site Built'!I6*(1-G6) -> 2.7243243 | J6: =I6*8 -> 21.794595 | K6: =J6*_xlfn.XLOOKUP(A6,'Parameter Adjustment'!$A$38:$A$63,'Parameter Adjustment'!$C$38:$C$63) -> 497.1347 | L6: Floor sheathing | M6: ='Parameter Adjustment'!J6 -> 0.2 | N6: ='SLC - Site Built'!$D6*(1-$M6) -> 1.494 | O6: ='SLC - Site Built'!$E6*(1-$M6) -> 0.996 | P6: =Q6/Q$29 -> 0.01473787 | Q6: =SUM(N6:O6) -> 2.49 | R6: ='Parameter Adjustment'!I6 -> 0.2 | S6: =T6/T$29 -> 0.016102751 | T6: ='NA - Site Built'!I6*(1-R6) -> 2.7243243 | U6: =T6*8 -> 21.794595 | V6: =U6*_xlfn.XLOOKUP(L6,'Parameter Adjustment'!$A$38:$A$63,'Parameter Adjustment'!$C$38:$C$63) -> 497.1347 | W6: Utah
A7: Interior Wall framing | B7: ='Parameter Adjustment'!J7 -> 0.2 | C7: ='SLC - Site Built'!$D7*(1-$B7) -> 1.494 | D7: ='SLC - Site Built'!$E7*(1-$B7) -> 0.996 | E7: =F7/F$29 -> 0.019366882 | F7: =SUM(C7:D7) -> 2.49 | G7: ='Parameter Adjustment'!I7 -> 0.2 | H7: =I7/$I$29 -> 0.043330238 | I7: ='NA - Site Built'!I7*(1-G7) -> 6.8108108 | J7: =I7*8 -> 54.486486 | K7: =J7*_xlfn.XLOOKUP(A7,'Parameter Adjustment'!$A$38:$A$63,'Parameter Adjustment'!$C$38:$C$63) -> 1430.8151 | L7: Interior Wall framing | M7: ='Parameter Adjustment'!J7 -> 0.2 | N7: ='SLC - Site Built'!$D7*(1-$M7) -> 1.494 | O7: ='SLC - Site Built'!$E7*(1-$M7) -> 0.996 | P7: =Q7/Q$29 -> 0.01473787 | Q7: =SUM(N7:O7) -> 2.49 | R7: ='Parameter Adjustment'!I7 -> 0.2 | S7: =T7/T$29 -> 0.040256877 | T7: ='NA - Site Built'!I7*(1-R7) -> 6.8108108 | U7: =T7*8 -> 54.486486 | V7: =U7*_xlfn.XLOOKUP(L7,'Parameter Adjustment'!$A$38:$A$63,'Parameter Adjustment'!$C$38:$C$63) -> 1430.8151 | W7: Utah
A8: Interior Wall sheathing | B8: ='Parameter Adjustment'!J8 -> 0.2 | C8: ='SLC - Site Built'!$D8*(1-$B8) -> 1.494 | D8: ='SLC - Site Built'!$E8*(1-$B8) -> 0.996 | E8: =F8/F$29 -> 0.019366882 | F8: =SUM(C8:D8) -> 2.49 | G8: ='Parameter Adjustment'!I8 -> 0.2 | H8: =I8/$I$29 -> 0.017332095 | I8: ='NA - Site Built'!I8*(1-G8) -> 2.7243243 | J8: =I8*8 -> 21.794595 | K8: =J8*_xlfn.XLOOKUP(A8,'Parameter Adjustment'!$A$38:$A$63,'Parameter Adjustment'!$C$38:$C$63) -> 572.32605 | L8: Interior Wall sheathing | M8: ='Parameter Adjustment'!J8 -> 0.2 | N8: ='SLC - Site Built'!$D8*(1-$M8) -> 1.494 | O8: ='SLC - Site Built'!$E8*(1-$M8) -> 0.996 | P8: =Q8/Q$29 -> 0.01473787 | Q8: =SUM(N8:O8) -> 2.49 | R8: ='Parameter Adjustment'!I8 -> 0.2 | S8: =T8/T$29 -> 0.016102751 | T8: ='NA - Site Built'!I8*(1-R8) -> 2.7243243 | U8: =T8*8 -> 21.794595 | V8: =U8*_xlfn.XLOOKUP(L8,'Parameter Adjustment'!$A$38:$A$63,'Parameter Adjustment'!$C$38:$C$63) -> 572.32605 | W8: Utah
A9: Exterior Walls framing | B9: ='Parameter Adjustment'!J9 -> 0.2 | C9: ='SLC - Site Built'!$D9*(1-$B9) -> 1.494 | D9: ='SLC - Site Built'!$E9*(1-$B9) -> 0.996 | E9: =F9/F$29 -> 0.019366882 | F9: =SUM(C9:D9) -> 2.49 | G9: ='Parameter Adjustment'!I9 -> 0.2 | H9: =I9/$I$29 -> 0.098215207 | I9: ='NA - Site Built'!I9*(1-G9) -> 15.437838 | J9: =I9*8 -> 123.5027 | K9: =J9*_xlfn.XLOOKUP(A9,'Parameter Adjustment'!$A$38:$A$63,'Parameter Adjustment'!$C$38:$C$63) -> 3243.181 | L9: Exterior Walls framing | M9: ='Parameter Adjustment'!J9 -> 0.2 | N9: ='SLC - Site Built'!$D9*(1-$M9) -> 1.494 | O9: ='SLC - Site Built'!$E9*(1-$M9) -> 0.996 | P9: =Q9/Q$29 -> 0.01473787 | Q9: =SUM(N9:O9) -> 2.49 | R9: ='Parameter Adjustment'!I9 -> 0.2 | S9: =T9/T$29 -> 0.091248922 | T9: ='NA - Site Built'!I9*(1-R9) -> 15.437838 | U9: =T9*8 -> 123.5027 | V9: =U9*_xlfn.XLOOKUP(L9,'Parameter Adjustment'!$A$38:$A$63,'Parameter Adjustment'!$C$38:$C$63) -> 3243.181 | W9: Utah
A10: Exterior Wall sheathing | B10: ='Parameter Adjustment'!J10 -> 0.2 | C10: ='SLC - Site Built'!$D10*(1-$B10) -> 1.494 | D10: ='SLC - Site Built'!$E10*(1-$B10) -> 0.996 | E10: =F10/F$29 -> 0.019366882 | F10: =SUM(C10:D10) -> 2.49 | G10: ='Parameter Adjustment'!I10 -> 0.2 | H10: =I10/$I$29 -> 0.028886826 | I10: ='NA - Site Built'!I10*(1-G10) -> 4.5405405 | J10: =I10*8 -> 36.324324 | K10: =J10*_xlfn.XLOOKUP(A10,'Parameter Adjustment'!$A$38:$A$63,'Parameter Adjustment'!$C$38:$C$63) -> 953.87676 | L10: Exterior Wall sheathing | M10: ='Parameter Adjustment'!J10 -> 0.2 | N10: ='SLC - Site Built'!$D10*(1-$M10) -> 1.494 | O10: ='SLC - Site Built'!$E10*(1-$M10) -> 0.996 | P10: =Q10/Q$29 -> 0.01473787 | Q10: =SUM(N10:O10) -> 2.49 | R10: ='Parameter Adjustment'!I10 -> 0.2 | S10: =T10/T$29 -> 0.026837918 | T10: ='NA - Site Built'!I10*(1-R10) -> 4.5405405 | U10: =T10*8 -> 36.324324 | V10: =U10*_xlfn.XLOOKUP(L10,'Parameter Adjustment'!$A$38:$A$63,'Parameter Adjustment'!$C$38:$C$63) -> 953.87676 | W10: Utah
A11: Roof framing | B11: ='Parameter Adjustment'!J11 -> 0.2 | C11: ='SLC - Site Built'!$D11*(1-$B11) -> 1.494 | D11: ='SLC - Site Built'!$E11*(1-$B11) -> 0.996 | E11: =F11/F$29 -> 0.019366882 | F11: =SUM(C11:D11) -> 2.49 | G11: ='Parameter Adjustment'!I11 -> 0.2 | H11: =I11/$I$29 -> 0.034664191 | I11: ='NA - Site Built'!I11*(1-G11) -> 5.4486486 | J11: =I11*8 -> 43.589189 | K11: =J11*_xlfn.XLOOKUP(A11,'Parameter Adjustment'!$A$38:$A$63,'Parameter Adjustment'!$C$38:$C$63) -> 1105.4218 | L11: Roof framing | M11: ='Parameter Adjustment'!J11 -> 0.2 | N11: ='SLC - Site Built'!$D11*(1-$M11) -> 1.494 | O11: ='SLC - Site Built'!$E11*(1-$M11) -> 0.996 | P11: =Q11/Q$29 -> 0.01473787 | Q11: =SUM(N11:O11) -> 2.49 | R11: ='Parameter Adjustment'!I11 -> 0.2 | S11: =T11/T$29 -> 0.032205502 | T11: ='NA - Site Built'!I11*(1-R11) -> 5.4486486 | U11: =T11*8 -> 43.589189 | V11: =U11*_xlfn.XLOOKUP(L11,'Parameter Adjustment'!$A$38:$A$63,'Parameter Adjustment'!$C$38:$C$63) -> 1105.4218 | W11: Utah
A12: Roof sheathing and waterproofing | B12: ='Parameter Adjustment'!J12 -> 0.2 | C12: ='SLC - Site Built'!$D12*(1-$B12) -> 1.494 | D12: ='SLC - Site Built'!$E12*(1-$B12) -> 0.996 | E12: =F12/F$29 -> 0.019366882 | F12: =SUM(C12:D12) -> 2.49 | G12: ='Parameter Adjustment'!I12 -> 0.2 | H12: =I12/$I$29 -> 0.028886826 | I12: ='NA - Site Built'!I12*(1-G12) -> 4.5405405 | J12: =I12*8 -> 36.324324 | K12: =J12*_xlfn.XLOOKUP(A12,'Parameter Adjustment'!$A$38:$A$63,'Parameter Adjustment'!$C$38:$C$63) -> 921.18486 | L12: Roof sheathing and waterproofing | M12: ='Parameter Adjustment'!J12 -> 0.2 | N12: ='SLC - Site Built'!$D12*(1-$M12) -> 1.494 | O12: ='SLC - Site Built'!$E12*(1-$M12) -> 0.996 | P12: =Q12/Q$29 -> 0.01473787 | Q12: =SUM(N12:O12) -> 2.49 | R12: ='Parameter Adjustment'!I12 -> 0.2 | S12: =T12/T$29 -> 0.026837918 | T12: ='NA - Site Built'!I12*(1-R12) -> 4.5405405 | U12: =T12*8 -> 36.324324 | V12: =U12*_xlfn.XLOOKUP(L12,'Parameter Adjustment'!$A$38:$A$63,'Parameter Adjustment'!$C$38:$C$63) -> 921.18486 | W12: Utah
A13: Mechanical Rough In | B13: ='Parameter Adjustment'!J13 -> 0.2 | C13: ='SLC - Site Built'!$D13*(1-$B13) -> 2.268 | D13: ='SLC - Site Built'!$E13*(1-$B13) -> 5.292 | E13: =F13/F$29 -> 0.058800653 | F13: =SUM(C13:D13) -> 7.56 | G13: ='Parameter Adjustment'!I13 -> 0.2 | H13: =I13/$I$29 -> 0.049107603 | I13: ='NA - Site Built'!I13*(1-G13) -> 7.7189189 | J13: =I13*8 -> 61.751351 | K13: =J13*_xlfn.XLOOKUP(A13,'Parameter Adjustment'!$A$38:$A$63,'Parameter Adjustment'!$C$38:$C$63) -> 1759.9135 | L13: Mechanical Rough In | M13: ='Parameter Adjustment'!J13 -> 0.2 | N13: ='SLC - Site Built'!$D13*(1-$M13) -> 2.268 | O13: ='SLC - Site Built'!$E13*(1-$M13) -> 5.292 | P13: =Q13/Q$29 -> 0.044746304 | Q13: =SUM(N13:O13) -> 7.56 | R13: ='Parameter Adjustment'!I13 -> 0.2 | S13: =T13/T$29 -> 0.045624461 | T13: ='NA - Site Built'!I13*(1-R13) -> 7.7189189 | U13: =T13*8 -> 61.751351 | V13: =U13*_xlfn.XLOOKUP(L13,'Parameter Adjustment'!$A$38:$A$63,'Parameter Adjustment'!$C$38:$C$63) -> 1759.9135 | W13: Utah
A14: Electrical Rough In | B14: ='Parameter Adjustment'!J14 -> 0.2 | C14: ='SLC - Site Built'!$D14*(1-$B14) -> 2.304 | D14: ='SLC - Site Built'!$E14*(1-$B14) -> 5.376 | E14: =F14/F$29 -> 0.059733997 | F14: =SUM(C14:D14) -> 7.68 | G14: ='Parameter Adjustment'!I14 -> 0.2 | H14: =I14/$I$29 -> 0.031775508 | I14: ='NA - Site Built'!I14*(1-G14) -> 4.9945946 | J14: =I14*8 -> 39.956757 | K14: =J14*_xlfn.XLOOKUP(A14,'Parameter Adjustment'!$A$38:$A$63,'Parameter Adjustment'!$C$38:$C$63) -> 1210.6897 | L14: Electrical Rough In | M14: ='Parameter Adjustment'!J14 -> 0.2 | N14: ='SLC - Site Built'!$D14*(1-$M14) -> 2.304 | O14: ='SLC - Site Built'!$E14*(1-$M14) -> 5.376 | P14: =Q14/Q$29 -> 0.045456563 | Q14: =SUM(N14:O14) -> 7.68 | R14: ='Parameter Adjustment'!I14 -> 0.2 | S14: =T14/T$29 -> 0.02952171 | T14: ='NA - Site Built'!I14*(1-R14) -> 4.9945946 | U14: =T14*8 -> 39.956757 | V14: =U14*_xlfn.XLOOKUP(L14,'Parameter Adjustment'!$A$38:$A$63,'Parameter Adjustment'!$C$38:$C$63) -> 1210.6897 | W14: Utah
A15: Plumbing Rough In | B15: ='Parameter Adjustment'!J15 -> 0.2 | C15: ='SLC - Site Built'!$D15*(1-$B15) -> 2.268 | D15: ='SLC - Site Built'!$E15*(1-$B15) -> 5.292 | E15: =F15/F$29 -> 0.058800653 | F15: =SUM(C15:D15) -> 7.56 | G15: ='Parameter Adjustment'!I15 -> 0.2 | H15: =I15/$I$29 -> 0.046218921 | I15: ='NA - Site Built'!I15*(1-G15) -> 7.2648649 | J15: =I15*8 -> 58.118919 | K15: =J15*_xlfn.XLOOKUP(A15,'Parameter Adjustment'!$A$38:$A$63,'Parameter Adjustment'!$C$38:$C$63) -> 1749.3795 | L15: Plumbing Rough In | M15: ='Parameter Adjustment'!J15 -> 0.2 | N15: ='SLC - Site Built'!$D15*(1-$M15) -> 2.268 | O15: ='SLC - Site Built'!$E15*(1-$M15) -> 5.292 | P15: =Q15/Q$29 -> 0.044746304 | Q15: =SUM(N15:O15) -> 7.56 | R15: ='Parameter Adjustment'!I15 -> 0.2 | S15: =T15/T$29 -> 0.042940669 | T15: ='NA - Site Built'!I15*(1-R15) -> 7.2648649 | U15: =T15*8 -> 58.118919 | V15: =U15*_xlfn.XLOOKUP(L15,'Parameter Adjustment'!$A$38:$A$63,'Parameter Adjustment'!$C$38:$C$63) -> 1749.3795 | W15: Utah
A16: Insulation | B16: ='Parameter Adjustment'!J16 -> 0.2 | C16: ='SLC - Site Built'!$D16*(1-$B16) -> 1.152 | D16: ='SLC - Site Built'!$E16*(1-$B16) -> 0.768 | E16: =F16/F$29 -> 0.014933499 | F16: =SUM(C16:D16) -> 1.92 | G16: ='Parameter Adjustment'!I16 -> 0.2 | H16: =I16/$I$29 -> 0.034664191 | I16: ='NA - Site Built'!I16*(1-G16) -> 5.4486486 | J16: =I16*8 -> 43.589189 | K16: =J16*_xlfn.XLOOKUP(A16,'Parameter Adjustment'!$A$38:$A$63,'Parameter Adjustment'!$C$38:$C$63) -> 979.88497 | L16: Insulation | M16: ='Parameter Adjustment'!J16 -> 0.2 | N16: ='SLC - Site Built'!$D16*(1-$M16) -> 1.152 | O16: ='SLC - Site Built'!$E16*(1-$M16) -> 0.768 | P16: =Q16/Q$29 -> 0.011364141 | Q16: =SUM(N16:O16) -> 1.92 | R16: ='Parameter Adjustment'!I16 -> 0.2 | S16: =T16/T$29 -> 0.032205502 | T16: ='NA - Site Built'!I16*(1-R16) -> 5.4486486 | U16: =T16*8 -> 43.589189 | V16: =U16*_xlfn.XLOOKUP(L16,'Parameter Adjustment'!$A$38:$A$63,'Parameter Adjustment'!$C$38:$C$63) -> 979.88497 | W16: Utah
... A25: Exterior Roof Finishing | B25: ='Parameter Adjustment'!J25 -> 0.2 | C25: ='SLC - Site Built'!$D25*(1-$B25) -> 2.808 | D25: ='SLC - Site Built'!$E25*(1-$B25) -> 1.872 | E25: =F25/F$29 -> 0.036400404 | F25: =SUM(C25:D25) -> 4.68 | G25: ='Parameter Adjustment'!I25 -> 0.2 | H25: =I25/$I$29 -> 0.028886826 | I25: ='NA - Site Built'!I25*(1-G25) -> 4.5405405 | J25: =I25*8 -> 36.324324 | K25: =J25*_xlfn.XLOOKUP(A25,'Parameter Adjustment'!$A$38:$A$63,'Parameter Adjustment'!$C$38:$C$63) -> 921.18486 | L25: Exterior Roof Finishing | M25: ='Parameter Adjustment'!J25 -> 0.2 | N25: ='SLC - Site Built'!$D25*(1-$M25) -> 2.808 | O25: ='SLC - Site Built'!$E25*(1-$M25) -> 1.872 | P25: =Q25/Q$29 -> 0.027700093 | Q25: =SUM(N25:O25) -> 4.68 | R25: ='Parameter Adjustment'!I25 -> 0.2 | S25: =T25/T$29 -> 0.026837918 | T25: ='NA - Site Built'!I25*(1-R25) -> 4.5405405 | U25: =T25*8 -> 36.324324 | V25: =U25*_xlfn.XLOOKUP(L25,'Parameter Adjustment'!$A$38:$A$63,'Parameter Adjustment'!$C$38:$C$63) -> 921.18486 | W25: Utah
A26: Transportation | B26: ='Parameter Adjustment'!J26 -> 0 | C26: ='SLC - Site Built'!$D26*(1-$B26) -> 0 | D26: ='Parameter Adjustment'!S3*'Parameter Adjustment'!T3/IF('Parameter Adjustment'!Z2="1,000 square-foot home",1,1000) -> 0.7 | E26: =F26/F$29 -> 0.0054445049 | F26: =SUM(C26:D26) -> 0.7 | G26: ='Parameter Adjustment'!I26 -> 0 | H26: =I26/$I$29 -> 0.019085938 | I26: 3 | J26: =I26*8 -> 24 | K26: =F26 -> 0.7 | L26: Transportation | M26: ='Parameter Adjustment'!J26 -> 0 | N26: ='SLC - Site Built'!$D26*(1-$M26) -> 0 | O26: ='Parameter Adjustment'!S5*'Parameter Adjustment'!T5/IF('Parameter Adjustment'!Z2="1,000 square-foot home",1,1000) -> 10.3125 | P26: =Q26/Q$29 -> 0.061037866 | Q26: =SUM(N26:O26) -> 10.3125 | R26: ='Parameter Adjustment'!I26 -> 0 | S26: =T26/T$29 -> 0.08866098 | T26: 15 | U26: =T26*8 -> 120 | V26: =Q26 -> 10.3125 | W26: Utah - California
A27: On-site Installation | B27: ='Parameter Adjustment'!J27 -> 0 | C27: ='SLC - Site Built'!$D27*(1-$B27) -> 0 | D27: ='Parameter Adjustment'!X2*'Parameter Adjustment'!X3/IF('Parameter Adjustment'!Z2="1,000 square-foot home",1,1000) -> 10 | E27: =F27/F$29 -> 0.077778642 | F27: =SUM(C27:D27) -> 10 | G27: ='Parameter Adjustment'!I27 -> 0 | H27: =I27/$I$29 -> 0.19085938 | I27: 30 | J27: =I27*8 -> 240 | K27: =J27*_xlfn.XLOOKUP("Assembly",'Parameter Adjustment'!$A$38:$A$63,'Parameter Adjustment'!$C$38:$C$63) -> 5510.4 | L27: On-site Installation | M27: ='Parameter Adjustment'!J27 -> 0 | N27: ='SLC - Site Built'!$D27*(1-$M27) -> 0 | O27: ='Parameter Adjustment'!X2*'Parameter Adjustment'!X3/IF('Parameter Adjustment'!Z2="1,000 square-foot home",1,1000) -> 10 | P27: =Q27/Q$29 -> 0.059188233 | Q27: =SUM(N27:O27) -> 10 | R27: ='Parameter Adjustment'!I27 -> 0 | S27: =T27/T$29 -> 0.17732196 | T27: 30 | U27: =T27*8 -> 240 | V27: =U27*_xlfn.XLOOKUP("Assembly",'Parameter Adjustment'!$A$38:$A$63,'Parameter Adjustment'!$B$38:$B$63) -> 7632 | W27: California
A28: All Inspections | B28: ='Parameter Adjustment'!J28 -> 0.8 | C28: ='SLC - Site Built'!$D28*(1-$B28) -> 0 | D28: ='SLC - Site Built'!$E28*(1-$B28) -> 2.52 | E28: =F28/F$29 -> 0.019600218 | F28: =SUM(C28:D28) -> 2.52 | G28: ='Parameter Adjustment'!I28 -> 0.8 | H28: =I28/$I$29 -> 0.015887754 | I28: ='NA - Site Built'!I28*(1-G28) -> 2.4972973 | J28: =I28*8 -> 19.978378 | K28: =J28*_xlfn.XLOOKUP(A28,'Parameter Adjustment'!$A$38:$A$63,'Parameter Adjustment'!$C$38:$C$63) -> 685.65795 | L28: All Inspections | M28: ='Parameter Adjustment'!J28 -> 0.8 | N28: ='SLC - Site Built'!$D28*(1-$M28) -> 0 | O28: ='SLC - Site Built'!$E28*(1-$M28) -> 2.52 | P28: =Q28/Q$29 -> 0.014915435 | Q28: =SUM(N28:O28) -> 2.52 | R28: ='Parameter Adjustment'!I28 -> 0.8 | S28: =T28/T$29 -> 0.014760855 | T28: ='NA - Site Built'!I28*(1-R28) -> 2.4972973 | U28: =T28*8 -> 19.978378 | V28: =U28*AVERAGE((_xlfn.XLOOKUP(L28,'Parameter Adjustment'!$A$38:$A$63,'Parameter Adjustment'!$B$38:$B$63),(_xlfn.XLOOKUP(L28,'Parameter Adjustment'!$A$38:$A$63,'Parameter Adjustment'!$C$38:$C$63)))) -> 839.89103 | W28: Average Utah and California
A29: =_xlfn.CONCAT("Total Construction Costs (",'Parameter Adjustment'!$Z$2,")") -> Total Construction Costs (Square foot) | C29: =SUM(C3:C28) -> 60.309 | D29: =SUM(D3:D28) -> 68.261 | E29: =SUM(E3:E28) -> 1 | F29: =SUM(F3:F28) -> 128.57 | H29: =SUM(H3:H28) -> 1 | I29: =SUM(I3:I28) -> 157.18378 | J29: =SUM(J3:J28) -> 1257.4703 | K29: =SUM(K3:K28) -> 32293.533 | L29: =_xlfn.CONCAT("Total Construction Costs (",'Parameter Adjustment'!$Z$2,")") -> Total Construction Costs (Square foot) | N29: =SUM(N3:N28) -> 80.556 | O29: =SUM(O3:O28) -> 88.3965 | P29: =SUM(P3:P28) -> 1 | Q29: =SUM(Q3:Q28) -> 168.9525 | S29: =SUM(S3:S28) -> 1 | T29: =SUM(T3:T28) -> 169.18378 | U29: =SUM(U3:U28) -> 1353.4703 | V29: =SUM(V3:V28) -> 34578.978
A33: Profit Calculation | B33: SLC Value | C33: LA Value
A34: Total Construction Costs | B34: =F29 -> 128.57 | C34: =Q29 -> 168.9525
A35: Other Costs | B35: ='Profit Calculation'!B11*'Profit Calculation'!F10*IF('Parameter Adjustment'!Z2="1,000 square-foot home",1000,1) -> 57.763623 | C35: ='Profit Calculation'!B11*'Profit Calculation'!E10*IF('Parameter Adjustment'!Z2="1,000 square-foot home",1000,1) -> 123.22906
A36: Fixed Costs | B36: =IF('Parameter Adjustment'!$Z$2="Square foot",'Parameter Adjustment'!AJ5,'Parameter Adjustment'!AJ5*1000) -> 19.152 | C36: =IF('Parameter Adjustment'!$Z$2="Square foot",'Parameter Adjustment'!AJ5,'Parameter Adjustment'!AJ5*1000) -> 19.152
A37: Profit | B37: =B38-B34-B35-B36 -> 27.961945 | C37: =C38-C34-C35-C36 -> 186.68792
A38: Total Selling Price | B38: ='SLC - Site Built'!B37 -> 233.44757 | C38: =+'LA - Site Built'!B37 -> 498.02148
A39: Profit Margin | B39: =B37/B38 -> 0.11977827 | C39: =C37/C38 -> 0.37485917
A41: SLC
A42: Cost Type | B42: % of Total Costs | C42: Profit | D42: Profit Margin
A43: Total Construction Costs | B43: =B34/SUM(B$34:B$36) -> 0.62568854 | C43: =B43*$B$37 -> 17.495469 | D43: =C43/$B$37 -> 0.62568854
A44: Other Costs | B44: =B35/SUM(B$34:B$36) -> 0.28110786 | C44: =B44*$B$37 -> 7.8603226 | D44: =C44/$B$37 -> 0.28110786
A45: Fixed Costs | B45: =B36/SUM(B$34:B$36) -> 0.093203601 | C45: =B45*$B$37 -> 2.606154 | D45: =C45/$B$37 -> 0.093203601
A46: Total | B46: =SUM(B43:B45) -> 1 | C46: =SUM(C43:C45) -> 27.961945 | D46: =SUM(D43:D45) -> 1
A48: LA
A49: Cost Type | B49: % of Total Costs | C49: Profit | D49: Profit Margin
A50: Total Construction Costs | B50: =C34/SUM(C$34:C$36) -> 0.54267358 | C50: =B50*$C$37 -> 101.3106 | D50: =C50/$C$37 -> 0.54267358
A51: Other Costs | B51: =C35/SUM(C$34:C$36) -> 0.3958104 | C51: =B51*$C$37 -> 73.89302 | D51: =C51/$C$37 -> 0.3958104
A52: Fixed Costs | B52: =C36/SUM(C$34:C$36) -> 0.061516015 | C52: =B52*$C$37 -> 11.484297 | D52: =C52/$C$37 -> 0.061516015
A53: Total | B53: =SUM(B50:B52) -> 1 | C53: =SUM(C50:C52) -> 186.68792 | D53: =SUM(D50:D52) -> 1

Sheet Multi-Market Hybrid 1
C1: SLC Modular | M1: LA Hybrid | Z1: Assumptions:
A2: Construction Process | B2: Location | C2: % Cost Savings | D2: Material Cost | E2: Labor Cost | F2: % of Total Cost | G2: Total Cost | H2: % Time Savings | I2: % of Total Time | J2: Total Time (days) | K2: Total Time per Employee (working hours) | L2: Total Labor Cost per Employee | M2: Construction Process | N2: % Cost Savings | O2: Material Cost | P2: Labor Cost | Q2: % of Total Cost | R2: Total Cost | S2: % Time Savings | T2: % of Total Time | U2: Total Time (days) | V2: Total Time per Employee (working hours) | W2: Total Labor Cost per Employee | X2: Comments | Z2: Materials same for both markets (no change in quality, etc.)
A3: Site Work | B3: Onsite | C3: {=_xlfn.IFS($B3="Onsite",0%,$B3="Hybrid",'Parameter Adjustment'!J3,$B3="Local",'Parameter Adjustment'!H3,$B3="Hybrid/Local",AVERAGE('Parameter Adjustment'!H3,'Parameter Adjustment'!J3))} -> 0 | D3: ='SLC - Site Built'!$D3*(1-$C3) -> 6.84 | E3: ='SLC - Site Built'!$E3*(1-$C3) -> 4.56 | F3: =G3/G$29 -> 0.086993018 | G3: =SUM(D3:E3) -> 11.4 | H3: {=_xlfn.IFS($B3="Onsite", IF('Parameter Adjustment'!$I3='Parameter Adjustment'!$K3,'Parameter Adjustment'!$I3,"Onsite % Savings Don't Match"),$B3="Hybrid",'Parameter Adjustment'!$K3,$B3="Local",'Parameter Adjustment'!$I3,$B3="Hybrid/Local",'Parameter Adjustment'!$K3)} -> 1 | I3: =J3/$J$29 -> 0 | J3: ='NA - Site Built'!I3*(1-H3) -> 0 | K3: =J3*8 -> 0 | L3: =K3*_xlfn.XLOOKUP(A3,'Parameter Adjustment'!$A$38:$A$63,'Parameter Adjustment'!$C$38:$C$63) -> 0 | M3: Site Work | N3: {=_xlfn.IFS($B3="Onsite",0%,$B3="Hybrid",'Parameter Adjustment'!J3,$B3="Local",'Parameter Adjustment'!F3,$B3="Hybrid/Local",AVERAGE('Parameter Adjustment'!H3,'Parameter Adjustment'!J3))} -> 0 | O3: {=_xlfn.IFS(B3="Onsite",'LA - Site Built'!$D3*(1-$N3),B3="Hybrid",'SLC - Site Built'!$D3*(1-$N3),B3="Local",'LA - Site Built'!$D3*(1-$N3),B3="Hybrid/Local",AVERAGE('SLC - Site Built'!$D3,'LA - Site Built'!$D3)*(1-$N3))} -> 14.592 | P3: {=_xlfn.IFS(B3="Onsite",'LA - Site Built'!$E3*(1-$N3),B3="Hybrid",'SLC - Site Built'!$E3*(1-$N3),B3="Local",'LA - Site Built'!$E3*(1-$N3),B3="Hybrid/Local",AVERAGE('SLC - Site Built'!$E3,'LA - Site Built'!$E3)*(1-$N3))} -> 9.728 | Q3: =R3/R$29 -> 0.11089427 | R3: =SUM(O3:P3) -> 24.32 | S3: {=_xlfn.IFS($B3="Onsite", IF('Parameter Adjustment'!$I3='Parameter Adjustment'!$K3,'Parameter Adjustment'!$I3,"Onsite % Savings Don't Match"),$B3="Hybrid",'Parameter Adjustment'!$K3,$B3="Local",'Parameter Adjustment'!$I3,$B3="Hybrid/Local",'Parameter Adjustment'!$K3)} -> 1 | T3: =U3/U$29 -> 0 | U3: ='NA - Site Built'!I3*(1-S3) -> 0 | V3: =U3*8 -> 0 | W3: =V3*_xlfn.XLOOKUP(M3,'Parameter Adjustment'!$A$38:$A$63,'Parameter Adjustment'!$B$38:$B$63) -> 0 | X3: {=_xlfn.IFS(B3="Onsite","California",B3="Hybrid","Utah",B3="Local","California",B3="Hybrid/Local","Utah - California")} -> California | Z3: Same on-site installation costs
A4: Foundations | B4: Onsite | C4: {=_xlfn.IFS($B4="Onsite",0%,$B4="Hybrid",'Parameter Adjustment'!J4,$B4="Local",'Parameter Adjustment'!H4,$B4="Hybrid/Local",AVERAGE('Parameter Adjustment'!H4,'Parameter Adjustment'!J4))} -> 0 | D4: ='SLC - Site Built'!$D4*(1-$C4) -> 11.025 | E4: ='SLC - Site Built'!$E4*(1-$C4) -> 4.725 | F4: =G4/G$29 -> 0.12018772 | G4: =SUM(D4:E4) -> 15.75 | H4: {=_xlfn.IFS($B4="Onsite", IF('Parameter Adjustment'!$I4='Parameter Adjustment'!$K4,'Parameter Adjustment'!$I4,"Onsite % Savings Don't Match"),$B4="Hybrid",'Parameter Adjustment'!$K4,$B4="Local",'Parameter Adjustment'!$I4,$B4="Hybrid/Local",'Parameter Adjustment'!$K4)} -> 1 | I4: =J4/$J$29 -> 0 | J4: ='NA - Site Built'!I4*(1-H4) -> 0 | K4: =J4*8 -> 0 | L4: =K4*_xlfn.XLOOKUP(A4,'Parameter Adjustment'!$A$38:$A$63,'Parameter Adjustment'!$C$38:$C$63) -> 0 | M4: Foundations | N4: {=_xlfn.IFS($B4="Onsite",0%,$B4="Hybrid",'Parameter Adjustment'!J4,$B4="Local",'Parameter Adjustment'!F4,$B4="Hybrid/Local",AVERAGE('Parameter Adjustment'!H4,'Parameter Adjustment'!J4))} -> 0 | O4: {=_xlfn.IFS(B4="Onsite",'LA - Site Built'!$D4*(1-$N4),B4="Hybrid",'SLC - Site Built'!$D4*(1-$N4),B4="Local",'LA - Site Built'!$D4*(1-$N4),B4="Hybrid/Local",AVERAGE('SLC - Site Built'!$D4,'LA - Site Built'!$D4)*(1-$N4))} -> 23.52 | P4: {=_xlfn.IFS(B4="Onsite",'LA - Site Built'!$E4*(1-$N4),B4="Hybrid",'SLC - Site Built'!$E4*(1-$N4),B4="Local",'LA - Site Built'!$E4*(1-$N4),B4="Hybrid/Local",AVERAGE('SLC - Site Built'!$E4,'LA - Site Built'!$E4)*(1-$N4))} -> 10.08 | Q4: =R4/R$29 -> 0.15320919 | R4: =SUM(O4:P4) -> 33.6 | S4: {=_xlfn.IFS($B4="Onsite", IF('Parameter Adjustment'!$I4='Parameter Adjustment'!$K4,'Parameter Adjustment'!$I4,"Onsite % Savings Don't Match"),$B4="Hybrid",'Parameter Adjustment'!$K4,$B4="Local",'Parameter Adjustment'!$I4,$B4="Hybrid/Local",'Parameter Adjustment'!$K4)} -> 1 | T4: =U4/U$29 -> 0 | U4: ='NA - Site Built'!I4*(1-S4) -> 0 | V4: =U4*8 -> 0 | W4: =V4*_xlfn.XLOOKUP(M4,'Parameter Adjustment'!$A$38:$A$63,'Parameter Adjustment'!$B$38:$B$63) -> 0 | X4: {=_xlfn.IFS(B4="Onsite","California",B4="Hybrid","Utah",B4="Local","California",B4="Hybrid/Local","Utah - California")} -> California
A5: Floor framing | B5: Hybrid | C5: {=_xlfn.IFS($B5="Onsite",0%,$B5="Hybrid",'Parameter Adjustment'!J5,$B5="Local",'Parameter Adjustment'!H5,$B5="Hybrid/Local",AVERAGE('Parameter Adjustment'!H5,'Parameter Adjustment'!J5))} -> 0.2 | D5: ='SLC - Site Built'!$D5*(1-$C5) -> 1.494 | E5: ='SLC - Site Built'!$E5*(1-$C5) -> 0.996 | F5: =G5/G$29 -> 0.019001106 | G5: =SUM(D5:E5) -> 2.49 | H5: {=_xlfn.IFS($B5="Onsite", IF('Parameter Adjustment'!$I5='Parameter Adjustment'!$K5,'Parameter Adjustment'!$I5,"Onsite % Savings Don't Match"),$B5="Hybrid",'Parameter Adjustment'!$K5,$B5="Local",'Parameter Adjustment'!$I5,$B5="Hybrid/Local",'Parameter Adjustment'!$K5)} -> 0.2 | I5: =J5/$J$29 -> 0.034664191 | J5: ='NA - Site Built'!I5*(1-H5) -> 5.4486486 | K5: =J5*8 -> 43.589189 | L5: =K5*_xlfn.XLOOKUP(A5,'Parameter Adjustment'!$A$38:$A$63,'Parameter Adjustment'!$C$38:$C$63) -> 994.26941 | M5: Floor framing | N5: {=_xlfn.IFS($B5="Onsite",0%,$B5="Hybrid",'Parameter Adjustment'!J5,$B5="Local",'Parameter Adjustment'!F5,$B5="Hybrid/Local",AVERAGE('Parameter Adjustment'!H5,'Parameter Adjustment'!J5))} -> 0.2 | O5: {=_xlfn.IFS(B5="Onsite",'LA - Site Built'!$D5*(1-$N5),B5="Hybrid",'SLC - Site Built'!$D5*(1-$N5),B5="Local",'LA - Site Built'!$D5*(1-$N5),B5="Hybrid/Local",AVERAGE('SLC - Site Built'!$D5,'LA - Site Built'!$D5)*(1-$N5))} -> 1.494 | P5: {=_xlfn.IFS(B5="Onsite",'LA - Site Built'!$E5*(1-$N5),B5="Hybrid",'SLC - Site Built'!$E5*(1-$N5),B5="Local",'LA - Site Built'!$E5*(1-$N5),B5="Hybrid/Local",AVERAGE('SLC - Site Built'!$E5,'LA - Site Built'!$E5)*(1-$N5))} -> 0.996 | Q5: =R5/R$29 -> 0.011353895 | R5: =SUM(O5:P5) -> 2.49 | S5: {=_xlfn.IFS($B5="Onsite", IF('Parameter Adjustment'!$I5='Parameter Adjustment'!$K5,'Parameter Adjustment'!$I5,"Onsite % Savings Don't Match"),$B5="Hybrid",'Parameter Adjustment'!$K5,$B5="Local",'Parameter Adjustment'!$I5,$B5="Hybrid/Local",'Parameter Adjustment'!$K5)} -> 0.2 | T5: =U5/U$29 -> 0.032205502 | U5: ='NA - Site Built'!I5*(1-S5) -> 5.4486486 | V5: =U5*8 -> 43.589189 | W5: =V5*_xlfn.XLOOKUP(M5,'Parameter Adjustment'!$A$38:$A$63,'Parameter Adjustment'!$C$38:$C$63) -> 994.26941 | X5: {=_xlfn.IFS(B5="Onsite","California",B5="Hybrid","Utah",B5="Local","California",B5="Hybrid/Local","Utah - California")} -> Utah
A6: Floor sheathing | B6: Hybrid | C6: {=_xlfn.IFS($B6="Onsite",0%,$B6="Hybrid",'Parameter Adjustment'!J6,$B6="Local",'Parameter Adjustment'!H6,$B6="Hybrid/Local",AVERAGE('Parameter Adjustment'!H6,'Parameter Adjustment'!J6))} -> 0.2 | D6: ='SLC - Site Built'!$D6*(1-$C6) -> 1.494 | E6: ='SLC - Site Built'!$E6*(1-$C6) -> 0.996 | F6: =G6/G$29 -> 0.019001106 | G6: =SUM(D6:E6) -> 2.49 | H6: {=_xlfn.IFS($B6="Onsite", IF('Parameter Adjustment'!$I6='Parameter Adjustment'!$K6,'Parameter Adjustment'!$I6,"Onsite % Savings Don't Match"),$B6="Hybrid",'Parameter Adjustment'!$K6,$B6="Local",'Parameter Adjustment'!$I6,$B6="Hybrid/Local",'Parameter Adjustment'!$K6)} -> 0.2 | I6: =J6/$J$29 -> 0.017332095 | J6: ='NA - Site Built'!I6*(1-H6) -> 2.7243243 | K6: =J6*8 -> 21.794595 | L6: =K6*_xlfn.XLOOKUP(A6,'Parameter Adjustment'!$A$38:$A$63,'Parameter Adjustment'!$C$38:$C$63) -> 497.1347 | M6: Floor sheathing | N6: {=_xlfn.IFS($B6="Onsite",0%,$B6="Hybrid",'Parameter Adjustment'!J6,$B6="Local",'Parameter Adjustment'!F6,$B6="Hybrid/Local",AVERAGE('Parameter Adjustment'!H6,'Parameter Adjustment'!J6))} -> 0.2 | O6: {=_xlfn.IFS(B6="Onsite",'LA - Site Built'!$D6*(1-$N6),B6="Hybrid",'SLC - Site Built'!$D6*(1-$N6),B6="Local",'LA - Site Built'!$D6*(1-$N6),B6="Hybrid/Local",AVERAGE('SLC - Site Built'!$D6,'LA - Site Built'!$D6)*(1-$N6))} -> 1.494 | P6: {=_xlfn.IFS(B6="Onsite",'LA - Site Built'!$E6*(1-$N6),B6="Hybrid",'SLC - Site Built'!$E6*(1-$N6),B6="Local",'LA - Site Built'!$E6*(1-$N6),B6="Hybrid/Local",AVERAGE('SLC - Site Built'!$E6,'LA - Site Built'!$E6)*(1-$N6))} -> 0.996 | Q6: =R6/R$29 -> 0.011353895 | R6: =SUM(O6:P6) -> 2.49 | S6: {=_xlfn.IFS($B6="Onsite", IF('Parameter Adjustment'!$I6='Parameter Adjustment'!$K6,'Parameter Adjustment'!$I6,"Onsite % Savings Don't Match"),$B6="Hybrid",'Parameter Adjustment'!$K6,$B6="Local",'Parameter Adjustment'!$I6,$B6="Hybrid/Local",'Parameter Adjustment'!$K6)} -> 0.2 | T6: =U6/U$29 -> 0.016102751 | U6: ='NA - Site Built'!I6*(1-S6) -> 2.7243243 | V6: =U6*8 -> 21.794595 | W6: =V6*_xlfn.XLOOKUP(M6,'Parameter Adjustment'!$A$38:$A$63,'Parameter Adjustment'!$C$38:$C$63) -> 497.1347 | X6: {=_xlfn.IFS(B6="Onsite","California",B6="Hybrid","Utah",B6="Local","California",B6="Hybrid/Local","Utah - California")} -> Utah
A7: Interior Wall framing | B7: Hybrid | C7: {=_xlfn.IFS($B7="Onsite",0%,$B7="Hybrid",'Parameter Adjustment'!J7,$B7="Local",'Parameter Adjustment'!H7,$B7="Hybrid/Local",AVERAGE('Parameter Adjustment'!H7,'Parameter Adjustment'!J7))} -> 0.2 | D7: ='SLC - Site Built'!$D7*(1-$C7) -> 1.494 | E7: ='SLC - Site Built'!$E7*(1-$C7) -> 0.996 | F7: =G7/G$29 -> 0.019001106 | G7: =SUM(D7:E7) -> 2.49 | H7: {=_xlfn.IFS($B7="Onsite", IF('Parameter Adjustment'!$I7='Parameter Adjustment'!$K7,'Parameter Adjustment'!$I7,"Onsite % Savings Don't Match"),$B7="Hybrid",'Parameter Adjustment'!$K7,$B7="Local",'Parameter Adjustment'!$I7,$B7="Hybrid/Local",'Parameter Adjustment'!$K7)} -> 0.2 | I7: =J7/$J$29 -> 0.043330238 | J7: ='NA - Site Built'!I7*(1-H7) -> 6.8108108 | K7: =J7*8 -> 54.486486 | L7: =K7*_xlfn.XLOOKUP(A7,'Parameter Adjustment'!$A$38:$A$63,'Parameter Adjustment'!$C$38:$C$63) -> 1430.8151 | M7: Interior Wall framing | N7: {=_xlfn.IFS($B7="Onsite",0%,$B7="Hybrid",'Parameter Adjustment'!J7,$B7="Local",'Parameter Adjustment'!F7,$B7="Hybrid/Local",AVERAGE('Parameter Adjustment'!H7,'Parameter Adjustment'!J7))} -> 0.2 | O7: {=_xlfn.IFS(B7="Onsite",'LA - Site Built'!$D7*(1-$N7),B7="Hybrid",'SLC - Site Built'!$D7*(1-$N7),B7="Local",'LA - Site Built'!$D7*(1-$N7),B7="Hybrid/Local",AVERAGE('SLC - Site Built'!$D7,'LA - Site Built'!$D7)*(1-$N7))} -> 1.494 | P7: {=_xlfn.IFS(B7="Onsite",'LA - Site Built'!$E7*(1-$N7),B7="Hybrid",'SLC - Site Built'!$E7*(1-$N7),B7="Local",'LA - Site Built'!$E7*(1-$N7),B7="Hybrid/Local",AVERAGE('SLC - Site Built'!$E7,'LA - Site Built'!$E7)*(1-$N7))} -> 0.996 | Q7: =R7/R$29 -> 0.011353895 | R7: =SUM(O7:P7) -> 2.49 | S7: {=_xlfn.IFS($B7="Onsite", IF('Parameter Adjustment'!$I7='Parameter Adjustment'!$K7,'Parameter Adjustment'!$I7,"Onsite % Savings Don't Match"),$B7="Hybrid",'Parameter Adjustment'!$K7,$B7="Local",'Parameter Adjustment'!$I7,$B7="Hybrid/Local",'Parameter Adjustment'!$K7)} -> 0.2 | T7: =U7/U$29 -> 0.040256877 | U7: ='NA - Site Built'!I7*(1-S7) -> 6.8108108 | V7: =U7*8 -> 54.486486 | W7: =V7*_xlfn.XLOOKUP(M7,'Parameter Adjustment'!$A$38:$A$63,'Parameter Adjustment'!$C$38:$C$63) -> 1430.8151 | X7: {=_xlfn.IFS(B7="Onsite","California",B7="Hybrid","Utah",B7="Local","California",B7="Hybrid/Local","Utah - California")} -> Utah
A8: Interior Wall sheathing | B8: Hybrid | C8: {=_xlfn.IFS($B8="Onsite",0%,$B8="Hybrid",'Parameter Adjustment'!J8,$B8="Local",'Parameter Adjustment'!H8,$B8="Hybrid/Local",AVERAGE('Parameter Adjustment'!H8,'Parameter Adjustment'!J8))} -> 0.2 | D8: ='SLC - Site Built'!$D8*(1-$C8) -> 1.494 | E8: ='SLC - Site Built'!$E8*(1-$C8) -> 0.996 | F8: =G8/G$29 -> 0.019001106 | G8: =SUM(D8:E8) -> 2.49 | H8: {=_xlfn.IFS($B8="Onsite", IF('Parameter Adjustment'!$I8='Parameter Adjustment'!$K8,'Parameter Adjustment'!$I8,"Onsite % Savings Don't Match"),$B8="Hybrid",'Parameter Adjustment'!$K8,$B8="Local",'Parameter Adjustment'!$I8,$B8="Hybrid/Local",'Parameter Adjustment'!$K8)} -> 0.2 | I8: =J8/$J$29 -> 0.017332095 | J8: ='NA - Site Built'!I8*(1-H8) -> 2.7243243 | K8: =J8*8 -> 21.794595 | L8: =K8*_xlfn.XLOOKUP(A8,'Parameter Adjustment'!$A$38:$A$63,'Parameter Adjustment'!$C$38:$C$63) -> 572.32605 | M8: Interior Wall sheathing | N8: {=_xlfn.IFS($B8="Onsite",0%,$B8="Hybrid",'Parameter Adjustment'!J8,$B8="Local",'Parameter Adjustment'!F8,$B8="Hybrid/Local",AVERAGE('Parameter Adjustment'!H8,'Parameter Adjustment'!J8))} -> 0.2 | O8: {=_xlfn.IFS(B8="Onsite",'LA - Site Built'!$D8*(1-$N8),B8="Hybrid",'SLC - Site Built'!$D8*(1-$N8),B8="Local",'LA - Site Built'!$D8*(1-$N8),B8="Hybrid/Local",AVERAGE('SLC - Site Built'!$D8,'LA - Site Built'!$D8)*(1-$N8))} -> 1.494 | P8: {=_xlfn.IFS(B8="Onsite",'LA - Site Built'!$E8*(1-$N8),B8="Hybrid",'SLC - Site Built'!$E8*(1-$N8),B8="Local",'LA - Site Built'!$E8*(1-$N8),B8="Hybrid/Local",AVERAGE('SLC - Site Built'!$E8,'LA - Site Built'!$E8)*(1-$N8))} -> 0.996 | Q8: =R8/R$29 -> 0.011353895 | R8: =SUM(O8:P8) -> 2.49 | S8: {=_xlfn.IFS($B8="Onsite", IF('Parameter Adjustment'!$I8='Parameter Adjustment'!$K8,'Parameter Adjustment'!$I8,"Onsite % Savings Don't Match"),$B8="Hybrid",'Parameter Adjustment'!$K8,$B8="Local",'Parameter Adjustment'!$I8,$B8="Hybrid/Local",'Parameter Adjustment'!$K8)} -> 0.2 | T8: =U8/U$29 -> 0.016102751 | U8: ='NA - Site Built'!I8*(1-S8) -> 2.7243243 | V8: =U8*8 -> 21.794595 | W8: =V8*_xlfn.XLOOKUP(M8,'Parameter Adjustment'!$A$38:$A$63,'Parameter Adjustment'!$C$38:$C$63) -> 572.32605 | X8: {=_xlfn.IFS(B8="Onsite","California",B8="Hybrid","Utah",B8="Local","California",B8="Hybrid/Local","Utah - California")} -> Utah
A9: Exterior Walls framing | B9: Hybrid | C9: {=_xlfn.IFS($B9="Onsite",0%,$B9="Hybrid",'Parameter Adjustment'!J9,$B9="Local",'Parameter Adjustment'!H9,$B9="Hybrid/Local",AVERAGE('Parameter Adjustment'!H9,'Parameter Adjustment'!J9))} -> 0.2 | D9: ='SLC - Site Built'!$D9*(1-$C9) -> 1.494 | E9: ='SLC - Site Built'!$E9*(1-$C9) -> 0.996 | F9: =G9/G$29 -> 0.019001106 | G9: =SUM(D9:E9) -> 2.49 | H9: {=_xlfn.IFS($B9="Onsite", IF('Parameter Adjustment'!$I9='Parameter Adjustment'!$K9,'Parameter Adjustment'!$I9,"Onsite % Savings Don't Match"),$B9="Hybrid",'Parameter Adjustment'!$K9,$B9="Local",'Parameter Adjustment'!$I9,$B9="Hybrid/Local",'Parameter Adjustment'!$K9)} -> 0.2 | I9: =J9/$J$29 -> 0.098215207 | J9: ='NA - Site Built'!I9*(1-H9) -> 15.437838 | K9: =J9*8 -> 123.5027 | L9: =K9*_xlfn.XLOOKUP(A9,'Parameter Adjustment'!$A$38:$A$63,'Parameter Adjustment'!$C$38:$C$63) -> 3243.181 | M9: Exterior Walls framing | N9: {=_xlfn.IFS($B9="Onsite",0%,$B9="Hybrid",'Parameter Adjustment'!J9,$B9="Local",'Parameter Adjustment'!F9,$B9="Hybrid/Local",AVERAGE('Parameter Adjustment'!H9,'Parameter Adjustment'!J9))} -> 0.2 | O9: {=_xlfn.IFS(B9="Onsite",'LA - Site Built'!$D9*(1-$N9),B9="Hybrid",'SLC - Site Built'!$D9*(1-$N9),B9="Local",'LA - Site Built'!$D9*(1-$N9),B9="Hybrid/Local",AVERAGE('SLC - Site Built'!$D9,'LA - Site Built'!$D9)*(1-$N9))} -> 1.494 | P9: {=_xlfn.IFS(B9="Onsite",'LA - Site Built'!$E9*(1-$N9),B9="Hybrid",'SLC - Site Built'!$E9*(1-$N9),B9="Local",'LA - Site Built'!$E9*(1-$N9),B9="Hybrid/Local",AVERAGE('SLC - Site Built'!$E9,'LA - Site Built'!$E9)*(1-$N9))} -> 0.996 | Q9: =R9/R$29 -> 0.011353895 | R9: =SUM(O9:P9) -> 2.49 | S9: {=_xlfn.IFS($B9="Onsite", IF('Parameter Adjustment'!$I9='Parameter Adjustment'!$K9,'Parameter Adjustment'!$I9,"Onsite % Savings Don't Match"),$B9="Hybrid",'Parameter Adjustment'!$K9,$B9="Local",'Parameter Adjustment'!$I9,$B9="Hybrid/Local",'Parameter Adjustment'!$K9)} -> 0.2 | T9: =U9/U$29 -> 0.091248922 | U9: ='NA - Site Built'!I9*(1-S9) -> 15.437838 | V9: =U9*8 -> 123.5027 | W9: =V9*_xlfn.XLOOKUP(M9,'Parameter Adjustment'!$A$38:$A$63,'Parameter Adjustment'!$C$38:$C$63) -> 3243.181 | X9: {=_xlfn.IFS(B9="Onsite","California",B9="Hybrid","Utah",B9="Local","California",B9="Hybrid/Local","Utah - California")} -> Utah
A10: Exterior Wall sheathing | B10: Hybrid | C10: {=_xlfn.IFS($B10="Onsite",0%,$B10="Hybrid",'Parameter Adjustment'!J10,$B10="Local",'Parameter Adjustment'!H10,$B10="Hybrid/Local",AVERAGE('Parameter Adjustment'!H10,'Parameter Adjustment'!J10))} -> 0.2 | D10: ='SLC - Site Built'!$D10*(1-$C10) -> 1.494 | E10: ='SLC - Site Built'!$E10*(1-$C10) -> 0.996 | F10: =G10/G$29 -> 0.019001106 | G10: =SUM(D10:E10) -> 2.49 | H10: {=_xlfn.IFS($B10="Onsite", IF('Parameter Adjustment'!$I10='Parameter Adjustment'!$K10,'Parameter Adjustment'!$I10,"Onsite % Savings Don't Match"),$B10="Hybrid",'Parameter Adjustment'!$K10,$B10="Local",'Parameter Adjustment'!$I10,$B10="Hybrid/Local",'Parameter Adjustment'!$K10)} -> 0.2 | I10: =J10/$J$29 -> 0.028886826 | J10: ='NA - Site Built'!I10*(1-H10) -> 4.5405405 | K10: =J10*8 -> 36.324324 | L10: =K10*_xlfn.XLOOKUP(A10,'Parameter Adjustment'!$A$38:$A$63,'Parameter Adjustment'!$C$38:$C$63) -> 953.87676 | M10: Exterior Wall sheathing | N10: {=_xlfn.IFS($B10="Onsite",0%,$B10="Hybrid",'Parameter Adjustment'!J10,$B10="Local",'Parameter Adjustment'!F10,$B10="Hybrid/Local",AVERAGE('Parameter Adjustment'!H10,'Parameter Adjustment'!J10))} -> 0.2 | O10: {=_xlfn.IFS(B10="Onsite",'LA - Site Built'!$D10*(1-$N10),B10="Hybrid",'SLC - Site Built'!$D10*(1-$N10),B10="Local",'LA - Site Built'!$D10*(1-$N10),B10="Hybrid/Local",AVERAGE('SLC - Site Built'!$D10,'LA - Site Built'!$D10)*(1-$N10))} -> 1.494 | P10: {=_xlfn.IFS(B10="Onsite",'LA - Site Built'!$E10*(1-$N10),B10="Hybrid",'SLC - Site Built'!$E10*(1-$N10),B10="Local",'LA - Site Built'!$E10*(1-$N10),B10="Hybrid/Local",AVERAGE('SLC - Site Built'!$E10,'LA - Site Built'!$E10)*(1-$N10))} -> 0.996 | Q10: =R10/R$29 -> 0.011353895 | R10: =SUM(O10:P10) -> 2.49 | S10: {=_xlfn.IFS($B10="Onsite", IF('Parameter Adjustment'!$I10='Parameter Adjustment'!$K10,'Parameter Adjustment'!$I10,"Onsite % Savings Don't Match"),$B10="Hybrid",'Parameter Adjustment'!$K10,$B10="Local",'Parameter Adjustment'!$I10,$B10="Hybrid/Local",'Parameter Adjustment'!$K10)} -> 0.2 | T10: =U10/U$29 -> 0.026837918 | U10: ='NA - Site Built'!I10*(1-S10) -> 4.5405405 | V10: =U10*8 -> 36.324324 | W10: =V10*_xlfn.XLOOKUP(M10,'Parameter Adjustment'!$A$38:$A$63,'Parameter Adjustment'!$C$38:$C$63) -> 953.87676 | X10: {=_xlfn.IFS(B10="Onsite","California",B10="Hybrid","Utah",B10="Local","California",B10="Hybrid/Local","Utah - California")} -> Utah
A11: Roof framing | B11: Hybrid | C11: {=_xlfn.IFS($B11="Onsite",0%,$B11="Hybrid",'Parameter Adjustment'!J11,$B11="Local",'Parameter Adjustment'!H11,$B11="Hybrid/Local",AVERAGE('Parameter Adjustment'!H11,'Parameter Adjustment'!J11))} -> 0.2 | D11: ='SLC - Site Built'!$D11*(1-$C11) -> 1.494 | E11: ='SLC - Site Built'!$E11*(1-$C11) -> 0.996 | F11: =G11/G$29 -> 0.019001106 | G11: =SUM(D11:E11) -> 2.49 | H11: {=_xlfn.IFS($B11="Onsite", IF('Parameter Adjustment'!$I11='Parameter Adjustment'!$K11,'Parameter Adjustment'!$I11,"Onsite % Savings Don't Match"),$B11="Hybrid",'Parameter Adjustment'!$K11,$B11="Local",'Parameter Adjustment'!$I11,$B11="Hybrid/Local",'Parameter Adjustment'!$K11)} -> 0.2 | I11: =J11/$J$29 -> 0.034664191 | J11: ='NA - Site Built'!I11*(1-H11) -> 5.4486486 | K11: =J11*8 -> 43.589189 | L11: =K11*_xlfn.XLOOKUP(A11,'Parameter Adjustment'!$A$38:$A$63,'Parameter Adjustment'!$C$38:$C$63) -> 1105.4218 | M11: Roof framing | N11: {=_xlfn.IFS($B11="Onsite",0%,$B11="Hybrid",'Parameter Adjustment'!J11,$B11="Local",'Parameter Adjustment'!F11,$B11="Hybrid/Local",AVERAGE('Parameter Adjustment'!H11,'Parameter Adjustment'!J11))} -> 0.2 | O11: {=_xlfn.IFS(B11="Onsite",'LA - Site Built'!$D11*(1-$N11),B11="Hybrid",'SLC - Site Built'!$D11*(1-$N11),B11="Local",'LA - Site Built'!$D11*(1-$N11),B11="Hybrid/Local",AVERAGE('SLC - Site Built'!$D11,'LA - Site Built'!$D11)*(1-$N11))} -> 1.494 | P11: {=_xlfn.IFS(B11="Onsite",'LA - Site Built'!$E11*(1-$N11),B11="Hybrid",'SLC - Site Built'!$E11*(1-$N11),B11="Local",'LA - Site Built'!$E11*(1-$N11),B11="Hybrid/Local",AVERAGE('SLC - Site Built'!$E11,'LA - Site Built'!$E11)*(1-$N11))} -> 0.996 | Q11: =R11/R$29 -> 0.011353895 | R11: =SUM(O11:P11) -> 2.49 | S11: {=_xlfn.IFS($B11="Onsite", IF('Parameter Adjustment'!$I11='Parameter Adjustment'!$K11,'Parameter Adjustment'!$I11,"Onsite % Savings Don't Match"),$B11="Hybrid",'Parameter Adjustment'!$K11,$B11="Local",'Parameter Adjustment'!$I11,$B11="Hybrid/Local",'Parameter Adjustment'!$K11)} -> 0.2 | T11: =U11/U$29 -> 0.032205502 | U11: ='NA - Site Built'!I11*(1-S11) -> 5.4486486 | V11: =U11*8 -> 43.589189 | W11: =V11*_xlfn.XLOOKUP(M11,'Parameter Adjustment'!$A$38:$A$63,'Parameter Adjustment'!$C$38:$C$63) -> 1105.4218 | X11: {=_xlfn.IFS(B11="Onsite","California",B11="Hybrid","Utah",B11="Local","California",B11="Hybrid/Local","Utah - California")} -> Utah
A12: Roof sheathing and waterproofing | B12: Hybrid | C12: {=_xlfn.IFS($B12="Onsite",0%,$B12="Hybrid",'Parameter Adjustment'!J12,$B12="Local",'Parameter Adjustment'!H12,$B12="Hybrid/Local",AVERAGE('Parameter Adjustment'!H12,'Parameter Adjustment'!J12))} -> 0.2 | D12: ='SLC - Site Built'!$D12*(1-$C12) -> 1.494 | E12: ='SLC - Site Built'!$E12*(1-$C12) -> 0.996 | F12: =G12/G$29 -> 0.019001106 | G12: =SUM(D12:E12) -> 2.49 | H12: {=_xlfn.IFS($B12="Onsite", IF('Parameter Adjustment'!$I12='Parameter Adjustment'!$K12,'Parameter Adjustment'!$I12,"Onsite % Savings Don't Match"),$B12="Hybrid",'Parameter Adjustment'!$K12,$B12="Local",'Parameter Adjustment'!$I12,$B12="Hybrid/Local",'Parameter Adjustment'!$K12)} -> 0.2 | I12: =J12/$J$29 -> 0.028886826 | J12: ='NA - Site Built'!I12*(1-H12) -> 4.5405405 | K12: =J12*8 -> 36.324324 | L12: =K12*_xlfn.XLOOKUP(A12,'Parameter Adjustment'!$A$38:$A$63,'Parameter Adjustment'!$C$38:$C$63) -> 921.18486 | M12: Roof sheathing and waterproofing | N12: {=_xlfn.IFS($B12="Onsite",0%,$B12="Hybrid",'Parameter Adjustment'!J12,$B12="Local",'Parameter Adjustment'!F12,$B12="Hybrid/Local",AVERAGE('Parameter Adjustment'!H12,'Parameter Adjustment'!J12))} -> 0.2 | O12: {=_xlfn.IFS(B12="Onsite",'LA - Site Built'!$D12*(1-$N12),B12="Hybrid",'SLC - Site Built'!$D12*(1-$N12),B12="Local",'LA - Site Built'!$D12*(1-$N12),B12="Hybrid/Local",AVERAGE('SLC - Site Built'!$D12,'LA - Site Built'!$D12)*(1-$N12))} -> 1.494 | P12: {=_xlfn.IFS(B12="Onsite",'LA - Site Built'!$E12*(1-$N12),B12="Hybrid",'SLC - Site Built'!$E12*(1-$N12),B12="Local",'LA - Site Built'!$E12*(1-$N12),B12="Hybrid/Local",AVERAGE('SLC - Site Built'!$E12,'LA - Site Built'!$E12)*(1-$N12))} -> 0.996 | Q12: =R12/R$29 -> 0.011353895 | R12: =SUM(O12:P12) -> 2.49 | S12: {=_xlfn.IFS($B12="Onsite", IF('Parameter Adjustment'!$I12='Parameter Adjustment'!$K12,'Parameter Adjustment'!$I12,"Onsite % Savings Don't Match"),$B12="Hybrid",'Parameter Adjustment'!$K12,$B12="Local",'Parameter Adjustment'!$I12,$B12="Hybrid/Local",'Parameter Adjustment'!$K12)} -> 0.2 | T12: =U12/U$29 -> 0.026837918 | U12: ='NA - Site Built'!I12*(1-S12) -> 4.5405405 | V12: =U12*8 -> 36.324324 | W12: =V12*_xlfn.XLOOKUP(M12,'Parameter Adjustment'!$A$38:$A$63,'Parameter Adjustment'!$C$38:$C$63) -> 921.18486 | X12: {=_xlfn.IFS(B12="Onsite","California",B12="Hybrid","Utah",B12="Local","California",B12="Hybrid/Local","Utah - California")} -> Utah
A13: Mechanical Rough In | B13: Hybrid | C13: {=_xlfn.IFS($B13="Onsite",0%,$B13="Hybrid",'Parameter Adjustment'!J13,$B13="Local",'Parameter Adjustment'!H13,$B13="Hybrid/Local",AVERAGE('Parameter Adjustment'!H13,'Parameter Adjustment'!J13))} -> 0.2 | D13: ='SLC - Site Built'!$D13*(1-$C13) -> 2.268 | E13: ='SLC - Site Built'!$E13*(1-$C13) -> 5.292 | F13: =G13/G$29 -> 0.057690106 | G13: =SUM(D13:E13) -> 7.56 | H13: {=_xlfn.IFS($B13="Onsite", IF('Parameter Adjustment'!$I13='Parameter Adjustment'!$K13,'Parameter Adjustment'!$I13,"Onsite % Savings Don't Match"),$B13="Hybrid",'Parameter Adjustment'!$K13,$B13="Local",'Parameter Adjustment'!$I13,$B13="Hybrid/Local",'Parameter Adjustment'!$K13)} -> 0.2 | I13: =J13/$J$29 -> 0.049107603 | J13: ='NA - Site Built'!I13*(1-H13) -> 7.7189189 | K13: =J13*8 -> 61.751351 | L13: =K13*_xlfn.XLOOKUP(A13,'Parameter Adjustment'!$A$38:$A$63,'Parameter Adjustment'!$C$38:$C$63) -> 1759.9135 | M13: Mechanical Rough In | N13: {=_xlfn.IFS($B13="Onsite",0%,$B13="Hybrid",'Parameter Adjustment'!J13,$B13="Local",'Parameter Adjustment'!F13,$B13="Hybrid/Local",AVERAGE('Parameter Adjustment'!H13,'Parameter Adjustment'!J13))} -> 0.2 | O13: {=_xlfn.IFS(B13="Onsite",'LA - Site Built'!$D13*(1-$N13),B13="Hybrid",'SLC - Site Built'!$D13*(1-$N13),B13="Local",'LA - Site Built'!$D13*(1-$N13),B13="Hybrid/Local",AVERAGE('SLC - Site Built'!$D13,'LA - Site Built'!$D13)*(1-$N13))} -> 2.268 | P13: {=_xlfn.IFS(B13="Onsite",'LA - Site Built'!$E13*(1-$N13),B13="Hybrid",'SLC - Site Built'!$E13*(1-$N13),B13="Local",'LA - Site Built'!$E13*(1-$N13),B13="Hybrid/Local",AVERAGE('SLC - Site Built'!$E13,'LA - Site Built'!$E13)*(1-$N13))} -> 5.292 | Q13: =R13/R$29 -> 0.034472067 | R13: =SUM(O13:P13) -> 7.56 | S13: {=_xlfn.IFS($B13="Onsite", IF('Parameter Adjustment'!$I13='Parameter Adjustment'!$K13,'Parameter Adjustment'!$I13,"Onsite % Savings Don't Match"),$B13="Hybrid",'Parameter Adjustment'!$K13,$B13="Local",'Parameter Adjustment'!$I13,$B13="Hybrid/Local",'Parameter Adjustment'!$K13)} -> 0.2 | T13: =U13/U$29 -> 0.045624461 | U13: ='NA - Site Built'!I13*(1-S13) -> 7.7189189 | V13: =U13*8 -> 61.751351 | W13: =V13*_xlfn.XLOOKUP(M13,'Parameter Adjustment'!$A$38:$A$63,'Parameter Adjustment'!$C$38:$C$63) -> 1759.9135 | X13: {=_xlfn.IFS(B13="Onsite","California",B13="Hybrid","Utah",B13="Local","California",B13="Hybrid/Local","Utah - California")} -> Utah
A14: Electrical Rough In | B14: Hybrid | C14: {=_xlfn.IFS($B14="Onsite",0%,$B14="Hybrid",'Parameter Adjustment'!J14,$B14="Local",'Parameter Adjustment'!H14,$B14="Hybrid/Local",AVERAGE('Parameter Adjustment'!H14,'Parameter Adjustment'!J14))} -> 0.2 | D14: ='SLC - Site Built'!$D14*(1-$C14) -> 2.304 | E14: ='SLC - Site Built'!$E14*(1-$C14) -> 5.376 | F14: =G14/G$29 -> 0.058605822 | G14: =SUM(D14:E14) -> 7.68 | H14: {=_xlfn.IFS($B14="Onsite", IF('Parameter Adjustment'!$I14='Parameter Adjustment'!$K14,'Parameter Adjustment'!$I14,"Onsite % Savings Don't Match"),$B14="Hybrid",'Parameter Adjustment'!$K14,$B14="Local",'Parameter Adjustment'!$I14,$B14="Hybrid/Local",'Parameter Adjustment'!$K14)} -> 0.2 | I14: =J14/$J$29 -> 0.031775508 | J14: ='NA - Site Built'!I14*(1-H14) -> 4.9945946 | K14: =J14*8 -> 39.956757 | L14: =K14*_xlfn.XLOOKUP(A14,'Parameter Adjustment'!$A$38:$A$63,'Parameter Adjustment'!$C$38:$C$63) -> 1210.6897 | M14: Electrical Rough In | N14: {=_xlfn.IFS($B14="Onsite",0%,$B14="Hybrid",'Parameter Adjustment'!J14,$B14="Local",'Parameter Adjustment'!F14,$B14="Hybrid/Local",AVERAGE('Parameter Adjustment'!H14,'Parameter Adjustment'!J14))} -> 0.2 | O14: {=_xlfn.IFS(B14="Onsite",'LA - Site Built'!$D14*(1-$N14),B14="Hybrid",'SLC - Site Built'!$D14*(1-$N14),B14="Local",'LA - Site Built'!$D14*(1-$N14),B14="Hybrid/Local",AVERAGE('SLC - Site Built'!$D14,'LA - Site Built'!$D14)*(1-$N14))} -> 2.304 | P14: {=_xlfn.IFS(B14="Onsite",'LA - Site Built'!$E14*(1-$N14),B14="Hybrid",'SLC - Site Built'!$E14*(1-$N14),B14="Local",'LA - Site Built'!$E14*(1-$N14),B14="Hybrid/Local",AVERAGE('SLC - Site Built'!$E14,'LA - Site Built'!$E14)*(1-$N14))} -> 5.376 | Q14: =R14/R$29 -> 0.035019242 | R14: =SUM(O14:P14) -> 7.68 | S14: {=_xlfn.IFS($B14="Onsite", IF('Parameter Adjustment'!$I14='Parameter Adjustment'!$K14,'Parameter Adjustment'!$I14,"Onsite % Savings Don't Match"),$B14="Hybrid",'Parameter Adjustment'!$K14,$B14="Local",'Parameter Adjustment'!$I14,$B14="Hybrid/Local",'Parameter Adjustment'!$K14)} -> 0.2 | T14: =U14/U$29 -> 0.02952171 | U14: ='NA - Site Built'!I14*(1-S14) -> 4.9945946 | V14: =U14*8 -> 39.956757 | W14: =V14*_xlfn.XLOOKUP(M14,'Parameter Adjustment'!$A$38:$A$63,'Parameter Adjustment'!$C$38:$C$63) -> 1210.6897 | X14: {=_xlfn.IFS(B14="Onsite","California",B14="Hybrid","Utah",B14="Local","California",B14="Hybrid/Local","Utah - California")} -> Utah
A15: Plumbing Rough In | B15: Hybrid | C15: {=_xlfn.IFS($B15="Onsite",0%,$B15="Hybrid",'Parameter Adjustment'!J15,$B15="Local",'Parameter Adjustment'!H15,$B15="Hybrid/Local",AVERAGE('Parameter Adjustment'!H15,'Parameter Adjustment'!J15))} -> 0.2 | D15: ='SLC - Site Built'!$D15*(1-$C15) -> 2.268 | E15: ='SLC - Site Built'!$E15*(1-$C15) -> 5.292 | F15: =G15/G$29 -> 0.057690106 | G15: =SUM(D15:E15) -> 7.56 | H15: {=_xlfn.IFS($B15="Onsite", IF('Parameter Adjustment'!$I15='Parameter Adjustment'!$K15,'Parameter Adjustment'!$I15,"Onsite % Savings Don't Match"),$B15="Hybrid",'Parameter Adjustment'!$K15,$B15="Local",'Parameter Adjustment'!$I15,$B15="Hybrid/Local",'Parameter Adjustment'!$K15)} -> 0.2 | I15: =J15/$J$29 -> 0.046218921 | J15: ='NA - Site Built'!I15*(1-H15) -> 7.2648649 | K15: =J15*8 -> 58.118919 | L15: =K15*_xlfn.XLOOKUP(A15,'Parameter Adjustment'!$A$38:$A$63,'Parameter Adjustment'!$C$38:$C$63) -> 1749.3795 | M15: Plumbing Rough In | N15: {=_xlfn.IFS($B15="Onsite",0%,$B15="Hybrid",'Parameter Adjustment'!J15,$B15="Local",'Parameter Adjustment'!F15,$B15="Hybrid/Local",AVERAGE('Parameter Adjustment'!H15,'Parameter Adjustment'!J15))} -> 0.2 | O15: {=_xlfn.IFS(B15="Onsite",'LA - Site Built'!$D15*(1-$N15),B15="Hybrid",'SLC - Site Built'!$D15*(1-$N15),B15="Local",'LA - Site Built'!$D15*(1-$N15),B15="Hybrid/Local",AVERAGE('SLC - Site Built'!$D15,'LA - Site Built'!$D15)*(1-$N15))} -> 2.268 | P15: {=_xlfn.IFS(B15="Onsite",'LA - Site Built'!$E15*(1-$N15),B15="Hybrid",'SLC - Site Built'!$E15*(1-$N15),B15="Local",'LA - Site Built'!$E15*(1-$N15),B15="Hybrid/Local",AVERAGE('SLC - Site Built'!$E15,'LA - Site Built'!$E15)*(1-$N15))} -> 5.292 | Q15: =R15/R$29 -> 0.034472067 | R15: =SUM(O15:P15) -> 7.56 | S15: {=_xlfn.IFS($B15="Onsite", IF('Parameter Adjustment'!$I15='Parameter Adjustment'!$K15,'Parameter Adjustment'!$I15,"Onsite % Savings Don't Match"),$B15="Hybrid",'Parameter Adjustment'!$K15,$B15="Local",'Parameter Adjustment'!$I15,$B15="Hybrid/Local",'Parameter Adjustment'!$K15)} -> 0.2 | T15: =U15/U$29 -> 0.042940669 | U15: ='NA - Site Built'!I15*(1-S15) -> 7.2648649 | V15: =U15*8 -> 58.118919 | W15: =V15*_xlfn.XLOOKUP(M15,'Parameter Adjustment'!$A$38:$A$63,'Parameter Adjustment'!$C$38:$C$63) -> 1749.3795 | X15: {=_xlfn.IFS(B15="Onsite","California",B15="Hybrid","Utah",B15="Local","California",B15="Hybrid/Local","Utah - California")} -> Utah
A16: Insulation | B16: Hybrid | C16: {=_xlfn.IFS($B16="Onsite",0%,$B16="Hybrid",'Parameter Adjustment'!J16,$B16="Local",'Parameter Adjustment'!H16,$B16="Hybrid/Local",AVERAGE('Parameter Adjustment'!H16,'Parameter Adjustment'!J16))} -> 0.2 | D16: ='SLC - Site Built'!$D16*(1-$C16) -> 1.152 | E16: ='SLC - Site Built'!$E16*(1-$C16) -> 0.768 | F16: =G16/G$29 -> 0.014651456 | G16: =SUM(D16:E16) -> 1.92 | H16: {=_xlfn.IFS($B16="Onsite", IF('Parameter Adjustment'!$I16='Parameter Adjustment'!$K16,'Parameter Adjustment'!$I16,"Onsite % Savings Don't Match"),$B16="Hybrid",'Parameter Adjustment'!$K16,$B16="Local",'Parameter Adjustment'!$I16,$B16="Hybrid/Local",'Parameter Adjustment'!$K16)} -> 0.2 | I16: =J16/$J$29 -> 0.034664191 | J16: ='NA - Site Built'!I16*(1-H16) -> 5.4486486 | K16: =J16*8 -> 43.589189 | L16: =K16*_xlfn.XLOOKUP(A16,'Parameter Adjustment'!$A$38:$A$63,'Parameter Adjustment'!$C$38:$C$63) -> 979.88497 | M16: Insulation | N16: {=_xlfn.IFS($B16="Onsite",0%,$B16="Hybrid",'Parameter Adjustment'!J16,$B16="Local",'Parameter Adjustment'!F16,$B16="Hybrid/Local",AVERAGE('Parameter Adjustment'!H16,'Parameter Adjustment'!J16))} -> 0.2 | O16: {=_xlfn.IFS(B16="Onsite",'LA - Site Built'!$D16*(1-$N16),B16="Hybrid",'SLC - Site Built'!$D16*(1-$N16),B16="Local",'LA - Site Built'!$D16*(1-$N16),B16="Hybrid/Local",AVERAGE('SLC - Site Built'!$D16,'LA - Site Built'!$D16)*(1-$N16))} -> 1.152 | P16: {=_xlfn.IFS(B16="Onsite",'LA - Site Built'!$E16*(1-$N16),B16="Hybrid",'SLC - Site Built'!$E16*(1-$N16),B16="Local",'LA - Site Built'!$E16*(1-$N16),B16="Hybrid/Local",AVERAGE('SLC - Site Built'!$E16,'LA - Site Built'!$E16)*(1-$N16))} -> 0.768 | Q16: =R16/R$29 -> 0.0087548106 | R16: =SUM(O16:P16) -> 1.92 | S16: {=_xlfn.IFS($B16="Onsite", IF('Parameter Adjustment'!$I16='Parameter Adjustment'!$K16,'Parameter Adjustment'!$I16,"Onsite % Savings Don't Match"),$B16="Hybrid",'Parameter Adjustment'!$K16,$B16="Local",'Parameter Adjustment'!$I16,$B16="Hybrid/Local",'Parameter Adjustment'!$K16)} -> 0.2 | T16: =U16/U$29 -> 0.032205502 | U16: ='NA - Site Built'!I16*(1-S16) -> 5.4486486 | V16: =U16*8 -> 43.589189 | W16: =V16*_xlfn.XLOOKUP(M16,'Parameter Adjustment'!$A$38:$A$63,'Parameter Adjustment'!$C$38:$C$63) -> 979.88497 | X16: {=_xlfn.IFS(B16="Onsite","California",B16="Hybrid","Utah",B16="Local","California",B16="Hybrid/Local","Utah - California")} -> Utah
... A25: Exterior Roof Finishing | B25: Local | C25: {=_xlfn.IFS($B25="Onsite",0%,$B25="Hybrid",'Parameter Adjustment'!J25,$B25="Local",'Parameter Adjustment'!H25,$B25="Hybrid/Local",AVERAGE('Parameter Adjustment'!H25,'Parameter Adjustment'!J25))} -> 0.15 | D25: ='SLC - Site Built'!$D25*(1-$C25) -> 2.9835 | E25: ='SLC - Site Built'!$E25*(1-$C25) -> 1.989 | F25: =G25/G$29 -> 0.037944981 | G25: =SUM(D25:E25) -> 4.9725 | H25: {=_xlfn.IFS($B25="Onsite", IF('Parameter Adjustment'!$I25='Parameter Adjustment'!$K25,'Parameter Adjustment'!$I25,"Onsite % Savings Don't Match"),$B25="Hybrid",'Parameter Adjustment'!$K25,$B25="Local",'Parameter Adjustment'!$I25,$B25="Hybrid/Local",'Parameter Adjustment'!$K25)} -> 0.2 | I25: =J25/$J$29 -> 0.028886826 | J25: ='NA - Site Built'!I25*(1-H25) -> 4.5405405 | K25: =J25*8 -> 36.324324 | L25: =K25*_xlfn.XLOOKUP(A25,'Parameter Adjustment'!$A$38:$A$63,'Parameter Adjustment'!$C$38:$C$63) -> 921.18486 | M25: Exterior Roof Finishing | N25: {=_xlfn.IFS($B25="Onsite",0%,$B25="Hybrid",'Parameter Adjustment'!J25,$B25="Local",'Parameter Adjustment'!F25,$B25="Hybrid/Local",AVERAGE('Parameter Adjustment'!H25,'Parameter Adjustment'!J25))} -> 0.1 | O25: {=_xlfn.IFS(B25="Onsite",'LA - Site Built'!$D25*(1-$N25),B25="Hybrid",'SLC - Site Built'!$D25*(1-$N25),B25="Local",'LA - Site Built'!$D25*(1-$N25),B25="Hybrid/Local",AVERAGE('SLC - Site Built'!$D25,'LA - Site Built'!$D25)*(1-$N25))} -> 6.7392 | P25: {=_xlfn.IFS(B25="Onsite",'LA - Site Built'!$E25*(1-$N25),B25="Hybrid",'SLC - Site Built'!$E25*(1-$N25),B25="Local",'LA - Site Built'!$E25*(1-$N25),B25="Hybrid/Local",AVERAGE('SLC - Site Built'!$E25,'LA - Site Built'!$E25)*(1-$N25))} -> 4.4928 | Q25: =R25/R$29 -> 0.051215642 | R25: =SUM(O25:P25) -> 11.232 | S25: {=_xlfn.IFS($B25="Onsite", IF('Parameter Adjustment'!$I25='Parameter Adjustment'!$K25,'Parameter Adjustment'!$I25,"Onsite % Savings Don't Match"),$B25="Hybrid",'Parameter Adjustment'!$K25,$B25="Local",'Parameter Adjustment'!$I25,$B25="Hybrid/Local",'Parameter Adjustment'!$K25)} -> 0.2 | T25: =U25/U$29 -> 0.026837918 | U25: ='NA - Site Built'!I25*(1-S25) -> 4.5405405 | V25: =U25*8 -> 36.324324 | W25: =V25*_xlfn.XLOOKUP(M25,'Parameter Adjustment'!$A$38:$A$63,'Parameter Adjustment'!$C$38:$C$63) -> 921.18486 | X25: {=_xlfn.IFS(B25="Onsite","California",B25="Hybrid","Utah",B25="Local","California",B25="Hybrid/Local","Utah - California")} -> California
A26: Transportation | D26: 0 | E26: {=(_xlfn.IFS(AND(ISNUMBER(SEARCH("Modular", C1)), ISNUMBER(SEARCH("SLC", C1))), 'Parameter Adjustment'!$S$3*'Parameter Adjustment'!$T$3,AND(ISNUMBER(SEARCH("Modular", C1)), ISNUMBER(SEARCH("Los Angeles", C1))),'Parameter Adjustment'!$S$5*'Parameter Adjustment'!$T$5,AND(ISNUMBER(SEARCH("Hybrid", C1)), ISNUMBER(SEARCH("SLC", C1))),'Parameter Adjustment'!$S$10*'Parameter Adjustment'!$T$10+'Parameter Adjustment'!$S$3*'Parameter Adjustment'!$T$3,AND(ISNUMBER(SEARCH("Hybrid", C1)), ISNUMBER(SEARCH("LA", C1))),'Parameter Adjustment'!$S$12*'Parameter Adjustment'!$T$12+'Parameter Adjustment'!$S$4*'Parameter Adjustment'!$T$4))/IF('Parameter Adjustment'!Z2="1,000 square-foot home",1,1000)} -> 0.7 | F26: =G26/G$29 -> 0.0053416765 | G26: =SUM(D26:E26) -> 0.7 | H26: 0 | I26: =J26/$J$29 -> 0.019085938 | J26: 3 | K26: =J26*8 -> 24 | L26: =G26 -> 0.7 | M26: Transportation | P26: {=(_xlfn.IFS(AND(ISNUMBER(SEARCH("Modular", M1)), ISNUMBER(SEARCH("SLC", M1))), 'Parameter Adjustment'!$S$3*'Parameter Adjustment'!$T$3,AND(ISNUMBER(SEARCH("Modular", M1)), ISNUMBER(SEARCH("Los Angeles", M1))),'Parameter Adjustment'!$S$5*'Parameter Adjustment'!$T$5,AND(ISNUMBER(SEARCH("Hybrid", M1)), ISNUMBER(SEARCH("SLC", M1))),'Parameter Adjustment'!$S$10*'Parameter Adjustment'!$T$10+'Parameter Adjustment'!$S$3*'Parameter Adjustment'!$T$3,AND(ISNUMBER(SEARCH("Hybrid", M1)), ISNUMBER(SEARCH("LA", M1))),'Parameter Adjustment'!$S$12*'Parameter Adjustment'!$T$12+'Parameter Adjustment'!$S$4*'Parameter Adjustment'!$T$4))/IF('Parameter Adjustment'!Z2="1,000 square-foot home",1,1000)} -> 3.8 | Q26: =R26/R$29 -> 0.017327229 | R26: =SUM(O26:P26) -> 3.8 | S26: 0 | T26: =U26/U$29 -> 0.08866098 | U26: 15 | V26: =U26*8 -> 120 | W26: =R26 -> 3.8 | X26: Utah - California
A27: On-site Installation | B27: Onsite | C27: {=_xlfn.IFS($B27="Onsite",0%,$B27="Hybrid",'Parameter Adjustment'!J27,$B27="Local",'Parameter Adjustment'!H27,$B27="Hybrid/Local",AVERAGE('Parameter Adjustment'!H27,'Parameter Adjustment'!J27))} -> 0 | E27: ='Parameter Adjustment'!X2*'Parameter Adjustment'!X3/IF('Parameter Adjustment'!Z2="1,000 square-foot home",1,1000) -> 10 | F27: =G27/G$29 -> 0.076309665 | G27: =SUM(D27:E27) -> 10 | H27: {=_xlfn.IFS($B27="Onsite", IF('Parameter Adjustment'!$I27='Parameter Adjustment'!$K27,'Parameter Adjustment'!$I27,"Onsite % Savings Don't Match"),$B27="Hybrid",'Parameter Adjustment'!$K27,$B27="Local",'Parameter Adjustment'!$I27,$B27="Hybrid/Local",'Parameter Adjustment'!$K27)} -> 0 | I27: =J27/$J$29 -> 0.19085938 | J27: 30 | K27: =J27*8 -> 240 | L27: =K27*_xlfn.XLOOKUP("Assembly",'Parameter Adjustment'!$A$38:$A$63,'Parameter Adjustment'!$C$38:$C$63) -> 5510.4 | M27: On-site Installation | N27: {=_xlfn.IFS($B27="Onsite",0%,$B27="Hybrid",'Parameter Adjustment'!J27,$B27="Local",'Parameter Adjustment'!F27,$B27="Hybrid/Local",AVERAGE('Parameter Adjustment'!H27,'Parameter Adjustment'!J27))} -> 0 | P27: ='Parameter Adjustment'!X2*'Parameter Adjustment'!X3/IF('Parameter Adjustment'!Z2="1,000 square-foot home",1,1000) -> 10 | Q27: =R27/R$29 -> 0.045597972 | R27: =SUM(O27:P27) -> 10 | S27: {=_xlfn.IFS($B27="Onsite", IF('Parameter Adjustment'!$I27='Parameter Adjustment'!$K27,'Parameter Adjustment'!$I27,"Onsite % Savings Don't Match"),$B27="Hybrid",'Parameter Adjustment'!$K27,$B27="Local",'Parameter Adjustment'!$I27,$B27="Hybrid/Local",'Parameter Adjustment'!$K27)} -> 0 | T27: =U27/U$29 -> 0.17732196 | U27: 30 | V27: =U27*8 -> 240 | W27: =V27*_xlfn.XLOOKUP("Assembly",'Parameter Adjustment'!$A$38:$A$63,'Parameter Adjustment'!$B$38:$B$63) -> 7632 | X27: {=_xlfn.IFS(B27="Onsite","California",B27="Hybrid","Utah",B27="Local","California",B27="Hybrid/Local","Utah - California")} -> California
